Workbook
Name Slicer_Gender: #N/A
Name Slicer_Monthly_income: #N/A

Sheet Project_Summary
A1: Fuel Consumption Analysis - Phaltan Survey 2025
A2: Primary Survey | Phaltan, Maharashtra | December 2025
B4: 567 | E4: =Clean_Data_Summary!B27 -> 3336.4427 | H4: =Per_Capita_Expenses!I3 -> 750.05726
B7: Total Respondents | E7: Avg Monthly Fuel(₹) | H7: Avg Per Capita(₹)
A11: Key Results Table
A13: Metric | B13: Value | C13: Interpretation
A14: Pearson Correlation (Income vs Fuel) | B14: =Correlation!K2 -> 0.51836596 | C14: Moderate positive relationship
A15: ANOVA F-statistic (Vehicle Owernship) | B15: =ANOVA1!M33 -> 150.81051 | C15: Highly significant
A16: ANOVA p-value (Vehicle Ownership) | B16: =ANOVA1!N33 -> 9.9800412e-72 | C16: Vehicle ownership drives fuel use
A17: ANOVA F-statistic (Income Groups) | B17: =ANOVA2!M18 -> 41.785378 | C17: Significant across income groups
A18: ANOVA p-value (Income Groups) | B18: =ANOVA2!N18 -> 1.3889177e-36 | C18: Income significantly affects fuel
A19: T-test (Gender difference) | B19: ='T-test'!E2 -> 5.2783151e-30 | C19: Males spend 3x more than females
A20: Multiple Regression Adj.R2 | B20: =Regression1!H6 -> 0.51758499 | C20: 4 variables explain 51.76% variance
A21: Effect Size ῃ2 (Vehicle Ownership) | B21: =ANOVA1!J40 -> 0.44555593 | C21: Large effect
A22: Effect Size ῃ2 (Income Groups) | B22: =ANOVA2!M25 -> 0.27135939 | C22: Moderate -large effect
A23: Male avg fuel expense | B23: ='T-test'!F5 -> 4730.6187 | C23: 4731
A24: Female avg Fuel expense | B24: ='T-test'!F6 -> 1530.2227 | C24: 1530
A26: Sheet Index
A28: Sheet Name | B28: Contents
A29: Form Responses | B29: Raw survey data - 597 original responses
A30: clean_data | B30: Cleaned dataset - 568 rows, 30 columns
A31: Clean_Data_Summary | B31: Column-wise summary of cleaned data ( min, max, mean, median, mode, count)
A32: Outlier_detection | B32: IQR method - 35 high outliers identified
A33: Descriptive_Statistics | B33: Mean, median, SD, min, max, skewness fpr 5 variables
A34: Pie_Chart | B34: Distribution of vehicle types ownership (percentage-wise)
A35: Box_plot | B35: Box plot visualization for detecting outliers and data spread
A36: Pivot_Charts | B36: Interactive Charts summarizing fuel usage across categories
A37: Fuel_Data_Used_Avg_Fuel(l) | B37: Avg fuel consumption (liters) by vehicle type
A38: Avg_Fuel(LMonth) | B38: Pivot table for Avg fuel consumption (liters) by vehicle type
A39: Avg_Fuel_Expense | B39: Avg fuel expenditure analysis
... A53: Dashboard | B53: Interactive dashboard with KPI cards and slicers

Sheet Form Responses 1
A1: Timestamp | B1: 1) Name | C1: 2) Age (eg. 21,22,18,etc) | D1: 3) Gender | E1: 4) Area of residence | F1: 5) occupation | G1: 6) Monthly income | H1: 7) Total family members | I1: 8) No. of vehicles in family | J1: 9) Type of vehicle | K1: 10) Type of fuel required for it. [Bike ] | L1: 10) Type of fuel required for it. [Scooty ] | M1: 10) Type of fuel required for it. [Car ] | N1: 10) Type of fuel required for it. [Commercial ] | O1: 10) Type of fuel required for it. [electric vehicle ] | P1: A] Bike details 11) Age of bike | Q1: 12) Daily distance travelled by bike | R1: 13)Fuel required monthly | S1: B] Scooty details 14)Age of Scooty | T1: 15)Daily distance travelled by Scooty | U1: 16)Fuel required monthly | V1: C] Car details 17)Age of Car | W1: 18)Daily distance travelled by Car | X1: 19)Fuel required monthly | Y1: D. Commercial Vehicle Details 20)Age | Z1: 21)Daily distance travelled | AA1: 22) Fuel required monthly | AB1: E. Electric Vehicle Details 23)Electricity consumption (kWh/month) | AC1: 24)Daily distance travelled | AD1: 25)Age of EV | AE1: 26)Total monthly fuel expense of your household (₹) | AF1: 27)Preferred fuel station brand | AG1: 28) Reason for choosing this brand | AH1: 29)Distance from home to workplace/college (km) | AI1: 30)Main purpose of using your vehicle | AJ1: 31)How often do you use public transport? | AK1: 32) Which type of public transport do you use? | AL1: 33)Would you consider buying an Electric Vehicle (EV)? | AM1: 34)If YES or MAYBE, what is your reason? | AN1: 35)If NO, what is your reason? | AO1: 35. Any suggestions about fuel rates or transportation ?
A2: 45945.517 | B2: Ankita Baburao Gawade | C2: 19 | D2: Female | E2: Rural | F2: Agriculture | G2: 30,000-50,000 | H2: 5 | I2: 1 | J2: bikes | K2: Petrol | P2: 20litre | S2: Indian oil | U2: 10km | X2: 18 | AA2: Work | AD2: 10km | AE2: private | AF2: Petrol | AG2: Cng | AH2: 3 | AI2: Daily | AJ2: Bike | AK2: Good
A3: 45945.518 | B3: Apeksha Sachin Ahiwale | C3: 20 | D3: Female | E3: Urban | F3: Student | G3: 50,000-70,000 | H3: 4 | I3: 2 | J3: bikes, Scooty | K3: Petrol | P3: 500 - 600 rupees | S3: Bharat petroleum | T3: Bharat petroleum | U3: 50km | V3: 20km | X3: 34 | Y3: 25 | AA3: Work | AB3: School / Colleges | AD3: 20km | AF3: Petrol | AG3: No | AH3: 4 | AI3: Often | AJ3: Scooty | AK3: Should be decreased.... the rate must be less so people can easily transport
A4: 45959.476 | B4: Rahul Patil | C4: 27 | D4: Male | E4: Urban | F4: private sector | G4: 50,000-70,000 | H4: 4 | I4: 2 | J4: bikes, Four wheeler | K4: Petrol | P4: 15 L | R4: 45 L | S4: Indian oil | U4: 10 KM | W4: 20 KM | X4: 4 YEAR | Z4: 3 YEAR | AA4: Work | AC4: Travel | AD4: 8 KM | AE4: private | AF4: Petrol | AG4: yes | AH4: 2 | AI4: Rarely | AJ4: Bike | AK4: “Government should reduce petrol tax.”
A5: 45959.485 | B5: Savita Kale | C5: 39 | D5: Female | E5: Rural | F5: Agriculture | G5: 10,000-30,000 | H5: 5 | I5: 1 | J5: bikes | K5: Petrol | P5: 55 | S5: Bharat petroleum | U5: 6 KM | X5: 6 YEARS | AA5: Market and field work | AD5: 5 KM | AE5: private | AF5: petrol | AG5: no | AH5: 1 | AI5: Weekly | AJ5: bike | AK5: petrol rate should be 80rs
A6: 45959.512 | B6: Shivani | C6: 21 | D6: Female | E6: Rural | F6: Student | G6: 50,000-70,000 | H6: 6 | I6: 4 | J6: Scooty | T6: Indian oil | V6: 10 km | X6: 7 years | AB6: School / Colleges | AD6: 3 km | AE6: private | AF6: Scooty | AG6: No | AH6: 5 | AI6: Rarely | AJ6: Scooty | AK6: Concession for women
A7: 45959.518 | B7: Siddhant kumbhar | C7: 20 | D7: Male | E7: Rural | F7: College student | G7: 70,000-1,00,000 | H7: 4 | I7: 2 | J7: bikes, Four wheeler | K7: Petrol | P7: 15 L | R7: 10 L | S7: Indian oil | U7: 9 km | W7: 7 km | X7: 15 years | Z7: 8 years | AA7: School / Colleges | AC7: Travel | AD7: 3 km | AE7: private | AF7: Petrol | AG7: No | AH7: 2 | AI7: Rarely | AJ7: Bike | AK7: Lower the rate of petrol
A8: 45959.523 | B8: Nikita Rajpurohit | C8: 21 | D8: Female | E8: Urban | F8: Student | G8: 70,000-1,00,000 | H8: 5 | I8: 1 | J8: Scooty | T8: Indian oil | V8: 3 km | Y8: 4.5 years | AB8: School / Colleges | AD8: 2 km | AE8: private | AF8: Scooty | AG8: No | AH8: 3 | AI8: Rarely | AJ8: Scooty | AK8: Rates are fine but petrol should be of good quality
A9: 45959.527 | B9: Tejashree Bankar | C9: 21 | D9: Female | E9: Rural | F9: Student | G9: 50,000-70,000 | H9: 6 | I9: 1 | J9: bikes | K9: Petrol | P9: 30 L | S9: Indian oil | U9: 30 km | X9: 13 years | AA9: Work | AD9: 13 km | AE9: private | AF9: Bike | AG9: No | AH9: 3 | AI9: Often | AJ9: Bike | AK9: Rate should be less
A10: 45959.53 | B10: Suhani balip | C10: 21 | D10: Female | E10: Rural | F10: Student | G10: 70,000-1,00,000 | H10: 4 | I10: 3 | J10: Scooty | T10: Indian oil | V10: 30 km | Y10: 2 years | AB10: School / Colleges | AD10: 13 km | AE10: private | AF10: Scooty | AG10: No | AH10: 3 | AI10: Sometimes | AJ10: Scooty | AK10: Should be less
A11: 45959.533 | B11: Ankita Gaikwad | C11: 21 | D11: Female | E11: Rural | F11: Student | G11: 50,000-70,000 | H11: 5 | I11: 1 | J11: bikes | K11: Petrol | P11: 15 L | S11: Indian oil | U11: 10 km | X11: 20 years | AA11: School / Colleges | AD11: 3 km | AE11: private | AF11: Petrol | AG11: Yes | AH11: 2 | AI11: Weekly | AJ11: Bike | AK11: Rate should be minimised
A12: 45974.821 | B12: Subhash Jadhav | C12: 55 | D12: Male | E12: Rural | F12: Government Sector | G12: 30,000-50,000 | H12: 6 | I12: 1 | J12: bikes | K12: Petrol | P12: 15 liter | S12: Indian oil | U12: 40 km | X12: 14 years | AA12: Work | AD12: 10 km | AE12: private | AF12: Petrol | AG12: No | AH12: 1 | AI12: Often | AJ12: Bike
A13: 45976.845 | B13: Dipti sanjay shirtode | C13: 21 | D13: Female | F13: Housewife | H13: 3 | I13: 1 | J13: bikes | K13: Petrol | P13: 5000 | R13: 5000 | S13: Indian oil | T13: Indian oil | U13: 15km | V13: 15 km | W13: 15 km | X13: 5year | Y13: 6year | Z13: 4 years | AA13: Work | AB13: Work | AC13: Work | AD13: 20 km | AE13: private | AF13: Petrol | AG13: Scooty four wheeler | AH13: Yes | AJ13: Bike | AK13: 105 litres for petrol
A14: 45976.848 | B14: Mane anjali sunil | C14: 21 | D14: Female | E14: Urban | F14: Government Sector | G14: above 1,00,000 | H14: 4 | I14: 2 | J14: bikes, Scooty, Four wheeler | K14: CNG | P14: No | R14: 5000litar | S14: HP | T14: Bharat petroleum | U14: 10kimi | V14: 20kimi | W14: २०kimi | X14: 5varsha | Y14: 3varash | Z14: 5varasha | AA14: School / Colleges | AB14: for dropping and picking up children | AC14: Work | AD14: 2kimi | AE14: public transport | AF14: सीएजी | AG14: Yes | AH14: 2 | AI14: Daily | AJ14: Yes | AK14: No
A15: 45976.849 | B15: Amar dhumal | C15: 20 | D15: Male | E15: Mumbai | F15: business | G15: 30,000-50,000 | H15: 6 | I15: 1 | J15: bikes, Four wheeler | K15: Petrol | P15: 45 | R15: 15 | S15: HP | T15: HP | U15: 130 .120km | V15: 60km | W15: 300km | X15: 4 | Y15: 12 | Z15: 8 | AA15: Travel | AC15: Travel | AD15: 1 | AE15: public transport | AF15: 440 | AG15: CNG | AI15: Weekly | AJ15: 19
A16: 45976.851 | B16: Dipti sanjay shirtode | C16: 21 | D16: Female | E16: Urban | F16: Housewife | G16: 10,000-30,000 | H16: 3 | I16: 1 | J16: bikes | K16: Petrol | P16: 5000 | R16: 5000 | S16: Bharat petroleum | T16: Indian oil | U16: 20 km | V16: 10 km | W16: 30 km | X16: 4 years | Y16: 5 years | Z16: 4 years | AA16: Work | AB16: Work | AC16: Work | AD16: 20 to 30km | AE16: private | AF16: Petrol | AG16: Scooty or four wheeler | AJ16: Bike | AK16: 105 litres for petrol
A17: 45976.863 | B17: Shaikh khushiya siraj | C17: 22 | D17: Female | E17: Rural | F17: Housewife | G17: below 10,000 | H17: 4 | I17: 2 | J17: bikes, Scooty | K17: Petrol | P17: 4500 | S17: Indian oil | T17: Indian oil | U17: Daily | X17: 5 | Y17: 6 | AA17: Work | AB17: School / Colleges | AD17: 30 | AE17: private
A18: 45976.87 | B18: Dhembare Dnyaneshwari Nivas | C18: 20 | D18: Female | E18: Rural | G18: 30,000-50,000 | H18: 4 | I18: 1 | J18: bikes | K18: Petrol | S18: Indian oil | U18: 20 | X18: 18 | AA18: for dropping and picking up children | AE18: private | AG18: Electric | AH18: 2 | AI18: Daily | AJ18: No | AK18: 60
A19: 45976.87 | B19: Jagtap Sonu Dattatray | C19: 20 | D19: Female | E19: Rural | F19: Agriculture | G19: 50,000-70,000 | H19: 4 | I19: 3 | J19: bikes, Four wheeler, Tractor | K19: Petrol, diesel, CNG | P19: 10 lit | R19: 200kg | S19: Bharat petroleum | T19: Indian oil | U19: 50km | V19: 20km | W19: 500km | X19: 9 years old | Y19: No | Z19: 3 years | AA19: Work | AB19: No | AC19: Travel | AD19: 100 | AE19: private | AF19: All | AG19: Yes cng | AH19: No | AI19: No | AJ19: No | AK19: No
A20: 45976.877 | B20: Sanidhya sanjay suryavanshi | C20: 19 | D20: Female | E20: Rural | F20: Agriculture | G20: 50,000-70,000 | H20: 5 | I20: 2 | J20: bikes, Scooty | K20: Petrol | S20: Indian oil | T20: Indian oil | U20: 40 km | V20: 30 | Y20: 1 year | AA20: Work | AB20: School / Colleges | AD20: Baramati to someshwar | AE20: private | AF20: Indian fuel | AG20: Yes | AH20: 4 | AI20: Weekly | AJ20: Scooty | AK20: 5
A21: 45976.891 | B21: Sahil Mane | C21: 22 | D21: Male | E21: Urban | F21: private sector | G21: 70,000-1,00,000 | H21: 4 | I21: 3 | J21: bikes, Scooty, Four wheeler | K21: Petrol | P21: 1500 | R21: 5000 | S21: Indian oil | T21: Indian oil | U21: 25 | V21: 15 | W21: 30 | X21: 13 year | Y21: 4 year | Z21: 3 year | AA21: Work | AB21: School / Colleges | AC21: Work | AD21: 500 m | AE21: Nothing | AF21: Petrol | AG21: Yes I can | AH21: 3 | AI21: No use | AJ21: Bike | AK21: 104
A22: 45976.903 | B22: Mulik Aaradhana Shamrao | C22: 19 | D22: Female | E22: Rural | F22: Student | G22: 10,000-30,000 | H22: 4 | I22: 2 | J22: Scooty | K22: Petrol | P22: 10 lit | S22: Indian oil | T22: Indian oil | U22: 20 | V22: 5 | X22: 5 | Y22: 10 | AA22: Work | AB22: Work | AD22: 10 | AE22: private | AF22: Petrol | AG22: इलेक्ट्रिक | AI22: Weekly | AK22: 60 rupees
A23: 45976.904 | B23: Snehal Somnath Kumbhar | C23: 24 | D23: Female | E23: Rural | F23: Housewife | G23: below 10,000 | H23: 3 | I23: 1 | J23: Scooty | K23: Petrol | T23: Bharat petroleum | V23: 25km | Y23: 10 year | AB23: Work | AD23: 10km | AE23: private | AF23: Cng | AG23: Ho | AH23: 1 | AI23: Often | AJ23: Two wheeler | AK23: इंधनाचे दर मापक असावेत
A24: 45976.905 | B24: Dhagare Vrushali Jayram | C24: 26 | D24: Female | E24: Urban | F24: Student | G24: below 10,000 | H24: 3 | I24: 1 | J24: Scooty | T24: Jio | V24: 50km | Y24: 15 | AD24: 5km | AE24: public transport | AF24: - | AG24: Might be in future | AH24: 2 | AI24: Weekly | AJ24: Public transport | AK24: NA
A25: 45976.908 | B25: Samruddhi Mangesh Gaikwad | C25: 20 | D25: Female | E25: Rural | F25: Student | G25: below 10,000 | H25: 5 | I25: 1 | J25: Scooty | T25: Bharat petroleum | V25: 2-4km | Y25: 6years | AB25: Work | AD25: 10km | AE25: private
A26: 45976.909 | B26: Jotiba holam | C26: 50 | D26: Male | E26: Rural | F26: business | G26: 10,000-30,000 | H26: 6 | I26: 2 | J26: bikes, Scooty | K26: Petrol | P26: 8 liter | R26: No four wheeler | S26: Indian oil | T26: Indian oil | U26: 16 km | V26: Not daily | W26: No | X26: 23 | Y26: 7 | Z26: No | AA26: Both work and college | AB26: Travel | AC26: No | AD26: 8 km | AE26: private | AF26: Petrol | AG26: No | AH26: 2 | AI26: Often | AJ26: Bike | AK26: Fuel prices change every day at 6 am, so it is important to check today's rates.
A27: 45977.434 | B27: Rajesh Patil | C27: 26 | D27: Male | E27: Urban | F27: private sector | G27: 30,000-50,000 | H27: 4 | I27: 2 | J27: bikes, Four wheeler | K27: Petrol | P27: 12 L | R27: 30 L | S27: Indian oil | U27: 10 km | W27: 7 km | X27: 4 years | Z27: 6 years | AA27: Work | AC27: for dropping and picking up children | AD27: 4 km | AE27: private | AF27: bike | AG27: Yes, willing to switch to Electric Vehicle (EV) | AH27: 2 | AI27: Occasionally | AJ27: bike | AK27: Fuel rates should be more stable and government should reduce prices to make daily travel affordable for middle-class families
A28: 45977.524 | B28: Akash Patil. | C28: 22 | D28: Male | E28: Rural | F28: private sector | G28: 10,000-30,000 | H28: 4 | I28: 2 | J28: bikes, car | K28: Petrol | M28: Petrol | P28: 4 Years | Q28: 25 km | R28: 18 liters | V28: 3 Years | W28: 30 km | X28: 55liters | AE28: 7000 | AF28: Indian Oil | AG28: Fuel quality | AH28: 12 km | AI28: Office | AJ28: Rarely | AK28: Bus | AL28: Maybe | AM28: Low running cost | AN28: Lack of charging stations | AO28: Fuel prices should be stable and charging stations increased.
A29: 45977.532 | B29: Supriya Jadhav | C29: 28 | D29: Female | E29: Urban | F29: private sector | G29: 10,000-30,000 | H29: 3 | I29: 2 | J29: bikes | K29: Petrol | P29: 6 years | Q29: 15-20km | R29: 17-18 litres | AI29: Office | AJ29: Weekly | AK29: Bus, Auto | AL29: Yes | AM29: Eco-friendly, Rising petrol/diesel prices, New technology | AN29: Lack of charging stations | AO29: Government must maintain the prices of fuel and support to eco friendly vehicles like EV ...and also pay more attention on public transportation it could be much better..
A30: 45977.55 | B30: Ghadge Rutuja. | C30: 24 | D30: Female | E30: Urban | F30: private sector | G30: 50,000-70,000 | H30: 4 | I30: 2 | J30: Scooty, car | L30: Petrol | M30: CNG | Q30: - | S30: 3 years | T30: 20 km | U30: 15 liters | V30: 2 years | W30: 35 km | X30: 35 kg CNG | AE30: 6,500₹ | AF30: Shell | AG30: Fuel quality | AH30: 10 km | AI30: Office | AJ30: Monthly | AK30: Bus | AL30: Yes | AM30: Rising petrol/diesel prices | AN30: Long charging time | AO30: Improve CNG availability.
A31: 45977.555 | B31: Suhani Himmat Mane | C31: 21 | D31: Female | E31: Rural | F31: Student | G31: below 10,000 | H31: 4 | I31: 1 | J31: bikes | K31: Petrol | P31: 10 year | Q31: 11km | R31: 30 litre | AE31: 3000 | AF31: Indian Oil | AG31: Closer to home | AH31: 11km | AI31: College | AJ31: Daily | AK31: Bus | AL31: Yes | AM31: Eco-friendly | AN31: Lack of charging stations, Long charging time | AO31: Rate must be affordable for everyone
A32: 45977.555 | B32: Vijay pawar | C32: 29 | D32: Male | E32: Rural | F32: Agriculture | G32: 10,000-30,000 | H32: 4 | I32: 2 | J32: bikes, Commercial vehicle | K32: Petrol | N32: Diesel | P32: 7years | Q32: 20km | R32: 75L | Y32: 7years | Z32: 50km | AA32: 100L | AE32: 9200 | AF32: Indian Oil | AG32: Price | AH32: 11km | AI32: Agriculture-related | AJ32: Rarely | AK32: Bus | AL32: Yes | AM32: Low running cost, Rising petrol/diesel prices | AN32: Lack of charging stations, Long charging time | AO32: Reduce Disel rates for farmers
A33: 45977.56 | B33: Sakshi Gejage | C33: 20 | D33: Female | E33: Rural | H33: 6 | I33: 1 | J33: Scooty | L33: Petrol | Q33: 12 km | S33: 1 year | T33: 10 km | U33: 10 liter | AF33: Indian Oil | AG33: Fuel quality | AH33: 14 km | AI33: College | AJ33: Daily | AK33: Bus | AL33: No | AM33: Eco-friendly | AN33: Not confident in EV technology | AO33: No
A34: 45977.562 | B34: Rushikesh Balaso Shinde | C34: 20 | D34: Male | E34: Rural | F34: Student | H34: 5 | I34: 1 | J34: bikes | K34: Petrol | P34: 3 | Q34: 30000 | R34: 2000 | AF34: Indian Oil | AG34: Fuel quality, Better service, Trust/Brand image | AH34: 10 | AI34: School pickup/drop | AJ34: Daily | AK34: I don’t use public transport | AL34: Maybe | AM34: Eco-friendly
A35: 45977.562 | B35: Mahesh Shinde 28 | C35: 28 | D35: Male | E35: Rural | F35: Agriculture | G35: 30,000-50,000 | H35: 5 | I35: 3 | J35: bikes, car, Commercial vehicle | K35: Petrol | M35: Diesel | N35: Diesel | P35: 5 yrs. | Q35: 10km | R35: 8 liters | V35: 6 yrs. | W35: 25 km | X35: 45 litres | Y35: 7 yrs. | Z35: 20 km | AA35: 60 litres | AE35: ₹10,000 | AF35: HP | AG35: Better service | AH35: 15 km | AI35: Agriculture-related | AJ35: Rarely | AK35: Private Bus | AL35: No | AN35: Lack of charging stations | AO35: Diesel prices should reduce for farmers.
A36: 45977.563 | B36: Snehal Jadhav | C36: 20 | D36: Female | E36: Urban | F36: College student | G36: below 10,000 | H36: 3 | I36: 1 | J36: Scooty | L36: Petrol | S36: 2 years | T36: 12 km | U36: 10 litres | AE36: 1,200₹ | AF36: BPCL | AG36: Closer to home | AH36: 6 km | AI36: College | AJ36: Weekly | AK36: Shared Rickshaw | AL36: Yes | AM36: Eco-friendly | AO36: Public buses should increase frequency.
A37: 45977.566 | B37: Anuja Aru | C37: 35 | D37: Female | E37: Urban | F37: private sector | G37: 30,000-50,000 | H37: 2 | I37: 2 | J37: bikes, car | K37: Petrol | M37: Diesel | P37: 6 years | Q37: 10kms | R37: 20l | V37: 13years | W37: 45kms | X37: 70l | AE37: 10k | AF37: Shell | AG37: Fuel quality, Better service, Trust/Brand image | AH37: 21kms | AI37: Office | AJ37: Rarely | AK37: Auto | AL37: No | AN37: Lack of charging stations, Not confident in EV technology | AO37: Fuel rates would be less
A38: 45977.567 | B38: Kolekar Prathamesh | C38: 26 | D38: Male | E38: Rural | F38: daily wages | G38: 10,000-30,000 | H38: 6 | I38: 1 | J38: bikes | K38: Petrol | P38: 8 yrs. | Q38: 40 km | R38: 28 litres | AE38: 3,000₹ | AF38: Indian Oil | AG38: Price | AH38: 18 km | AI38: Market/Shopping | AJ38: Weekly | AK38: Bus | AL38: Maybe | AM38: Low running cost | AO38: Reduce petrol prices.
A39: 45977.571 | B39: Neha jadhav | C39: 23 | D39: Female | E39: Urban | F39: private sector | G39: 30,000-50,000 | H39: 3 | I39: 1 | J39: Scooty | L39: Petrol | S39: 3years | T39: 18 km | U39: 12L | AE39: 1500 | AF39: BPCL | AG39: Closer to home | AH39: 7km | AI39: Office | AJ39: Weekly | AK39: Auto | AL39: Maybe | AM39: Eco-friendly | AO39: Increase woman friendly transport options
A40: 45977.572 | B40: Salunkhe Rohit | C40: 32 | D40: Male | E40: Urban | F40: business | G40: above 1,00,000 | H40: 4 | I40: 2 | J40: car, Electric Vehicle | M40: Petrol | O40: Electric | V40: 3 yrs. | W40: 40 km. | X40: 60 liters | AB40: 60 kWh/month | AC40: 25 km | AD40: 1 yrs. | AE40: ₹9,500 | AF40: Reliance | AG40: Trust/Brand image | AH40: 20 km | AI40: Office | AJ40: Never | AK40: I don’t use public transport | AL40: Yes | AM40: New technology | AO40: More EV charging stations needed.
A41: 45977.576 | B41: Mane Vaishanvi | C41: 19 | D41: Male | F41: Housewife | G41: below 10,000 | H41: 3 | I41: 1 | J41: Scooty | L41: Petrol | S41: 1 yrs. | T41: 10 km | U41: 8 litres | AF41: BPCL | AG41: Closer to home | AH41: 5 km | AI41: College | AJ41: Weekly | AK41: Shared Rickshaw | AL41: Maybe | AM41: Affordable maintenance | AO41: Improve road quality in village.
A42: 45977.579 | B42: Sanket Nalwade | C42: 27 | D42: Male | E42: Rural | F42: Agriculture | G42: 30,000-50,000 | H42: 5 | I42: 2 | J42: bikes, Commercial vehicle | K42: Petrol | N42: Diesel | P42: 6 yrs. | Q42: 15 km | R42: 10 litres | Y42: 5 yrs. | Z42: 25 km | AA42: 70 litres | AE42: 8,000₹ | AF42: HP | AG42: Better service | AH42: 14 km | AI42: Agriculture-related | AJ42: Rarely | AK42: Bus | AL42: No | AN42: Low range | AO42: Reduce diesel taxes.
A43: 45977.583 | B43: Komal Deshmukh | C43: 23 | D43: Female | E43: Urban | F43: Government Sector | G43: 50,000-70,000 | H43: 4 | I43: 2 | J43: bikes, car | K43: Petrol | M43: Petrol | P43: 3 yrs. | Q43: 20 km | R43: 12 litres | V43: 4 yrs. | W43: 30 km | X43: 55 litres | AE43: 6,800₹ | AF43: Indian Oil | AG43: Fuel quality | AH43: 10 km | AJ43: Monthly | AK43: Bus | AL43: Maybe | AM43: Rising petrol/diesel prices | AO43: Fuel prices should be reduced.
A44: 45977.584 | B44: Pratik Jadhav | C44: 26 | D44: Male | E44: Urban | F44: business | G44: 50,000-70,000 | H44: 4 | I44: 2 | J44: bikes, car | K44: Petrol | M44: Petrol | P44: 5year | Q44: 10km | R44: 7L | V44: 2years | W44: 45km | X44: 70L | AE44: 9000 | AF44: HP | AG44: Fuel quality | AH44: 18km | AI44: Office | AJ44: Rarely | AK44: I don’t use public transport | AL44: Yes | AM44: Low running cost | AO44: Cut petrol taxes
A45: 45977.588 | B45: Pawar Yash | C45: 30 | D45: Male | E45: Rural | F45: business | G45: 30,000-50,000 | H45: 5 | I45: 3 | J45: bikes, Scooty, car | K45: Petrol | L45: Petrol | M45: Petrol | P45: 4 yrs. | Q45: 18 km | R45: 13 litres | S45: 2 yrs. | T45: 12km | U45: 9 litres | V45: 5 yrs | W45: 40 km | X45: 65 litres | AE45: ₹9,000 | AF45: BPCL | AG45: Price | AH45: 15 km | AI45: Office | AJ45: Rarely | AK45: Auto | AL45: Yes | AM45: Eco-friendly | AO45: Encourage EV subsidies.
A46: 45977.599 | B46: Ashiwini Shinde | C46: 21 | D46: Female | E46: Rural | F46: College | G46: below 10,000 | H46: 4 | I46: 1 | J46: Scooty | L46: Petrol | S46: 1year | T46: 10km | U46: 7L | AE46: 900 | AF46: BPCL | AG46: Closer to home | AH46: 5km | AI46: College | AJ46: Weekly | AK46: Shared Rickshaw | AL46: Maybe | AM46: Government subsidy | AO46: Reduce student bus pass cost
A47: 45977.602 | B47: Prathmesh Baravkar | C47: 20 | D47: Male | E47: Rural | F47: Student | G47: below 10,000 | H47: 5 | I47: 3 | J47: bikes, car | K47: Petrol | L47: Petrol | M47: Petrol | P47: 8 | Q47: 3km | R47: 6l | S47: 4 | T47: 8km | U47: 14l | V47: 7 | W47: 10km | X47: 25l | AF47: HP | AG47: Closer to home | AH47: 9km | AI47: Office | AJ47: Daily | AK47: Bus, Shared Rickshaw | AL47: Yes | AM47: Rising petrol/diesel prices
A48: 45977.603 | B48: Rahul Kamble | C48: 25 | D48: Male | E48: Urban | F48: private sector | G48: 30,000-50,000 | H48: 3 | I48: 1 | J48: bikes | K48: Petrol | P48: 3 years | Q48: 22 km | R48: 18 L | AE48: 2,300 Rs | AF48: Indian Oil | AG48: Fuel quality | AH48: 10 km | AI48: Office | AJ48: Monthly | AK48: Bus | AL48: Maybe | AO48: Provide more EV charging stations.
A49: 45977.604 | B49: Pooja More | C49: 19 | D49: Female | E49: Rural | F49: student | G49: below 10,000 | H49: 4 | I49: 1 | J49: Scooty | L49: Petrol | S49: 2 years | T49: 15 km | U49: 10 L | AE49: 1,200 Rs | AF49: BPCL | AG49: Closer to home | AH49: 6 km | AI49: College | AJ49: Weekly | AK49: Shared Rickshaw | AL49: Yes | AM49: Eco-friendly | AO49: Bus frequency should improve.
A50: 45977.604 | B50: Dhananjay Mane | C50: 35 | D50: Male | E50: Rural | F50: Agriculture | G50: 30,000-50,000 | H50: 6 | I50: 3 | J50: bikes, Commercial vehicle, Tractor | K50: Petrol | N50: Diesel | P50: 10years | Q50: 15km | R50: 10L | Y50: 8years | Z50: 35km | AA50: 80L | AE50: 11100 | AF50: Indian Oil | AG50: Price | AH50: 12km | AI50: Agriculture-related | AJ50: Rarely | AK50: Bus | AL50: No | AN50: Lack of charging stations | AO50: Fuel rates should be farmer friendly
A51: 45977.606 | B51: Riya Deshmukh | C51: 24 | D51: Female | E51: Urban | F51: private sector | G51: 30,000-50,000 | H51: 3 | I51: 1 | J51: car | M51: Petrol | V51: 2years | W51: 30km | X51: 50L | AE51: 6000 | AF51: Shell | AG51: Fuel quality | AH51: 10km | AI51: Office | AJ51: Monthly | AK51: Bus | AL51: Yes | AM51: Eco-friendly
A52: 45977.606 | B52: Shubham Ghule | C52: 31 | D52: Male | E52: Urban | F52: business | G52: 70,000-1,00,000 | H52: 5 | I52: 3 | J52: bikes, car, Electric Vehicle | K52: Petrol | M52: Petrol | O52: Electric | P52: 4 years | Q52: 8 km | R52: 6 L | V52: 6 years | W52: 35 km | X52: 55 L | AB52: 45 kWh | AC52: 20 km | AD52: 1 years | AE52: 8,800 Rs | AF52: Shell | AG52: Trust/Brand image | AH52: 14 km | AI52: Office | AJ52: Never | AK52: I don’t use public transport | AL52: Yes | AM52: New technology | AO52: EV subsidy should increase.
A53: 45977.607 | B53: Omkar Salgude | C53: 27 | D53: Male | E53: Rural | F53: daily wages | G53: below 10,000 | H53: 4 | I53: 1 | J53: bikes | K53: Petrol | P53: 6years | Q53: 35km | R53: 24L | AE53: 2700 | AF53: BPCL | AG53: Price | AH53: 14km | AI53: Other | AJ53: Weekly | AK53: Bus | AL53: Maybe | AM53: Low running cost
A54: 45977.609 | B54: Gayatri Chavan | C54: 27 | D54: Female | E54: Rural | F54: Housewife | G54: 10,000-30,000 | H54: 6 | I54: 2 | J54: bikes, Scooty | K54: Petrol | L54: Petrol | P54: 5 years | Q54: 12 km | R54: 9 L | S54: 3 years | T54: 10 km | U54: 8 L | AE54: 3,000 Rs | AF54: Indian Oil | AG54: Price | AH54: 4 km | AI54: Market/Shopping | AJ54: Weekly | AK54: Auto | AL54: Maybe | AM54: Affordable maintenance | AO54: Petrol should be under ₹100.
A55: 45977.61 | B55: Amruta Pawar | C55: 28 | D55: Female | E55: Urban | F55: Housewife | G55: 10,000-30,000 | H55: 5 | I55: 2 | J55: Scooty, car | L55: Petrol | M55: Petrol | S55: 5years | T55: 12km | U55: 9L | V55: 8years | W55: 20km | X55: 40L | AE55: 5200 | AF55: Indian Oil | AG55: Trust/Brand image | AH55: 8km | AI55: School pickup/drop | AJ55: Rarely | AK55: Auto | AL55: No | AN55: High price | AO55: Improve roads
A56: 45977.611 | B56: Ajinkya Nikam | C56: 34 | D56: Male | E56: Urban | F56: Government Sector | G56: 50,000-70,000 | H56: 4 | I56: 2 | J56: bikes, car | K56: Petrol | M56: Diesel | P56: 7 years | Q56: 10 km | R56: 7 L | V56: 4 years | W56: 50 km | X56: 70 L | AE56: 9,700 Rs | AF56: BPCL | AG56: Better service | AH56: 15 km | AI56: Office | AJ56: Rarely | AK56: Train | AL56: Maybe | AM56: Rising petrol/diesel prices | AO56: Improve traffic discipline.
A57: 45977.613 | B57: Madhuri Pawar | C57: 30 | D57: Female | E57: Rural | F57: Agriculture | G57: 30,000-50,000 | H57: 5 | I57: 2 | J57: bikes, Commercial vehicle | K57: Petrol | N57: Diesel | P57: 6 years | Q57: 18 km | R57: 12 L | Y57: 10 years | Z57: 25 km | AA57: 65 L | AE57: ₹8,200 | AF57: Indian Oil | AG57: Price | AH57: 8 km | AI57: Agriculture-related | AJ57: Monthly | AK57: Bus | AL57: No | AN57: Lack of charging stations | AO57: Diesel rates should be reduced for farmers.
A58: 45977.614 | B58: Soham Jagtap | C58: 22 | D58: Male | E58: Urban | F58: Student | G58: 10,000-30,000 | H58: 3 | I58: 1 | J58: bikes | K58: Petrol | P58: 2 yrs | Q58: 30 km | R58: 20 L | AE58: ₹2,400 | AF58: HP | AG58: Price | AH58: 7 km | AI58: College | AJ58: Weekly | AK58: Bus | AL58: Yes | AM58: Eco-friendly | AO58: More cycle tracks needed.
A59: 45977.616 | B59: Swapnil Kadam | C59: 28 | D59: Male | E59: Rural | F59: daily wages | G59: below 10,000 | H59: 4 | I59: 1 | J59: bikes | K59: Petrol | P59: 8 yrs | Q59: 40 km | R59: 26 L | AE59: ₹2,900 | AF59: BPCL | AG59: Closer to home | AH59: 12 km | AI59: Other | AJ59: Monthly | AK59: Bus | AL59: Maybe | AM59: Low running cost | AO59: Roads should be repaired.
A60: 45977.617 | B60: Santosh khande | C60: 33 | D60: Male | E60: Rural | F60: business | G60: 50,000-70,000 | H60: 6 | I60: 3 | J60: bikes, Scooty, car | K60: Petrol | L60: Petrol | M60: Petrol | P60: 4years | Q60: 25km | R60: 16L | S60: 3years | T60: 8km | U60: 6L | V60: 5years | W60: 40km | X60: 60L | AE60: 9500 | AF60: HP | AG60: Other | AH60: 20km | AI60: Office | AJ60: Rarely | AK60: Bus | AL60: Yes | AM60: Rising petrol/diesel prices
A61: 45977.617 | B61: Rohini Salunke | C61: 26 | D61: Female | E61: Urban | F61: private sector | G61: 30,000-50,000 | H61: 3 | I61: 1 | J61: car | M61: Petrol | V61: 3 yrs | W61: 25 km | X61: 45 L | AE61: ₹5,200 | AF61: Indian Oil | AG61: Trust/Brand image | AH61: 9 km | AI61: Office | AJ61: Monthly | AK61: Auto | AL61: Yes | AM61: Low running cost | AO61: Parking facilities should be improved.
A62: 45977.619 | B62: Kiran Bhalekar | C62: 30 | D62: Male | E62: Rural | F62: Government Sector | G62: 70,000-1,00,000 | H62: 4 | I62: 2 | J62: bikes, car | K62: Petrol | M62: Diesel | P62: 2years | Q62: 10km | R62: 7L | V62: 3years | W62: 50km | X62: 65L | AE62: 8500 | AF62: BPCL | AG62: Trust/Brand image | AH62: 18km | AI62: Office | AJ62: Rarely | AK62: I don’t use public transport | AL62: Maybe | AM62: Eco-friendly
A63: 45977.619 | B63: Nitin Kolekar | C63: 33 | D63: Male | E63: Rural | F63: Agriculture | G63: 10,000-30,000 | H63: 5 | I63: 2 | J63: bikes, Commercial vehicle | K63: Petrol | N63: Diesel | P63: 9 yrs | Q63: 20 km | R63: 14 L | Y63: 12 yrs | Z63: 18 km | AA63: 55 L | AE63: ₹7,000 | AF63: HP | AG63: Better service | AH63: 10 km | AI63: Agriculture-related | AJ63: Rarely | AK63: Private Bus | AL63: No | AN63: High price | AO63: Fuel rates must be reduced for rural areas.
A64: 45977.626 | B64: Shashikant Jadhav | C64: 38 | D64: Male | E64: Rural | F64: business | G64: 50,000-70,000 | H64: 5 | I64: 2 | J64: bikes, car | K64: Petrol | M64: Petrol | P64: 9 years | Q64: 15 km | R64: 12 litres | V64: 4 years | W64: 20 km | X64: 24 litres | AE64: ₹5,500 | AF64: Reliance | AG64: Fuel quality | AH64: 12 km | AI64: Other | AJ64: Never | AK64: I don’t use public transport | AL64: No | AN64: Lack of charging stations | AO64: Increase rural petrol pumps
A65: 45977.628 | B65: Kavita Satpute | C65: 29 | D65: Female | E65: Urban | F65: private sector | G65: 30,000-50,000 | H65: 3 | I65: 1 | J65: Scooty | L65: Petrol | S65: 3 years | T65: 9 km | U65: 7 litres | AE65: ₹900 | AF65: Indian Oil | AG65: Trust/Brand image | AH65: 4 km | AI65: Office | AJ65: Monthly | AK65: Auto | AL65: Yes | AM65: Low running cost | AO65: Provide subsidy on EV scooters
A66: 45977.631 | B66: Krishna Pawar | C66: 26 | D66: Male | E66: Rural | F66: Agriculture | G66: 10,000-30,000 | H66: 6 | I66: 2 | J66: bikes, Commercial vehicle | K66: Petrol | N66: Diesel | P66: 4 years | Q66: 14 km | R66: 10 L | Y66: 7 years | Z66: 32 km | AA66: 42 L | AE66: ₹5,200 | AF66: HP | AG66: Price | AH66: 10 km | AI66: Agriculture-related | AJ66: Rarely | AK66: Bus | AL66: Maybe | AM66: Rising petrol/diesel prices | AO66: Diesel should be subsidized for farmers
A67: 45977.632 | B67: Rucha Phadke | C67: 20 | D67: Female | E67: Urban | F67: student | G67: below 10,000 | H67: 4 | I67: 1 | J67: Scooty | L67: Petrol | S67: 1 year | T67: 8 km | U67: 5 L | AE67: ₹650 | AF67: BPCL | AG67: Closer to home | AH67: 5 km | AI67: College | AJ67: Weekly | AK67: Bus | AL67: Yes | AM67: Eco-friendly | AO67: Increase student bus passes
A68: 45977.634 | B68: Sagar Ghatage | C68: 42 | D68: Male | E68: Rural | F68: Government Sector | G68: 70,000-1,00,000 | H68: 5 | I68: 3 | J68: bikes, car, Commercial vehicle | K68: Petrol | M68: Petrol | N68: Diesel | P68: 8 years | Q68: 20 km | R68: 15 L | V68: 5 years | W68: 22 km | X68: 26 L | Y68: 6 years | Z68: 45 km | AA68: 26 L | AE68: ₹12,000 | AF68: Indian Oil | AG68: Fuel quality | AH68: 15 km | AI68: Office | AJ68: Never | AK68: I don’t use public transport | AL68: Maybe | AM68: Government subsidy | AO68: Improve road conditions
A69: 45977.636 | B69: Prajakta More | C69: 31 | D69: Female | E69: Urban | F69: business | G69: 50,000-70,000 | H69: 4 | I69: 1 | J69: car | M69: Petrol | V69: 3 years | W69: 16 km | X69: 20 L | AE69: ₹2,400 | AF69: Shell | AG69: Better service | AH69: 6 km | AI69: Office | AJ69: Rarely | AK69: Auto | AL69: Yes | AM69: Affordable maintenance | AO69: Build more EV charging points
A70: 45977.638 | B70: Akshay Kharat | C70: 24 | D70: Male | E70: Urban | F70: private sector | G70: 10,000-30,000 | H70: 3 | I70: 1 | J70: bikes | K70: Petrol | P70: 2 years | Q70: 18 km | R70: 14 L | AE70: ₹1,500 | AF70: BPCL | AG70: Price | AH70: 9 km | AI70: Office | AJ70: Monthly | AK70: Bus | AL70: Yes | AM70: Rising petrol/diesel prices | AO70: Provide bike EV subsidies
A71: 45977.64 | B71: Suvarna Sawant | C71: 47 | D71: Female | E71: Rural | F71: Housewife | G71: below 10,000 | H71: 4 | I71: 1 | J71: Scooty | L71: Petrol | S71: 6 years | T71: 5 km | U71: 4 L | AE71: ₹500 | AF71: Indian Oil | AG71: Closer to home | AH71: 3 km | AI71: Household work | AJ71: Weekly | AK71: Shared Rickshaw | AL71: Maybe | AM71: Low running cost | AO71: Reduce petrol tax
A72: 45977.642 | B72: Omkar Nikam | C72: 34 | D72: Male | E72: Urban | F72: business | G72: above 1,00,000 | H72: 4 | I72: 2 | J72: bikes, car | K72: Petrol | M72: Petrol | P72: 3 years | Q72: 12 km | R72: 9 L | V72: 2 years | W72: 25 km | X72: 9 L | AE72: ₹5,800 | AF72: Shell | AG72: Fuel quality | AH72: 10 km | AI72: Business | AJ72: Never | AK72: I don’t use public transport | AL72: Yes | AM72: New technology | AO72: EV cars should be cheaper
A73: 45977.644 | B73: Mitali Khot | C73: 22 | D73: Female | E73: Rural | F73: student | G73: below 10,000 | H73: 5 | I73: 1 | J73: bikes | K73: Petrol | P73: 2 years | Q73: 10 km | R73: 7 L | AE73: ₹850 | AF73: HP | AG73: Price | AH73: 6 km | AI73: College | AJ73: Weekly | AK73: Bus | AL73: Maybe | AM73: Eco-friendly | AO73: Reduce fuel prices for students
A74: 45977.648 | B74: Shinde Ritesh | C74: 22 | D74: Male | E74: Rural | F74: daily wages | G74: 10,000-30,000 | H74: 4 | I74: 1 | J74: bikes | K74: Petrol | P74: 4 yrs. | Q74: 18 km | R74: 14 litres | AE74: 1,400₹ | AF74: Indian Oil | AG74: Fuel quality | AH74: 9km | AI74: Office | AJ74: Rarely | AK74: Bus | AL74: Maybe | AM74: Low running cost | AO74: Reduce petrol rates for rural areas
A75: 45977.65 | B75: Vaishali Zende | C75: 27 | D75: Female | E75: Urban | F75: private sector | G75: 30,000-50,000 | H75: 3 | I75: 2 | J75: Scooty, car | L75: Petrol | M75: Petrol | S75: 3yrs | T75: 10km | U75: 7 litres | V75: 6 yrs | W75: 14 km | X75: 20 litres | AE75: ₹3,200 | AF75: BPCL | AG75: Price | AH75: 7 km | AI75: Office | AJ75: Monthly | AK75: Bus | AL75: Yes | AM75: Eco-friendly | AO75: Increase EV charging stations.
A76: 45977.653 | B76: Dnyaneshwar Pawar | C76: 40 | D76: Male | E76: Rural | F76: Agriculture | G76: 30,000-50,000 | H76: 5 | I76: 2 | J76: bikes, Commercial vehicle | K76: Petrol | N76: Diesel | P76: 7 yrs | Q76: 20 km | R76: 16 litres | Y76: 5 yrs | Z76: 35 km | AA76: 45 litres | AE76: ₹6,800 | AF76: HP | AG76: Closer to home | AH76: 11km | AI76: Agriculture-related | AJ76: Rarely | AK76: Shared Rickshaw | AL76: No | AN76: Low range | AO76: Diesel prices should be reduced.
A77: 45977.656 | B77: Smita Lohar | C77: 32 | D77: Female | E77: Urban | F77: Housewife | G77: 10,000-30,000 | H77: 4 | I77: 1 | J77: Scooty | L77: Petrol | S77: 4 yrs | T77: 8 km | U77: 6 litres | AE77: ₹700 | AF77: Indian Oil | AG77: Trust/Brand image | AH77: 4km | AI77: Market/Shopping | AJ77: Weekly | AK77: Auto | AL77: Maybe | AM77: Eco-friendly | AO77: Bus frequency should increase.
A78: 45977.659 | B78: Ganesh Deshmukh | C78: 45 | D78: Male | E78: Rural | F78: business | G78: 70,000-1,00,000 | H78: 5 | I78: 3 | J78: bikes, car, Commercial vehicle | K78: Petrol | M78: Petrol | N78: Diesel | P78: 10 yrs | Q78: 15 km | R78: 12 litres | V78: 8 yrs | W78: 25 km | X78: 28 litres | Y78: 6 yrs. | Z78: 40km | AA78: 55 litres | AE78: ₹11,000 | AF78: Reliance | AG78: Better service | AH78: 13 km | AI78: Business | AJ78: Never | AK78: I don’t use public transport | AL78: No | AN78: High price | AO78: Reduce GST on fuel.
A79: 45977.662 | B79: Kadam Nisha | C79: 19 | D79: Female | E79: Urban | F79: student | G79: below 10,000 | H79: 3 | I79: 1 | J79: Scooty | L79: Petrol | S79: 2 yrs. | T79: 12 km | U79: 8 litres | AE79: ₹850 | AF79: BPCL | AG79: Closer to home | AH79: 6 km | AI79: College | AJ79: Weekly | AK79: Bus | AL79: Yes | AM79: Low running cost | AO79: Provide student discount on fuel.
A80: 45977.665 | B80: Balaju Thorat | C80: 36 | D80: Male | E80: Rural | F80: Government Sector | G80: 50,000-70,000 | H80: 4 | I80: 2 | J80: bikes, Scooty | K80: Petrol | L80: Petrol | P80: 5 yrs. | Q80: 22 km | R80: 18 litres | S80: 3 yrs. | T80: 12 km | U80: 16 litres | AE80: ₹4,500 | AF80: Indian Oil | AG80: Fuel quality | AH80: 10 km | AI80: Office | AJ80: Rarely | AK80: Private Bus | AL80: Maybe | AM80: Rising petrol/diesel prices | AO80: Build more highways.
A81: 45977.673 | B81: Srushti Arjun Yadav | C81: 21 | D81: Female | E81: Rural | F81: student | G81: below 10,000 | H81: 5 | I81: 3 | J81: bikes, Scooty | K81: Petrol | L81: Petrol | M81: CNG | N81: LPG | O81: Electric | P81: 4 year | Q81: 10 | R81: 500 | S81: 3 year | T81: 10 | U81: 500 | V81: 2 year | W81: 9 | X81: 400 | Y81: 2 year | Z81: 5 | AA81: 300 | AB81: 4 | AC81: 3 | AD81: 2 | AE81: 200 | AF81: HP | AG81: Fuel quality | AH81: 10 | AI81: College | AJ81: Daily | AK81: Bus | AL81: No | AM81: New technology | AN81: Lack of charging stations | AO81: No
A82: 45977.679 | B82: Snehal Kambale | C82: 23 | D82: Female | E82: Urban | F82: private sector | G82: 30,000-50,000 | H82: 3 | I82: 1 | J82: car | M82: Petrol | S82: 2 years | T82: 18 km | U82: 22 litres | AE82: ₹2,700 | AF82: Shell | AG82: Fuel quality | AH82: 9 km | AI82: Office | AJ82: Monthly | AK82: Auto | AL82: Yes | AM82: New technology | AO82: Encourage carpooling
A83: 45977.682 | B83: Pratik More | C83: 28 | D83: Male | E83: Rural | F83: Agriculture | G83: 10,000-30,000 | H83: 6 | I83: 2 | J83: bikes, Commercial vehicle | K83: Petrol | N83: Diesel | P83: 3 yrs | Q83: 14 km | R83: 10 litres | Y83: 4 years | Z83: 28 km | AA83: 38 litres | AE83: ₹5000 | AF83: HP | AG83: Price | AH83: 10 km | AI83: Agriculture-related | AJ83: Rarely | AK83: Shared Rickshaw | AL83: Maybe | AM83: Low running cost | AO83: Lower diesel prices
A84: 45977.684 | B84: Puja Bhosale | C84: 21 | D84: Female | E84: Rural | F84: student | G84: below 10,000 | H84: 4 | I84: 1 | J84: Scooty | L84: Petrol | S84: 1years. | T84: 10km | U84: 6 litres | AE84: ₹750 | AF84: Indian Oil | AG84: Closer to home | AH84: 5 km | AI84: College | AJ84: Weekly | AK84: Bus | AL84: Yes | AM84: Eco-friendly | AO84: Make fuel prices stable
A85: 45977.705 | B85: Mansi santosh algude | C85: 21 | D85: Female | E85: Rural | F85: student | G85: below 10,000 | H85: 5 | I85: 1 | J85: bikes | K85: Petrol | P85: 3 | Q85: 4km | R85: 10 liter | AF85: Indian Oil | AG85: Closer to home | AH85: 4km | AI85: Office | AJ85: Daily | AK85: Bus | AL85: Yes | AM85: Eco-friendly | AO85: No
A86: 45977.706 | B86: Raju Mane | C86: 40 | D86: Male | E86: Urban | F86: daily wages | G86: 30,000-50,000 | H86: 4 | I86: 2 | J86: bikes, Scooty | K86: Petrol | L86: Petrol | P86: 13 years | Q86: 2 km | R86: ₹ 1,200 | S86: 1 years | T86: 3 km | U86: 1000 | AE86: ₹ 4000 | AF86: Indian Oil | AG86: Closer to home | AH86: 1 km | AI86: Work | AJ86: Monthly | AK86: Auto | AL86: Maybe | AM86: Low running cost | AO86: Petrol price should be below 100 ₹
A87: 45977.735 | B87: Khalate vaishnavi sanjay | C87: 22 | D87: Female | F87: student | G87: below 10,000 | H87: 5 | I87: 1 | J87: bikes | K87: Petrol | P87: 2 | Q87: 40 | R87: 1 | S87: 1 | T87: 30 | U87: 3 | V87: No | W87: No | X87: No | Y87: No | Z87: No | AA87: No
A88: 45977.744 | B88: Kunal Bhongale | C88: 21 | D88: Male | E88: Rural | F88: student | G88: 10,000-30,000 | H88: 5 | I88: 1 | J88: bikes | K88: Petrol | P88: 06
A89: 45977.747 | B89: Akanksha | C89: 20 | D89: Female | E89: Rural | F89: student | H89: 6 | I89: 2 | J89: bikes, Scooty | K89: Diesel | L89: Petrol | AF89: HP | AG89: Fuel quality, Better service | AH89: 10km | AI89: Market/Shopping | AJ89: Rarely | AK89: Bus, Auto | AL89: Yes | AM89: Eco-friendly
A90: 45977.76 | B90: Suyash Danawale | C90: 20 | D90: Male | E90: Rural | F90: student | G90: below 10,000 | H90: 5 | I90: 1 | J90: Scooty | L90: Petrol | S90: 10 | T90: 20000 | U90: 1000
A91: 45977.805 | B91: Swapnil Suryakant Jadhav | C91: 25 | D91: Male | E91: Rural | F91: Agriculture | G91: below 10,000 | H91: 3 | I91: 2 | J91: bikes | K91: Petrol | P91: 5 year's | Q91: 20-25 km | R91: 60 to 70 litre | AF91: HP | AG91: Fuel quality | AH91: 10 to 15 km | AI91: Agriculture-related | AJ91: Rarely | AK91: Bus | AL91: No | AN91: High price, Lack of charging stations | AO91: Fule Price are so high.
A92: 45977.899 | B92: Ashok Landge | C92: 48 | D92: Male | E92: Rural | F92: Agriculture | G92: 30,000-50,000 | H92: 6 | I92: 2 | J92: bikes, Commercial vehicle | K92: Petrol | N92: Diesel | P92: 8 years | Q92: 16 km | R92: 55 L | Y92: 10 years | Z92: 40 km | AA92: 55 L | AE92: ₹7,500 | AF92: HP | AG92: Price | AH92: 8 km | AI92: Agriculture-related | AJ92: Rarely | AK92: Bus | AL92: No | AN92: Low range | AO92: Reduce diesel price for farmers
A93: 45977.9 | B93: Shraddha Pise | C93: 25 | D93: Female | E93: Urban | F93: private sector | G93: 10,000-30,000 | H93: 3 | I93: 1 | J93: Scooty | L93: Petrol | S93: 2 years | T93: 11 km | U93: 7 L | AE93: ₹900 | AF93: Indian Oil | AG93: Closer to home | AH93: 6 km | AI93: Office | AJ93: Monthly | AK93: Auto | AL93: Yes | AM93: Rising petrol/diesel prices | AO93: More EV stations needed
A94: 45977.902 | B94: Nitin Mane | C94: 33 | D94: Male | E94: Rural | F94: business | G94: 50,000-70,000 | H94: 4 | I94: 2 | J94: bikes, car | K94: Petrol | M94: Petrol | P94: 7 years | Q94: 20 km | R94: 15 L | V94: 3 years | W94: 18 km | X94: 22 L | AE94: ₹5,500 | AF94: BPCL | AG94: Business | AH94: 12 km | AI94: Business | AJ94: Rarely | AK94: Bus | AL94: Maybe | AM94: Low running cost | AO94: Reduce petrol tax
A95: 45977.904 | B95: Mayuri Bhadane | C95: 21 | D95: Female | E95: Urban | F95: student | G95: below 10,000 | H95: 5 | I95: 1 | J95: Scooty | L95: Petrol | S95: 1 years | T95: 9 km | U95: 6 L | AE95: ₹700 | AF95: Indian Oil | AG95: Trust/Brand image | AH95: 5 km | AI95: College | AJ95: Weekly | AK95: Bus | AL95: Yes | AM95: Eco-friendly | AO95: More buses for students
A96: 45977.905 | B96: Dilip Kharade | C96: 50 | D96: Male | E96: Rural | F96: Agriculture | G96: 10,000-30,000 | H96: 6 | I96: 1 | J96: bikes | K96: Petrol | P96: 11 years | Q96: 14 km | R96: 10 L | AE96: ₹1,200 | AF96: HP | AG96: Closer to home | AH96: 7 km | AI96: Agriculture-related | AJ96: Rarely | AK96: Shared Rickshaw | AL96: No | AN96: High price | AO96: Subsidy for farmers
A97: 45977.906 | B97: Neha More | C97: 34 | D97: Female | E97: Urban | F97: Government Sector | G97: 70,000-1,00,000 | H97: 3 | I97: 1 | J97: car | M97: Petrol | V97: 4 years | W97: 20 km | X97: 24 L | AE97: ₹3,200 | AF97: Shell | AG97: Fuel quality | AH97: 10 km | AI97: Office | AJ97: Monthly | AK97: Bus | AL97: Yes | AM97: Affordable maintenance | AO97: EV parking areas needed
A98: 45977.908 | B98: Tushar Gaikwad | C98: 30 | D98: Male | E98: Urban | F98: private sector | G98: 30,000-50,000 | H98: 4 | I98: 2 | J98: bikes, car | K98: Petrol | M98: Petrol | P98: 5 years | Q98: 18 km | R98: 14 L | V98: 3 years | W98: 15 km | X98: 19 L | AE98: ₹4,800 | AF98: Indian Oil | AG98: Fuel quality | AH98: 8 km | AI98: Office | AJ98: Rarely | AK98: Auto | AL98: Maybe | AM98: New technology | AO98: Reduce petrol price
A99: 45977.909 | B99: Swapnali Chavan | C99: 22 | D99: Female | E99: Urban | F99: student | G99: below 10,000 | H99: 4 | I99: 1 | J99: Scooty | L99: Petrol | S99: 2 years | T99: 10 km | U99: 6 L | AE99: ₹750 | AF99: BPCL | AG99: Price | AH99: 4 km | AI99: College | AJ99: Weekly | AK99: Bus | AL99: Yes | AM99: Rising petrol/diesel prices | AO99: Make EV bikes cheaper
A100: 45977.914 | B100: Ajay Salunkhe | C100: 39 | D100: Male | E100: Rural | F100: business | G100: 50,000-70,000 | H100: 5 | I100: 2 | J100: car, Commercial vehicle | M100: Diesel | N100: Petrol | V100: 6 years | W100: 22 km | X100: 25 litres | Y100: 8 years | Z100: 45 km | AA100: 65 litres | AE100: ₹10,000 | AF100: Reliance | AG100: Better service | AH100: 12 km | AI100: Business | AJ100: Never | AK100: I don’t use public transport | AL100: No | AM100: Low running cost | AN100: Low range | AO100: Improve diesel quality
...

Sheet clean_data
A1: Age | B1: Gender | C1: Monthly_income | D1: Total_family _members | E1: Num_vehicles_in_family | F1: Type_vehicle | G1: fuel_required_Bike | H1: fuel_required_Scooty | I1: fuel_required_Car | J1: fuel_required_Commercial | K1: Age_bike | L1: Daily_distance_travelled_bike | M1: fuel_monthly_bikes | N1: Age_Scooty | O1: Daily_distance_travelled_Scooty | P1: Fuel_required_monthly_scooty | Q1: Age_Car | R1: Daily_distance_travelled_Car | S1: Fuel_required_monthly_car | T1: Age_commercial | U1: Daily_distance_travelled_commercial | V1: Fuel_required_monthly_commercial | W1: Total_monthly_fuel_expense | X1: Preferred_fuel_brand | Y1: Distance_home_ workplace | Z1: Main_purpose_vehicle | AA1: How_often_use_PT | AB1: type_PT | AC1: consider_ev | AD1: Is_Outliers
A2: 21 | B2: Female | C2: below 10,000 | D2: 4 | E2: 1 | F2: bikes | G2: Petrol | K2: 10 | L2: 11 | M2: 30 | W2: 3000 | X2: Indian Oil | Y2: 11 | Z2: College | AA2: Daily | AB2: Bus | AC2: Yes | AD2: =IF(OR(Form_Responses34[[#This Row],[Total_monthly_fuel_expense ]]>10040,Form_Responses34[[#This Row],[Total_monthly_fuel_expense ]]<-4760),"Outlier","Normal") -> Normal
A3: 29 | B3: Male | C3: 10,000 - 30,000 | D3: 4 | E3: 2 | F3: bikes, Commercial vehicle | G3: Petrol | J3: Diesel | K3: 7 | L3: 20 | M3: 75 | T3: 7 | U3: 50 | V3: 1 | W3: 9200 | X3: Indian Oil | Y3: 11 | Z3: Agriculture-related | AA3: Rarely | AB3: Bus | AC3: Yes | AD3: =IF(OR(Form_Responses34[[#This Row],[Total_monthly_fuel_expense ]]>10040,Form_Responses34[[#This Row],[Total_monthly_fuel_expense ]]<-4760),"Outlier","Normal") -> Normal
A4: 20 | B4: Female | C4: 10,000 - 30,000 | D4: 6 | E4: 1 | F4: Scooty | H4: Petrol | N4: 1 | O4: 10 | P4: 10 | W4: 1000 | X4: Indian Oil | Y4: 14 | Z4: College | AA4: Daily | AB4: Bus | AC4: No | AD4: =IF(OR(Form_Responses34[[#This Row],[Total_monthly_fuel_expense ]]>10040,Form_Responses34[[#This Row],[Total_monthly_fuel_expense ]]<-4760),"Outlier","Normal") -> Normal
A5: 20 | B5: Male | C5: 10,000 - 30,000 | D5: 5 | E5: 1 | F5: bikes | G5: Petrol | K5: 3 | L5: 30 | M5: 20 | W5: 1000 | X5: Indian Oil | Y5: 10 | Z5: School pickup/drop | AA5: Daily | AB5: I don’t use public transport | AC5: Maybe | AD5: =IF(OR(Form_Responses34[[#This Row],[Total_monthly_fuel_expense ]]>10040,Form_Responses34[[#This Row],[Total_monthly_fuel_expense ]]<-4760),"Outlier","Normal") -> Normal
A6: 28 | B6: Male | C6: 30,000 - 50,000 | D6: 5 | E6: 3 | F6: bikes, car, Commercial vehicle | G6: Petrol | I6: Diesel | J6: Diesel | K6: 5 | L6: 10 | M6: 8 | Q6: 6 | R6: 25 | S6: 45 | T6: 7 | U6: 20 | V6: 60 | W6: 10000 | X6: HP | Y6: 15 | Z6: Agriculture-related | AA6: Rarely | AB6: Private Bus | AC6: No | AD6: =IF(OR(Form_Responses34[[#This Row],[Total_monthly_fuel_expense ]]>10040,Form_Responses34[[#This Row],[Total_monthly_fuel_expense ]]<-4760),"Outlier","Normal") -> Normal
A7: 20 | B7: Female | C7: below 10,000 | D7: 3 | E7: 1 | F7: Scooty | H7: Petrol | N7: 2 | O7: 12 | P7: 10 | W7: 1200 | X7: BPCL | Y7: 6 | Z7: College | AA7: Weekly | AB7: Shared Rickshaw | AC7: Yes | AD7: =IF(OR(Form_Responses34[[#This Row],[Total_monthly_fuel_expense ]]>10040,Form_Responses34[[#This Row],[Total_monthly_fuel_expense ]]<-4760),"Outlier","Normal") -> Normal
A8: 35 | B8: Female | C8: 30,000 - 50,000 | D8: 2 | E8: 2 | F8: bikes, car | G8: Petrol | I8: Diesel | K8: 6 | L8: 10 | M8: 20 | Q8: 13 | R8: 45 | S8: 70 | W8: 1000 | X8: Shell | Y8: 21 | Z8: Office | AA8: Rarely | AB8: Auto | AC8: No | AD8: =IF(OR(Form_Responses34[[#This Row],[Total_monthly_fuel_expense ]]>10040,Form_Responses34[[#This Row],[Total_monthly_fuel_expense ]]<-4760),"Outlier","Normal") -> Normal
A9: 26 | B9: Male | C9: 10,000 - 30,000 | D9: 6 | E9: 1 | F9: bikes | G9: Petrol | K9: 8 | L9: 40 | M9: 28 | W9: 3000 | X9: Indian Oil | Y9: 18 | Z9: Market/Shopping | AA9: Weekly | AB9: Bus | AC9: Maybe | AD9: =IF(OR(Form_Responses34[[#This Row],[Total_monthly_fuel_expense ]]>10040,Form_Responses34[[#This Row],[Total_monthly_fuel_expense ]]<-4760),"Outlier","Normal") -> Normal
A10: 23 | B10: Female | C10: 30,000 - 50,000 | D10: 3 | E10: 1 | F10: Scooty | H10: Petrol | N10: 3 | O10: 18 | P10: 12 | W10: 1500 | X10: BPCL | Y10: 7 | Z10: Office | AA10: Weekly | AB10: Auto | AC10: Maybe | AD10: =IF(OR(Form_Responses34[[#This Row],[Total_monthly_fuel_expense ]]>10040,Form_Responses34[[#This Row],[Total_monthly_fuel_expense ]]<-4760),"Outlier","Normal") -> Normal
A11: 32 | B11: Male | C11: above 1,00,000 | D11: 4 | E11: 2 | F11: car, Electric Vehicle | I11: Petrol | Q11: 3 | R11: 40 | S11: 60 | W11: 9500 | X11: Reliance | Y11: 20 | Z11: Office | AA11: Never | AB11: I don’t use public transport | AC11: Yes | AD11: =IF(OR(Form_Responses34[[#This Row],[Total_monthly_fuel_expense ]]>10040,Form_Responses34[[#This Row],[Total_monthly_fuel_expense ]]<-4760),"Outlier","Normal") -> Normal
A12: 19 | B12: Male | C12: below 10,000 | D12: 3 | E12: 1 | F12: Scooty | H12: Petrol | N12: 1 | O12: 10 | P12: 8 | W12: 1500 | X12: BPCL | Y12: 5 | Z12: College | AA12: Weekly | AB12: Shared Rickshaw | AC12: Maybe | AD12: =IF(OR(Form_Responses34[[#This Row],[Total_monthly_fuel_expense ]]>10040,Form_Responses34[[#This Row],[Total_monthly_fuel_expense ]]<-4760),"Outlier","Normal") -> Normal
A13: 27 | B13: Male | C13: 30,000 - 50,000 | D13: 5 | E13: 2 | F13: bikes, Commercial vehicle | G13: Petrol | J13: Diesel | K13: 6 | L13: 15 | M13: 10 | T13: 5 | U13: 25 | V13: 70 | W13: 8000 | X13: HP | Y13: 14 | Z13: Agriculture-related | AA13: Rarely | AB13: Bus | AC13: No | AD13: =IF(OR(Form_Responses34[[#This Row],[Total_monthly_fuel_expense ]]>10040,Form_Responses34[[#This Row],[Total_monthly_fuel_expense ]]<-4760),"Outlier","Normal") -> Normal
A14: 23 | B14: Female | C14: 50,000 - 70,000 | D14: 4 | E14: 2 | F14: bikes, car | G14: Petrol | I14: Petrol | K14: 3 | L14: 20 | M14: 12 | Q14: 4 | R14: 30 | S14: 55 | W14: 6800 | X14: Indian Oil | Y14: 10 | Z14: Work | AA14: Monthly | AB14: Bus | AC14: Maybe | AD14: =IF(OR(Form_Responses34[[#This Row],[Total_monthly_fuel_expense ]]>10040,Form_Responses34[[#This Row],[Total_monthly_fuel_expense ]]<-4760),"Outlier","Normal") -> Normal
A15: 26 | B15: Male | C15: 50,000 - 70,000 | D15: 4 | E15: 2 | F15: bikes, car | G15: Petrol | I15: Petrol | K15: 5 | L15: 10 | M15: 7 | Q15: 2 | R15: 45 | S15: 70 | W15: 9000 | X15: HP | Y15: 18 | Z15: Office | AA15: Rarely | AB15: I don’t use public transport | AC15: Yes | AD15: =IF(OR(Form_Responses34[[#This Row],[Total_monthly_fuel_expense ]]>10040,Form_Responses34[[#This Row],[Total_monthly_fuel_expense ]]<-4760),"Outlier","Normal") -> Normal
A16: 30 | B16: Male | C16: 30,000 - 50,000 | D16: 5 | E16: 3 | F16: bikes, Scooty, car | G16: Petrol | H16: Petrol | I16: Petrol | K16: 4 | L16: 18 | M16: 13 | N16: 2 | O16: 12 | P16: 9 | Q16: 5 | R16: 40 | S16: 65 | W16: 9000 | X16: BPCL | Y16: 15 | Z16: Office | AA16: Rarely | AB16: Auto | AC16: Yes | AD16: =IF(OR(Form_Responses34[[#This Row],[Total_monthly_fuel_expense ]]>10040,Form_Responses34[[#This Row],[Total_monthly_fuel_expense ]]<-4760),"Outlier","Normal") -> Normal
A17: 21 | B17: Female | C17: below 10,000 | D17: 4 | E17: 1 | F17: Scooty | H17: Petrol | N17: 1 | O17: 10 | P17: 7 | W17: 900 | X17: BPCL | Y17: 5 | Z17: College | AA17: Weekly | AB17: Shared Rickshaw | AC17: Maybe | AD17: =IF(OR(Form_Responses34[[#This Row],[Total_monthly_fuel_expense ]]>10040,Form_Responses34[[#This Row],[Total_monthly_fuel_expense ]]<-4760),"Outlier","Normal") -> Normal
A18: 20 | B18: Male | C18: below 10,000 | D18: 5 | E18: 3 | F18: bikes, car | G18: Petrol | I18: Petrol | K18: 8 | L18: 3 | M18: 6 | Q18: 7 | R18: 10 | S18: 25 | W18: 2000 | X18: HP | Y18: 9 | Z18: Office | AA18: Daily | AB18: Bus, Shared Rickshaw | AC18: Yes | AD18: =IF(OR(Form_Responses34[[#This Row],[Total_monthly_fuel_expense ]]>10040,Form_Responses34[[#This Row],[Total_monthly_fuel_expense ]]<-4760),"Outlier","Normal") -> Normal
A19: 25 | B19: Male | C19: 30,000 - 50,000 | D19: 3 | E19: 1 | F19: bikes | G19: Petrol | K19: 3 | L19: 22 | M19: 18 | W19: 2300 | X19: Indian Oil | Y19: 10 | Z19: Office | AA19: Monthly | AB19: Bus | AC19: Maybe | AD19: =IF(OR(Form_Responses34[[#This Row],[Total_monthly_fuel_expense ]]>10040,Form_Responses34[[#This Row],[Total_monthly_fuel_expense ]]<-4760),"Outlier","Normal") -> Normal
A20: 19 | B20: Female | C20: below 10,000 | D20: 4 | E20: 1 | F20: Scooty | H20: Petrol | N20: 2 | O20: 15 | P20: 10 | W20: 1200 | X20: BPCL | Y20: 6 | Z20: College | AA20: Weekly | AB20: Shared Rickshaw | AC20: Yes | AD20: =IF(OR(Form_Responses34[[#This Row],[Total_monthly_fuel_expense ]]>10040,Form_Responses34[[#This Row],[Total_monthly_fuel_expense ]]<-4760),"Outlier","Normal") -> Normal
A21: 35 | B21: Male | C21: 30,000 - 50,000 | D21: 6 | E21: 3 | F21: bikes, Commercial vehicle, Tractor | G21: Petrol | J21: Diesel | K21: 10 | L21: 15 | M21: 10 | T21: 8 | U21: 35 | V21: 80 | W21: 11100 | X21: Indian Oil | Y21: 12 | Z21: Agriculture-related | AA21: Rarely | AB21: Bus | AC21: No | AD21: =IF(OR(Form_Responses34[[#This Row],[Total_monthly_fuel_expense ]]>10040,Form_Responses34[[#This Row],[Total_monthly_fuel_expense ]]<-4760),"Outlier","Normal") -> Outlier
A22: 24 | B22: Female | C22: 30,000 - 50,000 | D22: 3 | E22: 1 | F22: car | I22: Petrol | Q22: 2 | R22: 30 | S22: 50 | W22: 6000 | X22: Shell | Y22: 10 | Z22: Office | AA22: Monthly | AB22: Bus | AC22: Yes | AD22: =IF(OR(Form_Responses34[[#This Row],[Total_monthly_fuel_expense ]]>10040,Form_Responses34[[#This Row],[Total_monthly_fuel_expense ]]<-4760),"Outlier","Normal") -> Normal
A23: 31 | B23: Male | C23: 70,000 - 1,00,000 | D23: 5 | E23: 3 | F23: bikes, car, Electric Vehicle | G23: Petrol | I23: Petrol | K23: 4 | L23: 8 | M23: 6 | Q23: 6 | R23: 35 | S23: 55 | W23: 8800 | X23: Shell | Y23: 14 | Z23: Office | AA23: Never | AB23: I don’t use public transport | AC23: Yes | AD23: =IF(OR(Form_Responses34[[#This Row],[Total_monthly_fuel_expense ]]>10040,Form_Responses34[[#This Row],[Total_monthly_fuel_expense ]]<-4760),"Outlier","Normal") -> Normal
A24: 27 | B24: Male | C24: below 10,000 | D24: 4 | E24: 1 | F24: bikes | G24: Petrol | K24: 6 | L24: 35 | M24: 24 | W24: 2700 | X24: BPCL | Y24: 14 | Z24: Other | AA24: Weekly | AB24: Bus | AC24: Maybe | AD24: =IF(OR(Form_Responses34[[#This Row],[Total_monthly_fuel_expense ]]>10040,Form_Responses34[[#This Row],[Total_monthly_fuel_expense ]]<-4760),"Outlier","Normal") -> Normal
A25: 27 | B25: Female | C25: 10,000 - 30,000 | D25: 6 | E25: 2 | F25: bikes, Scooty | G25: Petrol | H25: Petrol | K25: 5 | L25: 12 | M25: 9 | N25: 3 | O25: 10 | P25: 8 | W25: 3000 | X25: Indian Oil | Y25: 4 | Z25: Market/Shopping | AA25: Weekly | AB25: Auto | AC25: Maybe | AD25: =IF(OR(Form_Responses34[[#This Row],[Total_monthly_fuel_expense ]]>10040,Form_Responses34[[#This Row],[Total_monthly_fuel_expense ]]<-4760),"Outlier","Normal") -> Normal
A26: 28 | B26: Female | C26: 10,000 - 30,000 | D26: 5 | E26: 2 | F26: Scooty, car | H26: Petrol | I26: Petrol | N26: 5 | O26: 12 | P26: 9 | Q26: 8 | R26: 20 | S26: 40 | W26: 5200 | X26: Indian Oil | Y26: 8 | Z26: School pickup/drop | AA26: Rarely | AB26: Auto | AC26: No | AD26: =IF(OR(Form_Responses34[[#This Row],[Total_monthly_fuel_expense ]]>10040,Form_Responses34[[#This Row],[Total_monthly_fuel_expense ]]<-4760),"Outlier","Normal") -> Normal
A27: 34 | B27: Male | C27: 50,000 - 70,000 | D27: 4 | E27: 2 | F27: bikes, car | G27: Petrol | I27: Diesel | K27: 7 | L27: 10 | M27: 7 | Q27: 4 | R27: 50 | S27: 70 | W27: 9700 | X27: BPCL | Y27: 15 | Z27: Office | AA27: Rarely | AB27: Train | AC27: Maybe | AD27: =IF(OR(Form_Responses34[[#This Row],[Total_monthly_fuel_expense ]]>10040,Form_Responses34[[#This Row],[Total_monthly_fuel_expense ]]<-4760),"Outlier","Normal") -> Normal
A28: 30 | B28: Female | C28: 30,000 - 50,000 | D28: 5 | E28: 2 | F28: bikes, Commercial vehicle | G28: Petrol | J28: Diesel | K28: 6 | L28: 18 | M28: 12 | T28: 10 | U28: 25 | V28: 65 | W28: 8200 | X28: Indian Oil | Y28: 8 | Z28: Agriculture-related | AA28: Monthly | AB28: Bus | AC28: No | AD28: =IF(OR(Form_Responses34[[#This Row],[Total_monthly_fuel_expense ]]>10040,Form_Responses34[[#This Row],[Total_monthly_fuel_expense ]]<-4760),"Outlier","Normal") -> Normal
A29: 22 | B29: Male | C29: 10,000 - 30,000 | D29: 3 | E29: 1 | F29: bikes | G29: Petrol | K29: 2 | L29: 30 | M29: 20 | W29: 2400 | X29: HP | Y29: 7 | Z29: College | AA29: Weekly | AB29: Bus | AC29: Yes | AD29: =IF(OR(Form_Responses34[[#This Row],[Total_monthly_fuel_expense ]]>10040,Form_Responses34[[#This Row],[Total_monthly_fuel_expense ]]<-4760),"Outlier","Normal") -> Normal
A30: 28 | B30: Male | C30: below 10,000 | D30: 4 | E30: 1 | F30: bikes | G30: Petrol | K30: 8 | L30: 40 | M30: 26 | W30: 2900 | X30: BPCL | Y30: 12 | Z30: Other | AA30: Monthly | AB30: Bus | AC30: Maybe | AD30: =IF(OR(Form_Responses34[[#This Row],[Total_monthly_fuel_expense ]]>10040,Form_Responses34[[#This Row],[Total_monthly_fuel_expense ]]<-4760),"Outlier","Normal") -> Normal
A31: 33 | B31: Male | C31: 50,000 - 70,000 | D31: 6 | E31: 3 | F31: bikes, Scooty, car | G31: Petrol | H31: Petrol | I31: Petrol | K31: 4 | L31: 25 | M31: 16 | N31: 3 | O31: 8 | P31: 6 | Q31: 5 | R31: 40 | S31: 60 | W31: 9500 | X31: HP | Y31: 20 | Z31: Office | AA31: Rarely | AB31: Bus | AC31: Yes | AD31: =IF(OR(Form_Responses34[[#This Row],[Total_monthly_fuel_expense ]]>10040,Form_Responses34[[#This Row],[Total_monthly_fuel_expense ]]<-4760),"Outlier","Normal") -> Normal
A32: 26 | B32: Female | C32: 30,000 - 50,000 | D32: 3 | E32: 1 | F32: car | I32: Petrol | Q32: 3 | R32: 25 | S32: 45 | W32: 5200 | X32: Indian Oil | Y32: 9 | Z32: Office | AA32: Monthly | AB32: Auto | AC32: Yes | AD32: =IF(OR(Form_Responses34[[#This Row],[Total_monthly_fuel_expense ]]>10040,Form_Responses34[[#This Row],[Total_monthly_fuel_expense ]]<-4760),"Outlier","Normal") -> Normal
A33: 30 | B33: Male | C33: 70,000 - 1,00,000 | D33: 4 | E33: 2 | F33: bikes, car | G33: Petrol | I33: Diesel | K33: 2 | L33: 10 | M33: 7 | Q33: 3 | R33: 50 | S33: 65 | W33: 8500 | X33: BPCL | Y33: 18 | Z33: Office | AA33: Rarely | AB33: I don’t use public transport | AC33: Maybe | AD33: =IF(OR(Form_Responses34[[#This Row],[Total_monthly_fuel_expense ]]>10040,Form_Responses34[[#This Row],[Total_monthly_fuel_expense ]]<-4760),"Outlier","Normal") -> Normal
A34: 33 | B34: Male | C34: 10,000 - 30,000 | D34: 5 | E34: 2 | F34: bikes, Commercial vehicle | G34: Petrol | J34: Diesel | K34: 9 | L34: 20 | M34: 14 | T34: 12 | U34: 18 | V34: 55 | W34: 7000 | X34: HP | Y34: 10 | Z34: Agriculture-related | AA34: Rarely | AB34: Private Bus | AC34: No | AD34: =IF(OR(Form_Responses34[[#This Row],[Total_monthly_fuel_expense ]]>10040,Form_Responses34[[#This Row],[Total_monthly_fuel_expense ]]<-4760),"Outlier","Normal") -> Normal
A35: 38 | B35: Male | C35: 50,000 - 70,000 | D35: 5 | E35: 2 | F35: bikes, car | G35: Petrol | I35: Petrol | K35: 9 | L35: 15 | M35: 12 | Q35: 4 | R35: 20 | S35: 24 | W35: 5500 | X35: Reliance | Y35: 12 | Z35: Other | AA35: Never | AB35: I don’t use public transport | AC35: No | AD35: =IF(OR(Form_Responses34[[#This Row],[Total_monthly_fuel_expense ]]>10040,Form_Responses34[[#This Row],[Total_monthly_fuel_expense ]]<-4760),"Outlier","Normal") -> Normal
A36: 29 | B36: Female | C36: 30,000 - 50,000 | D36: 3 | E36: 1 | F36: Scooty | H36: Petrol | N36: 3 | O36: 9 | P36: 7 | W36: 900 | X36: Indian Oil | Y36: 4 | Z36: Office | AA36: Monthly | AB36: Auto | AC36: Yes | AD36: =IF(OR(Form_Responses34[[#This Row],[Total_monthly_fuel_expense ]]>10040,Form_Responses34[[#This Row],[Total_monthly_fuel_expense ]]<-4760),"Outlier","Normal") -> Normal
A37: 26 | B37: Male | C37: 10,000 - 30,000 | D37: 6 | E37: 2 | F37: bikes, Commercial vehicle | G37: Petrol | J37: Diesel | K37: 4 | L37: 14 | M37: 10 | T37: 7 | U37: 32 | V37: 42 | W37: 5200 | X37: HP | Y37: 10 | Z37: Agriculture-related | AA37: Rarely | AB37: Bus | AC37: Maybe | AD37: =IF(OR(Form_Responses34[[#This Row],[Total_monthly_fuel_expense ]]>10040,Form_Responses34[[#This Row],[Total_monthly_fuel_expense ]]<-4760),"Outlier","Normal") -> Normal
A38: 20 | B38: Female | C38: below 10,000 | D38: 4 | E38: 1 | F38: Scooty | H38: Petrol | N38: 1 | O38: 8 | P38: 5 | W38: 650 | X38: BPCL | Y38: 5 | Z38: College | AA38: Weekly | AB38: Bus | AC38: Yes | AD38: =IF(OR(Form_Responses34[[#This Row],[Total_monthly_fuel_expense ]]>10040,Form_Responses34[[#This Row],[Total_monthly_fuel_expense ]]<-4760),"Outlier","Normal") -> Normal
A39: 42 | B39: Male | C39: 70,000 - 1,00,000 | D39: 5 | E39: 3 | F39: bikes, car, Commercial vehicle | G39: Petrol | I39: Petrol | J39: Diesel | K39: 8 | L39: 20 | M39: 15 | Q39: 5 | R39: 22 | S39: 26 | T39: 6 | U39: 45 | V39: 26 | W39: 12000 | X39: Indian Oil | Y39: 15 | Z39: Office | AA39: Never | AB39: I don’t use public transport | AC39: Maybe | AD39: =IF(OR(Form_Responses34[[#This Row],[Total_monthly_fuel_expense ]]>10040,Form_Responses34[[#This Row],[Total_monthly_fuel_expense ]]<-4760),"Outlier","Normal") -> Outlier
A40: 31 | B40: Female | C40: 50,000 - 70,000 | D40: 4 | E40: 1 | F40: car | I40: Petrol | Q40: 3 | R40: 16 | S40: 20 | W40: 2400 | X40: Shell | Y40: 6 | Z40: Office | AA40: Rarely | AB40: Auto | AC40: Yes | AD40: =IF(OR(Form_Responses34[[#This Row],[Total_monthly_fuel_expense ]]>10040,Form_Responses34[[#This Row],[Total_monthly_fuel_expense ]]<-4760),"Outlier","Normal") -> Normal
A41: 24 | B41: Male | C41: 10,000 - 30,000 | D41: 3 | E41: 1 | F41: bikes | G41: Petrol | K41: 2 | L41: 18 | M41: 14 | W41: 1500 | X41: BPCL | Y41: 9 | Z41: Office | AA41: Monthly | AB41: Bus | AC41: Yes | AD41: =IF(OR(Form_Responses34[[#This Row],[Total_monthly_fuel_expense ]]>10040,Form_Responses34[[#This Row],[Total_monthly_fuel_expense ]]<-4760),"Outlier","Normal") -> Normal
A42: 47 | B42: Female | C42: below 10,000 | D42: 4 | E42: 1 | F42: Scooty | H42: Petrol | N42: 6 | O42: 5 | P42: 4 | W42: 500 | X42: Indian Oil | Y42: 3 | Z42: Household work | AA42: Weekly | AB42: Shared Rickshaw | AC42: Maybe | AD42: =IF(OR(Form_Responses34[[#This Row],[Total_monthly_fuel_expense ]]>10040,Form_Responses34[[#This Row],[Total_monthly_fuel_expense ]]<-4760),"Outlier","Normal") -> Normal
A43: 34 | B43: Male | C43: above 1,00,000 | D43: 4 | E43: 2 | F43: bikes, car | G43: Petrol | I43: Petrol | K43: 3 | L43: 12 | M43: 9 | Q43: 2 | R43: 25 | S43: 9 | W43: 5800 | X43: Shell | Y43: 10 | Z43: Business | AA43: Never | AB43: I don’t use public transport | AC43: Yes | AD43: =IF(OR(Form_Responses34[[#This Row],[Total_monthly_fuel_expense ]]>10040,Form_Responses34[[#This Row],[Total_monthly_fuel_expense ]]<-4760),"Outlier","Normal") -> Normal
A44: 22 | B44: Female | C44: below 10,000 | D44: 5 | E44: 1 | F44: bikes | G44: Petrol | K44: 2 | L44: 10 | M44: 7 | W44: 850 | X44: HP | Y44: 6 | Z44: College | AA44: Weekly | AB44: Bus | AC44: Maybe | AD44: =IF(OR(Form_Responses34[[#This Row],[Total_monthly_fuel_expense ]]>10040,Form_Responses34[[#This Row],[Total_monthly_fuel_expense ]]<-4760),"Outlier","Normal") -> Normal
A45: 22 | B45: Male | C45: 10,000 - 30,000 | D45: 4 | E45: 1 | F45: bikes | G45: Petrol | K45: 4 | L45: 18 | M45: 14 | W45: 1400 | X45: Indian Oil | Y45: 9 | Z45: Office | AA45: Rarely | AB45: Bus | AC45: Maybe | AD45: =IF(OR(Form_Responses34[[#This Row],[Total_monthly_fuel_expense ]]>10040,Form_Responses34[[#This Row],[Total_monthly_fuel_expense ]]<-4760),"Outlier","Normal") -> Normal
A46: 27 | B46: Female | C46: 30,000 - 50,000 | D46: 3 | E46: 2 | F46: Scooty, car | H46: Petrol | I46: Petrol | N46: 3 | O46: 10 | P46: 7 | Q46: 6 | R46: 14 | S46: 20 | W46: 3200 | X46: BPCL | Y46: 7 | Z46: Office | AA46: Monthly | AB46: Bus | AC46: Yes | AD46: =IF(OR(Form_Responses34[[#This Row],[Total_monthly_fuel_expense ]]>10040,Form_Responses34[[#This Row],[Total_monthly_fuel_expense ]]<-4760),"Outlier","Normal") -> Normal
A47: 40 | B47: Male | C47: 30,000 - 50,000 | D47: 5 | E47: 2 | F47: bikes, Commercial vehicle | G47: Petrol | J47: Diesel | K47: 7 | L47: 20 | M47: 16 | T47: 5 | U47: 35 | V47: 45 | W47: 6800 | X47: HP | Y47: 11 | Z47: Agriculture-related | AA47: Rarely | AB47: Shared Rickshaw | AC47: No | AD47: =IF(OR(Form_Responses34[[#This Row],[Total_monthly_fuel_expense ]]>10040,Form_Responses34[[#This Row],[Total_monthly_fuel_expense ]]<-4760),"Outlier","Normal") -> Normal
A48: 32 | B48: Female | C48: 10,000 - 30,000 | D48: 4 | E48: 1 | F48: Scooty | H48: Petrol | N48: 4 | O48: 8 | P48: 6 | W48: 700 | X48: Indian Oil | Y48: 4 | Z48: Market/Shopping | AA48: Weekly | AB48: Auto | AC48: Maybe | AD48: =IF(OR(Form_Responses34[[#This Row],[Total_monthly_fuel_expense ]]>10040,Form_Responses34[[#This Row],[Total_monthly_fuel_expense ]]<-4760),"Outlier","Normal") -> Normal
A49: 45 | B49: Male | C49: 70,000 - 1,00,000 | D49: 5 | E49: 3 | F49: bikes, car, Commercial vehicle | G49: Petrol | I49: Petrol | J49: Diesel | K49: 10 | L49: 15 | M49: 12 | Q49: 8 | R49: 25 | S49: 28 | T49: 6 | U49: 40 | V49: 55 | W49: 11000 | X49: Reliance | Y49: 13 | Z49: Business | AA49: Never | AB49: I don’t use public transport | AC49: No | AD49: =IF(OR(Form_Responses34[[#This Row],[Total_monthly_fuel_expense ]]>10040,Form_Responses34[[#This Row],[Total_monthly_fuel_expense ]]<-4760),"Outlier","Normal") -> Outlier
A50: 19 | B50: Female | C50: below 10,000 | D50: 3 | E50: 1 | F50: Scooty | H50: Petrol | N50: 2 | O50: 12 | P50: 8 | W50: 850 | X50: BPCL | Y50: 6 | Z50: College | AA50: Weekly | AB50: Bus | AC50: Yes | AD50: =IF(OR(Form_Responses34[[#This Row],[Total_monthly_fuel_expense ]]>10040,Form_Responses34[[#This Row],[Total_monthly_fuel_expense ]]<-4760),"Outlier","Normal") -> Normal
A51: 36 | B51: Male | C51: 50,000 - 70,000 | D51: 4 | E51: 2 | F51: bikes, Scooty | G51: Petrol | H51: Petrol | K51: 5 | L51: 22 | M51: 18 | N51: 3 | O51: 12 | P51: 16 | W51: 4500 | X51: Indian Oil | Y51: 10 | Z51: Office | AA51: Rarely | AB51: Private Bus | AC51: Maybe | AD51: =IF(OR(Form_Responses34[[#This Row],[Total_monthly_fuel_expense ]]>10040,Form_Responses34[[#This Row],[Total_monthly_fuel_expense ]]<-4760),"Outlier","Normal") -> Normal
A52: 21 | B52: Female | C52: below 10,000 | D52: 5 | E52: 3 | F52: bikes, Scooty | G52: Petrol | H52: Petrol | K52: 4 | L52: 10 | M52: 5 | N52: 3 | O52: 10 | P52: 5 | W52: 200 | X52: HP | Y52: 10 | Z52: College | AA52: Daily | AB52: Bus | AC52: No | AD52: =IF(OR(Form_Responses34[[#This Row],[Total_monthly_fuel_expense ]]>10040,Form_Responses34[[#This Row],[Total_monthly_fuel_expense ]]<-4760),"Outlier","Normal") -> Normal
A53: 23 | B53: Female | C53: 30,000 - 50,000 | D53: 3 | E53: 1 | F53: car | I53: Petrol | Q53: 5 | R53: 24 | S53: 24 | W53: 2700 | X53: Shell | Y53: 9 | Z53: Office | AA53: Monthly | AB53: Auto | AC53: Yes | AD53: =IF(OR(Form_Responses34[[#This Row],[Total_monthly_fuel_expense ]]>10040,Form_Responses34[[#This Row],[Total_monthly_fuel_expense ]]<-4760),"Outlier","Normal") -> Normal
A54: 28 | B54: Male | C54: 10,000 - 30,000 | D54: 6 | E54: 2 | F54: bikes, Commercial vehicle | G54: Petrol | J54: Diesel | K54: 3 | L54: 14 | M54: 10 | T54: 4 | U54: 28 | V54: 38 | W54: 5000 | X54: HP | Y54: 10 | Z54: Agriculture-related | AA54: Rarely | AB54: Shared Rickshaw | AC54: Maybe | AD54: =IF(OR(Form_Responses34[[#This Row],[Total_monthly_fuel_expense ]]>10040,Form_Responses34[[#This Row],[Total_monthly_fuel_expense ]]<-4760),"Outlier","Normal") -> Normal
A55: 21 | B55: Female | C55: below 10,000 | D55: 4 | E55: 1 | F55: Scooty | H55: Petrol | N55: 1 | O55: 10 | P55: 6 | W55: 750 | X55: Indian Oil | Y55: 5 | Z55: College | AA55: Weekly | AB55: Bus | AC55: Yes | AD55: =IF(OR(Form_Responses34[[#This Row],[Total_monthly_fuel_expense ]]>10040,Form_Responses34[[#This Row],[Total_monthly_fuel_expense ]]<-4760),"Outlier","Normal") -> Normal
A56: 21 | B56: Female | C56: below 10,000 | D56: 5 | E56: 1 | F56: bikes | G56: Petrol | K56: 3 | L56: 4 | M56: 10 | W56: 650 | X56: Indian Oil | Y56: 4 | Z56: Office | AA56: Daily | AB56: Bus | AC56: Yes | AD56: =IF(OR(Form_Responses34[[#This Row],[Total_monthly_fuel_expense ]]>10040,Form_Responses34[[#This Row],[Total_monthly_fuel_expense ]]<-4760),"Outlier","Normal") -> Normal
A57: 40 | B57: Male | C57: 30,000 - 50,000 | D57: 4 | E57: 2 | F57: bikes, Scooty | G57: Petrol | H57: Petrol | K57: 13 | L57: 2 | M57: 12 | N57: 1 | O57: 3 | P57: 10 | W57: 4000 | X57: Indian Oil | Y57: 1 | Z57: Work | AA57: Monthly | AB57: Auto | AC57: Maybe | AD57: =IF(OR(Form_Responses34[[#This Row],[Total_monthly_fuel_expense ]]>10040,Form_Responses34[[#This Row],[Total_monthly_fuel_expense ]]<-4760),"Outlier","Normal") -> Normal
A58: 22 | B58: Female | C58: below 10,000 | D58: 5 | E58: 1 | F58: bikes | G58: Petrol | K58: 2 | L58: 40 | M58: 1 | W58: 650 | X58: Indian Oil | Y58: 6 | Z58: Work | AA58: Never | AB58: I don’t use public transport | AC58: Yes | AD58: =IF(OR(Form_Responses34[[#This Row],[Total_monthly_fuel_expense ]]>10040,Form_Responses34[[#This Row],[Total_monthly_fuel_expense ]]<-4760),"Outlier","Normal") -> Normal
A59: 21 | B59: Male | C59: 10,000 - 30,000 | D59: 5 | E59: 1 | F59: bikes | G59: Petrol | K59: 6 | L59: 12 | M59: 8 | W59: 650 | X59: Indian Oil | Y59: 6 | Z59: Work | AA59: Never | AB59: I don’t use public transport | AC59: Yes | AD59: =IF(OR(Form_Responses34[[#This Row],[Total_monthly_fuel_expense ]]>10040,Form_Responses34[[#This Row],[Total_monthly_fuel_expense ]]<-4760),"Outlier","Normal") -> Normal
A60: 20 | B60: Female | C60: 10,000 - 30,000 | D60: 6 | E60: 2 | F60: bikes, Scooty | G60: Diesel | H60: Petrol | K60: 6 | L60: 12 | M60: 8 | N60: 3 | O60: 8 | P60: 6 | W60: 650 | X60: HP | Y60: 10 | Z60: Market/Shopping | AA60: Rarely | AB60: Bus, Auto | AC60: Yes | AD60: =IF(OR(Form_Responses34[[#This Row],[Total_monthly_fuel_expense ]]>10040,Form_Responses34[[#This Row],[Total_monthly_fuel_expense ]]<-4760),"Outlier","Normal") -> Normal
A61: 20 | B61: Male | C61: below 10,000 | D61: 5 | E61: 1 | F61: Scooty | H61: Petrol | N61: 10 | O61: 2 | P61: 10 | W61: 1000 | X61: Indian Oil | Y61: 6 | Z61: Work | AA61: Never | AB61: I don’t use public transport | AC61: Yes | AD61: =IF(OR(Form_Responses34[[#This Row],[Total_monthly_fuel_expense ]]>10040,Form_Responses34[[#This Row],[Total_monthly_fuel_expense ]]<-4760),"Outlier","Normal") -> Normal
A62: 25 | B62: Male | C62: below 10,000 | D62: 3 | E62: 2 | F62: bikes | G62: Petrol | K62: 5 | L62: 20 | M62: 60 | W62: 1000 | X62: HP | Y62: 15 | Z62: Agriculture-related | AA62: Rarely | AB62: Bus | AC62: No | AD62: =IF(OR(Form_Responses34[[#This Row],[Total_monthly_fuel_expense ]]>10040,Form_Responses34[[#This Row],[Total_monthly_fuel_expense ]]<-4760),"Outlier","Normal") -> Normal
A63: 48 | B63: Male | C63: 30,000 - 50,000 | D63: 6 | E63: 2 | F63: bikes, Commercial vehicle | G63: Petrol | J63: Diesel | K63: 8 | L63: 16 | M63: 55 | T63: 10 | U63: 40 | V63: 55 | W63: 7500 | X63: HP | Y63: 8 | Z63: Agriculture-related | AA63: Rarely | AB63: Bus | AC63: No | AD63: =IF(OR(Form_Responses34[[#This Row],[Total_monthly_fuel_expense ]]>10040,Form_Responses34[[#This Row],[Total_monthly_fuel_expense ]]<-4760),"Outlier","Normal") -> Normal
A64: 25 | B64: Female | C64: 10,000 - 30,000 | D64: 3 | E64: 1 | F64: Scooty | H64: Petrol | N64: 2 | O64: 11 | P64: 7 | W64: 900 | X64: Indian Oil | Y64: 6 | Z64: Office | AA64: Monthly | AB64: Auto | AC64: Yes | AD64: =IF(OR(Form_Responses34[[#This Row],[Total_monthly_fuel_expense ]]>10040,Form_Responses34[[#This Row],[Total_monthly_fuel_expense ]]<-4760),"Outlier","Normal") -> Normal
A65: 33 | B65: Male | C65: 50,000 - 70,000 | D65: 4 | E65: 2 | F65: bikes, car | G65: Petrol | I65: Petrol | K65: 7 | L65: 20 | M65: 15 | Q65: 3 | R65: 18 | S65: 22 | W65: 5500 | X65: BPCL | Y65: 12 | Z65: Business | AA65: Rarely | AB65: Bus | AC65: Maybe | AD65: =IF(OR(Form_Responses34[[#This Row],[Total_monthly_fuel_expense ]]>10040,Form_Responses34[[#This Row],[Total_monthly_fuel_expense ]]<-4760),"Outlier","Normal") -> Normal
A66: 21 | B66: Female | C66: below 10,000 | D66: 5 | E66: 1 | F66: Scooty | H66: Petrol | N66: 1 | O66: 9 | P66: 6 | W66: 700 | X66: Indian Oil | Y66: 5 | Z66: College | AA66: Weekly | AB66: Bus | AC66: Yes | AD66: =IF(OR(Form_Responses34[[#This Row],[Total_monthly_fuel_expense ]]>10040,Form_Responses34[[#This Row],[Total_monthly_fuel_expense ]]<-4760),"Outlier","Normal") -> Normal
A67: 50 | B67: Male | C67: 10,000 - 30,000 | D67: 6 | E67: 1 | F67: bikes | G67: Petrol | K67: 11 | L67: 14 | M67: 10 | W67: 1200 | X67: HP | Y67: 7 | Z67: Agriculture-related | AA67: Rarely | AB67: Shared Rickshaw | AC67: No | AD67: =IF(OR(Form_Responses34[[#This Row],[Total_monthly_fuel_expense ]]>10040,Form_Responses34[[#This Row],[Total_monthly_fuel_expense ]]<-4760),"Outlier","Normal") -> Normal
A68: 34 | B68: Female | C68: 70,000 - 1,00,000 | D68: 3 | E68: 1 | F68: car | I68: Petrol | Q68: 4 | R68: 20 | S68: 24 | W68: 3200 | X68: Shell | Y68: 10 | Z68: Office | AA68: Monthly | AB68: Bus | AC68: Yes | AD68: =IF(OR(Form_Responses34[[#This Row],[Total_monthly_fuel_expense ]]>10040,Form_Responses34[[#This Row],[Total_monthly_fuel_expense ]]<-4760),"Outlier","Normal") -> Normal
A69: 30 | B69: Male | C69: 30,000 - 50,000 | D69: 4 | E69: 2 | F69: bikes, car | G69: Petrol | I69: Petrol | K69: 5 | L69: 18 | M69: 14 | Q69: 3 | R69: 15 | S69: 19 | W69: 4800 | X69: Indian Oil | Y69: 8 | Z69: Office | AA69: Rarely | AB69: Auto | AC69: Maybe | AD69: =IF(OR(Form_Responses34[[#This Row],[Total_monthly_fuel_expense ]]>10040,Form_Responses34[[#This Row],[Total_monthly_fuel_expense ]]<-4760),"Outlier","Normal") -> Normal
A70: 22 | B70: Female | C70: below 10,000 | D70: 4 | E70: 1 | F70: Scooty | H70: Petrol | N70: 2 | O70: 10 | P70: 6 | W70: 750 | X70: BPCL | Y70: 4 | Z70: College | AA70: Weekly | AB70: Bus | AC70: Yes | AD70: =IF(OR(Form_Responses34[[#This Row],[Total_monthly_fuel_expense ]]>10040,Form_Responses34[[#This Row],[Total_monthly_fuel_expense ]]<-4760),"Outlier","Normal") -> Normal
A71: 39 | B71: Male | C71: 50,000 - 70,000 | D71: 5 | E71: 2 | F71: car, Commercial vehicle | I71: Diesel | J71: Petrol | Q71: 6 | R71: 22 | S71: 25 | T71: 8 | U71: 45 | V71: 65 | W71: 10000 | X71: Reliance | Y71: 12 | Z71: Business | AA71: Never | AB71: I don’t use public transport | AC71: No | AD71: =IF(OR(Form_Responses34[[#This Row],[Total_monthly_fuel_expense ]]>10040,Form_Responses34[[#This Row],[Total_monthly_fuel_expense ]]<-4760),"Outlier","Normal") -> Normal
A72: 28 | B72: Female | C72: 30,000 - 50,000 | D72: 3 | E72: 1 | F72: car | I72: Petrol | Q72: 3 | R72: 16 | S72: 19 | W72: 2300 | X72: Indian Oil | Y72: 8 | Z72: Office | AA72: Monthly | AB72: Auto | AC72: Yes | AD72: =IF(OR(Form_Responses34[[#This Row],[Total_monthly_fuel_expense ]]>10040,Form_Responses34[[#This Row],[Total_monthly_fuel_expense ]]<-4760),"Outlier","Normal") -> Normal
A73: 45 | B73: Male | C73: 30,000 - 50,000 | D73: 4 | E73: 1 | F73: bikes | G73: Petrol | K73: 8 | L73: 10 | M73: 19 | W73: 2000 | X73: Indian Oil | Y73: 2 | Z73: work | AA73: Monthly | AB73: Bus | AC73: No | AD73: =IF(OR(Form_Responses34[[#This Row],[Total_monthly_fuel_expense ]]>10040,Form_Responses34[[#This Row],[Total_monthly_fuel_expense ]]<-4760),"Outlier","Normal") -> Normal
A74: 23 | B74: Male | C74: 30,000 - 50,000 | D74: 4 | E74: 2 | F74: bikes, car | G74: Petrol | I74: Petrol | K74: 3 | L74: 18 | M74: 10 | Q74: 5 | R74: 25 | S74: 40 | W74: 5000 | X74: Indian Oil | Y74: 12 | Z74: Office | AA74: Rarely | AB74: Auto | AC74: Maybe | AD74: =IF(OR(Form_Responses34[[#This Row],[Total_monthly_fuel_expense ]]>10040,Form_Responses34[[#This Row],[Total_monthly_fuel_expense ]]<-4760),"Outlier","Normal") -> Normal
A75: 21 | B75: Female | C75: below 10,000 | D75: 5 | E75: 1 | F75: Scooty | H75: Petrol | N75: 6 | O75: 10 | P75: 6 | W75: 1000 | X75: BPCL | Y75: 7 | Z75: College | AA75: Weekly | AB75: Bus | AC75: Yes | AD75: =IF(OR(Form_Responses34[[#This Row],[Total_monthly_fuel_expense ]]>10040,Form_Responses34[[#This Row],[Total_monthly_fuel_expense ]]<-4760),"Outlier","Normal") -> Normal
A76: 34 | B76: Male | C76: 10,000 - 30,000 | D76: 6 | E76: 2 | F76: bikes, Commercial vehicle | G76: Petrol | J76: Diesel | K76: 9 | L76: 12 | M76: 7 | T76: 7 | U76: 35 | V76: 70 | W76: 9500 | X76: HP | Y76: 8 | Z76: Agriculture-related | AA76: Rarely | AB76: Auto | AC76: No | AD76: =IF(OR(Form_Responses34[[#This Row],[Total_monthly_fuel_expense ]]>10040,Form_Responses34[[#This Row],[Total_monthly_fuel_expense ]]<-4760),"Outlier","Normal") -> Normal
A77: 25 | B77: Female | C77: 50,000 - 70,000 | D77: 3 | E77: 2 | F77: Scooty, car | H77: Petrol | I77: Petrol | N77: 3 | O77: 5 | P77: 4 | Q77: 2 | R77: 20 | S77: 5 | W77: 4800 | X77: Indian Oil | Y77: 9 | Z77: Office | AA77: Rarely | AB77: Other | AC77: Maybe | AD77: =IF(OR(Form_Responses34[[#This Row],[Total_monthly_fuel_expense ]]>10040,Form_Responses34[[#This Row],[Total_monthly_fuel_expense ]]<-4760),"Outlier","Normal") -> Normal
A78: 29 | B78: Male | C78: above 1,00,000 | D78: 4 | E78: 3 | F78: car, Commercial vehicle | I78: Petrol | J78: Diesel | Q78: 1 | R78: 30 | S78: 50 | T78: 3 | U78: 40 | V78: 80 | W78: 14000 | X78: Shell | Y78: 10 | Z78: Business | AA78: Never | AB78: I don’t use public transport | AC78: No | AD78: =IF(OR(Form_Responses34[[#This Row],[Total_monthly_fuel_expense ]]>10040,Form_Responses34[[#This Row],[Total_monthly_fuel_expense ]]<-4760),"Outlier","Normal") -> Outlier
A79: 22 | B79: Female | C79: 10,000 - 30,000 | D79: 5 | E79: 1 | F79: bikes | G79: Petrol | K79: 10 | L79: 8 | M79: 6 | W79: 1500 | X79: Indian Oil | Y79: 6 | Z79: Market/Shopping | AA79: Monthly | AB79: Auto | AC79: Maybe | AD79: =IF(OR(Form_Responses34[[#This Row],[Total_monthly_fuel_expense ]]>10040,Form_Responses34[[#This Row],[Total_monthly_fuel_expense ]]<-4760),"Outlier","Normal") -> Normal
A80: 20 | B80: Male | C80: below 10,000 | D80: 3 | E80: 1 | F80: bikes | G80: Petrol | K80: 2 | L80: 22 | M80: 12 | W80: 2000 | X80: BPCL | Y80: 11 | Z80: College | AA80: Weekly | AB80: Shared Rickshaw | AC80: Yes | AD80: =IF(OR(Form_Responses34[[#This Row],[Total_monthly_fuel_expense ]]>10040,Form_Responses34[[#This Row],[Total_monthly_fuel_expense ]]<-4760),"Outlier","Normal") -> Normal
A81: 32 | B81: Male | C81: below 10,000 | D81: 4 | E81: 1 | F81: Scooty | H81: Petrol | N81: 5 | O81: 12 | P81: 7 | W81: 1200 | X81: HP | Y81: 5 | Z81: work | AA81: Weekly | AB81: Bus | AC81: No | AD81: =IF(OR(Form_Responses34[[#This Row],[Total_monthly_fuel_expense ]]>10040,Form_Responses34[[#This Row],[Total_monthly_fuel_expense ]]<-4760),"Outlier","Normal") -> Normal
A82: 37 | B82: Male | C82: 50,000 - 70,000 | D82: 3 | E82: 2 | F82: car, Electric Vehicle | I82: Petrol | Q82: 6 | R82: 18 | S82: 30 | W82: 3200 | X82: Indian Oil | Y82: 10 | Z82: Office | AA82: Rarely | AB82: I don’t use public transport | AC82: Yes | AD82: =IF(OR(Form_Responses34[[#This Row],[Total_monthly_fuel_expense ]]>10040,Form_Responses34[[#This Row],[Total_monthly_fuel_expense ]]<-4760),"Outlier","Normal") -> Normal
A83: 19 | B83: Female | C83: 10,000 - 30,000 | D83: 6 | E83: 1 | F83: Scooty | H83: Petrol | N83: 3 | O83: 6 | P83: 5 | W83: 900 | X83: Indian Oil | Y83: 4 | Z83: College | AA83: Daily | AB83: Bus | AC83: Yes | AD83: =IF(OR(Form_Responses34[[#This Row],[Total_monthly_fuel_expense ]]>10040,Form_Responses34[[#This Row],[Total_monthly_fuel_expense ]]<-4760),"Outlier","Normal") -> Normal
A84: 40 | B84: Male | C84: 30,000 - 50,000 | D84: 6 | E84: 2 | F84: bikes, Commercial vehicle | G84: Petrol | J84: Diesel | K84: 6 | L84: 15 | M84: 9 | T84: 10 | U84: 50 | V84: 90 | W84: 12000 | X84: HP | Y84: 6 | Z84: Agriculture-related | AA84: Rarely | AB84: Other | AC84: No | AD84: =IF(OR(Form_Responses34[[#This Row],[Total_monthly_fuel_expense ]]>10040,Form_Responses34[[#This Row],[Total_monthly_fuel_expense ]]<-4760),"Outlier","Normal") -> Outlier
A85: 18 | B85: Female | C85: 50,000 - 70,000 | D85: 6 | E85: 2 | F85: bikes | G85: Petrol | K85: 6 | L85: 10 | M85: 20 | W85: 650 | X85: Indian Oil | Y85: 10 | Z85: Office | AA85: Weekly | AB85: Bus | AC85: Yes | AD85: =IF(OR(Form_Responses34[[#This Row],[Total_monthly_fuel_expense ]]>10040,Form_Responses34[[#This Row],[Total_monthly_fuel_expense ]]<-4760),"Outlier","Normal") -> Normal
A86: 36 | B86: Male | C86: 30,000 - 50,000 | D86: 5 | E86: 2 | F86: bikes, car | G86: Petrol | I86: Petrol | K86: 7 | L86: 12 | M86: 9 | Q86: 4 | R86: 16 | S86: 21 | W86: 4200 | X86: BPCL | Y86: 7 | Z86: Business | AA86: Never | AB86: I don’t use public transport | AC86: Maybe | AD86: =IF(OR(Form_Responses34[[#This Row],[Total_monthly_fuel_expense ]]>10040,Form_Responses34[[#This Row],[Total_monthly_fuel_expense ]]<-4760),"Outlier","Normal") -> Normal
A87: 28 | B87: Female | C87: 50,000 - 70,000 | D87: 3 | E87: 1 | F87: car | I87: Petrol | Q87: 3 | R87: 18 | S87: 20 | W87: 2600 | X87: Indian Oil | Y87: 9 | Z87: Office | AA87: Monthly | AB87: Auto | AC87: Yes | AD87: =IF(OR(Form_Responses34[[#This Row],[Total_monthly_fuel_expense ]]>10040,Form_Responses34[[#This Row],[Total_monthly_fuel_expense ]]<-4760),"Outlier","Normal") -> Normal
A88: 42 | B88: Male | C88: 10,000 - 30,000 | D88: 6 | E88: 1 | F88: bikes | G88: Petrol | K88: 11 | L88: 13 | M88: 10 | W88: 1100 | X88: HP | Y88: 5 | Z88: Agriculture-related | AA88: Rarely | AB88: Train | AC88: No | AD88: =IF(OR(Form_Responses34[[#This Row],[Total_monthly_fuel_expense ]]>10040,Form_Responses34[[#This Row],[Total_monthly_fuel_expense ]]<-4760),"Outlier","Normal") -> Normal
A89: 24 | B89: Female | C89: below 10,000 | D89: 4 | E89: 1 | F89: Scooty | H89: Petrol | N89: 2 | O89: 8 | P89: 5 | W89: 650 | X89: Shell | Y89: 4 | Z89: College | AA89: Weekly | AB89: Auto, Shared Rickshaw | AC89: Yes | AD89: =IF(OR(Form_Responses34[[#This Row],[Total_monthly_fuel_expense ]]>10040,Form_Responses34[[#This Row],[Total_monthly_fuel_expense ]]<-4760),"Outlier","Normal") -> Normal
A90: 29 | B90: Male | C90: 30,000 - 50,000 | D90: 3 | E90: 2 | F90: bikes, car | G90: Petrol | I90: Petrol | K90: 4 | L90: 10 | M90: 8 | Q90: 2 | R90: 14 | S90: 18 | W90: 3600 | X90: BPCL | Y90: 8 | Z90: Office | AA90: Rarely | AB90: Auto | AC90: Maybe | AD90: =IF(OR(Form_Responses34[[#This Row],[Total_monthly_fuel_expense ]]>10040,Form_Responses34[[#This Row],[Total_monthly_fuel_expense ]]<-4760),"Outlier","Normal") -> Normal
A91: 32 | B91: Male | C91: 10,000 - 30,000 | D91: 5 | E91: 1 | F91: bikes | G91: Petrol | K91: 9 | L91: 15 | M91: 11 | W91: 1300 | X91: HP | Y91: 6 | Z91: Agriculture-related | AA91: Rarely | AB91: Bus | AC91: No | AD91: =IF(OR(Form_Responses34[[#This Row],[Total_monthly_fuel_expense ]]>10040,Form_Responses34[[#This Row],[Total_monthly_fuel_expense ]]<-4760),"Outlier","Normal") -> Normal
A92: 23 | B92: Female | C92: 10,000 - 30,000 | D92: 4 | E92: 1 | F92: Scooty | H92: Petrol | N92: 2 | O92: 8 | P92: 5 | W92: 650 | X92: Indian Oil | Y92: 4 | Z92: College | AA92: Weekly | AB92: Auto | AC92: Yes | AD92: =IF(OR(Form_Responses34[[#This Row],[Total_monthly_fuel_expense ]]>10040,Form_Responses34[[#This Row],[Total_monthly_fuel_expense ]]<-4760),"Outlier","Normal") -> Normal
A93: 27 | B93: Male | C93: 30,000 - 50,000 | D93: 3 | E93: 2 | F93: bikes, car | G93: Petrol | I93: Petrol | K93: 4 | L93: 12 | M93: 9 | Q93: 2 | R93: 14 | S93: 17 | W93: 3800 | X93: BPCL | Y93: 10 | Z93: Office | AA93: Rarely | AB93: Bus | AC93: Maybe | AD93: =IF(OR(Form_Responses34[[#This Row],[Total_monthly_fuel_expense ]]>10040,Form_Responses34[[#This Row],[Total_monthly_fuel_expense ]]<-4760),"Outlier","Normal") -> Normal
A94: 24 | B94: Female | C94: 10,000 - 30,000 | D94: 4 | E94: 1 | F94: Scooty | H94: Petrol | N94: 3 | O94: 9 | P94: 6 | W94: 720 | X94: BPCL | Y94: 7 | Z94: Office | AA94: Weekly | AB94: Bus | AC94: Yes | AD94: =IF(OR(Form_Responses34[[#This Row],[Total_monthly_fuel_expense ]]>10040,Form_Responses34[[#This Row],[Total_monthly_fuel_expense ]]<-4760),"Outlier","Normal") -> Normal
A95: 29 | B95: Female | C95: 30,000 - 50,000 | D95: 3 | E95: 1 | F95: car | I95: Petrol | Q95: 4 | R95: 15 | S95: 18 | W95: 2300 | X95: Indian Oil | Y95: 9 | Z95: Office | AA95: Monthly | AB95: Auto | AC95: Yes | AD95: =IF(OR(Form_Responses34[[#This Row],[Total_monthly_fuel_expense ]]>10040,Form_Responses34[[#This Row],[Total_monthly_fuel_expense ]]<-4760),"Outlier","Normal") -> Normal
A96: 31 | B96: Male | C96: 10,000 - 30,000 | D96: 5 | E96: 1 | F96: bikes | G96: Petrol | K96: 6 | L96: 13 | M96: 10 | W96: 1200 | X96: Indian Oil | Y96: 5 | Z96: work | AA96: Rarely | AB96: Bus | AC96: No | AD96: =IF(OR(Form_Responses34[[#This Row],[Total_monthly_fuel_expense ]]>10040,Form_Responses34[[#This Row],[Total_monthly_fuel_expense ]]<-4760),"Outlier","Normal") -> Normal
A97: 22 | B97: Female | C97: below 10,000 | D97: 4 | E97: 1 | F97: Scooty | H97: Petrol | N97: 1 | O97: 7 | P97: 5 | W97: 600 | X97: Indian Oil | Y97: 3 | Z97: College | AA97: Monthly | AB97: Auto | AC97: Yes | AD97: =IF(OR(Form_Responses34[[#This Row],[Total_monthly_fuel_expense ]]>10040,Form_Responses34[[#This Row],[Total_monthly_fuel_expense ]]<-4760),"Outlier","Normal") -> Normal
A98: 40 | B98: Male | C98: 30,000 - 50,000 | D98: 6 | E98: 2 | F98: bikes, Commercial vehicle | G98: Petrol | J98: Diesel | K98: 10 | L98: 14 | M98: 11 | T98: 12 | U98: 45 | V98: 60 | W98: 8200 | X98: HP | Y98: 4 | Z98: Agriculture-related | AA98: Rarely | AB98: Bus | AC98: No | AD98: =IF(OR(Form_Responses34[[#This Row],[Total_monthly_fuel_expense ]]>10040,Form_Responses34[[#This Row],[Total_monthly_fuel_expense ]]<-4760),"Outlier","Normal") -> Normal
A99: 45 | B99: Male | C99: 50,000 - 70,000 | D99: 6 | E99: 2 | F99: bikes, Commercial vehicle | G99: Petrol | J99: Diesel | K99: 8 | L99: 18 | M99: 13 | T99: 11 | U99: 50 | V99: 70 | W99: 9000 | X99: HP | Y99: 8 | Z99: Business | AA99: Never | AB99: I don’t use public transport | AC99: No | AD99: =IF(OR(Form_Responses34[[#This Row],[Total_monthly_fuel_expense ]]>10040,Form_Responses34[[#This Row],[Total_monthly_fuel_expense ]]<-4760),"Outlier","Normal") -> Normal
A100: 26 | B100: Female | C100: 30,000 - 50,000 | D100: 3 | E100: 1 | F100: car | I100: Petrol | Q100: 3 | R100: 14 | S100: 19 | W100: 2400 | X100: Indian Oil | Y100: 8 | Z100: Office | AA100: Monthly | AB100: Bus | AC100: Maybe | AD100: =IF(OR(Form_Responses34[[#This Row],[Total_monthly_fuel_expense ]]>10040,Form_Responses34[[#This Row],[Total_monthly_fuel_expense ]]<-4760),"Outlier","Normal") -> Normal
...

Sheet Clean_Data_Summary
A5: Colunm | B5: (clean data)blank | C5: Min | D5: max | E5: Average | F5: median | G5: MODE | H5: count
A6: fuel_required_Bike | B6: =COUNTBLANK(Form_Responses34[fuel_required_Bike ]) -> 212 | H6: =COUNTA(Form_Responses34[fuel_required_Bike ]) -> 355
A7: fuel_required_Scooty | B7: =COUNTBLANK(Form_Responses34[fuel_required_Scooty ]) -> 402 | H7: =COUNTA(Form_Responses34[fuel_required_Scooty ]) -> 165
A8: fuel_required_Car | B8: =COUNTBLANK(Form_Responses34[fuel_required_Car ]) -> 398 | H8: =COUNTA(Form_Responses34[fuel_required_Car ]) -> 169
A9: fuel_required_Commercial | B9: =COUNTBLANK(Form_Responses34[fuel_required_Commercial ]) -> 481 | H9: =COUNTA(Form_Responses34[fuel_required_Commercial ]) -> 86
A10: Age_bike | B10: =COUNTBLANK(Form_Responses34[Age_bike ]) -> 212 | C10: =MIN(clean_data!K2:K568) -> 1 | D10: =MAX(clean_data!K2:K568) -> 38 | E10: =AVEDEV(clean_data!K2:K568) -> 3.4466177 | F10: =MEDIAN(clean_data!K2:K568) -> 6 | G10: =_xlfn.MODE.MULT(clean_data!K2:K568) -> 6 | H10: =COUNT(Form_Responses34[Age_bike ]) -> 355 | I10: year
A11: Daily_distance_travelled_bike | B11: =COUNTBLANK(Form_Responses34[Daily_distance_travelled_bike ]) -> 212 | C11: =MIN(clean_data!L2:L568) -> 1 | D11: =MAX(clean_data!L2:L569) -> 120 | E11: =AVEDEV(clean_data!L2:L569) -> 6.3055743 | F11: =MEDIAN(clean_data!L2:L569) -> 12 | G11: =_xlfn.MODE.MULT(clean_data!L2:L569) -> 10 | H11: =COUNT(Form_Responses34[Daily_distance_travelled_bike ]) -> 355 | I11: km
A12: fuel_monthly_bike | B12: =COUNTBLANK(Form_Responses34[fuel_monthly_bikes]) -> 212 | C12: =MIN(clean_data!M2:M568) -> 1 | D12: =MAX(clean_data!M2:M568) -> 90 | E12: =AVEDEV(clean_data!M2:M570) -> 5.6650347 | F12: =MEDIAN(clean_data!M2:M570) -> 8 | G12: =_xlfn.MODE.MULT(clean_data!M2:M570) -> 5 | H12: =COUNT(Form_Responses34[fuel_monthly_bikes]) -> 355 | I12: lit
A13: Age_Scooty | B13: =COUNTBLANK(Form_Responses34[Age_Scooty]) -> 402 | C13: =MIN(clean_data!N2:N568) -> 1 | D13: =MAX(clean_data!N2:N568) -> 25 | E13: =AVEDEV(clean_data!N2:N571) -> 1.9023691 | F13: =MEDIAN(clean_data!N2:N571) -> 3 | G13: =_xlfn.MODE.MULT(clean_data!N2:N571) -> 3 | H13: =COUNT(Form_Responses34[Age_Scooty]) -> 165 | I13: yrs
A14: Daily_distance_travelled_Scooty | B14: =COUNTBLANK(Form_Responses34[Daily_distance_travelled_Scooty ]) -> 402 | C14: =MIN(clean_data!O2:O572) -> 1 | D14: =MAX(clean_data!O2:O568) -> 50 | E14: =AVEDEV(clean_data!O2:O572) -> 3.4461708 | F14: =MEDIAN(clean_data!O2:O572) -> 8 | G14: =_xlfn.MODE.MULT(clean_data!O2:O572) -> 10 | H14: =COUNT(Form_Responses34[Daily_distance_travelled_Scooty ]) -> 165 | I14: km
A15: Fuel_required_monthly_scooty | B15: =COUNTBLANK(Form_Responses34[Fuel_required_monthly_scooty]) -> 402 | C15: =MIN(clean_data!P2:P572) -> 2 | D15: =MAX(clean_data!P2:P568) -> 46 | E15: =AVEDEV(clean_data!P2:P573) -> 3.2916804 | F15: =MEDIAN(clean_data!P2:P573) -> 6 | G15: =_xlfn.MODE.MULT(clean_data!P2:P573) -> 5 | H15: =COUNT(Form_Responses34[Fuel_required_monthly_scooty]) -> 165 | I15: lit
A16: Age_Car | B16: =COUNTBLANK(Form_Responses34[[#All],[ Age_Car]]) -> 398 | C16: =MIN(clean_data!Q6:Q572) -> 1 | D16: =MAX(clean_data!Q2:Q568) -> 13 | E16: =AVEDEV(clean_data!Q2:Q574) -> 1.5685025 | F16: =MEDIAN(clean_data!Q2:Q574) -> 5 | G16: =_xlfn.MODE.MULT(clean_data!Q2:Q574) -> 5 | H16: =COUNT(Form_Responses34[[#All],[ Age_Car]]) -> 169 | I16: yrs
A17: Daily_distance_travelled_Car | B17: =COUNTBLANK(Form_Responses34[Daily_distance_travelled_Car ]) -> 398 | C17: =MIN(clean_data!R2:R572) -> 8 | D17: =MAX(clean_data!R2:R568) -> 100 | E17: =AVEDEV(clean_data!R2:R575) -> 5.7728371 | F17: =MEDIAN(clean_data!R2:R575) -> 24 | G17: =_xlfn.MODE.MULT(clean_data!R2:R575) -> 25 | H17: =COUNT(Form_Responses34[Daily_distance_travelled_Car ]) -> 169 | I17: km
A18: Fuel_required_monthly_car | B18: =COUNTBLANK(Form_Responses34[Fuel_required_monthly_car]) -> 398 | C18: =MIN(clean_data!S2:S576) -> 5 | D18: =MAX(clean_data!S2:S568) -> 70 | E18: =AVEDEV(clean_data!S2:S576) -> 7.6939883 | F18: =MEDIAN(clean_data!S2:S576) -> 24 | G18: =_xlfn.MODE.MULT(clean_data!S2:S576) -> 22 | H18: =COUNT(Form_Responses34[Fuel_required_monthly_car]) -> 169 | I18: lit
A19: Age_commercial | B19: =COUNTBLANK(Form_Responses34[[#All],[ Age_commercial]]) -> 481 | C19: =MIN(clean_data!T10:T576) -> 2 | D19: =MAX(clean_data!T2:T568) -> 24 | E19: =AVEDEV(clean_data!T2:T577) -> 3.8658734 | F19: =MEDIAN(clean_data!T2:T577) -> 12 | G19: =_xlfn.MODE.MULT(clean_data!T2:T577) -> 10 | H19: =COUNT(Form_Responses34[[#All],[ Age_commercial]]) -> 86 | I19: yrs
A20: Daily_distance_travelled_commercial | B20: =COUNTBLANK(Form_Responses34[Daily_distance_travelled_commercial]) -> 481 | C20: =MIN(clean_data!U10:U576) -> 0 | D20: =MAX(clean_data!U2:U568) -> 75 | E20: =AVEDEV(clean_data!U2:U578) -> 13.777177 | F20: =MEDIAN(clean_data!U2:U578) -> 45 | G20: =_xlfn.MODE.MULT(clean_data!U2:U578) -> 45 | H20: =COUNT(Form_Responses34[Daily_distance_travelled_commercial]) -> 86 | I20: km
A21: Fuel_required_monthly_commercial | B21: =COUNTBLANK(Form_Responses34[Fuel_required_monthly_commercial]) -> 481 | C21: =MIN(clean_data!V2:V576) -> 1 | D21: =MAX(clean_data!V2:V568) -> 110 | E21: =AVEDEV(clean_data!V2:V579) -> 16.092482 | F21: =MEDIAN(clean_data!V2:V579) -> 70 | G21: =_xlfn.MODE.MULT(clean_data!V2:V579) -> 70 | H21: =COUNT(Form_Responses34[Fuel_required_monthly_commercial]) -> 86 | I21: lit
A22: Total_monthly_fuel_expense | B22: =COUNTBLANK(Form_Responses34[Total_monthly_fuel_expense ]) -> 0 | C22: =MIN(clean_data!W2:W580) -> 200 | D22: =MAX(clean_data!W2:W568) -> 20000 | E22: =AVEDEV(clean_data!W2:W580) -> 2704.8788 | F22: =MEDIAN(clean_data!W2:W580) -> 1600 | G22: =_xlfn.MODE.MULT(clean_data!W2:W580) -> 650 | H22: =COUNT(Form_Responses34[Total_monthly_fuel_expense ]) -> 567 | I22: rs
A26: SUMMARY
A27: Avg Monthly Fuel Expense per Household | B27: =AVERAGE(Form_Responses34[Total_monthly_fuel_expense ]) -> 3336.4427

Sheet Outlier_detection
A1: Summary sheet for outliers - calculate fences
A2: Q1 | B2: =QUARTILE(Form_Responses34[Total_monthly_fuel_expense ],1) -> 790
A3: Q3 | B3: =QUARTILE(Form_Responses34[Total_monthly_fuel_expense ],3) -> 4490
A4: IQR | B4: =B3-B2 -> 3700
A5: Lower fence | B5: =B2-1.5*B4 -> -4760
A6: Upper fence | B6: =B3+1.5*B4 -> 10040
A7: High outliers | B7: =COUNTIF(Form_Responses34[Total_monthly_fuel_expense ],">"&Outlier_detection!B6) -> 35
A8: Low outliers | B8: =COUNTIF(Form_Responses34[Total_monthly_fuel_expense ],"<"&Outlier_detection!B5) -> 0

Sheet Descriptive_Statistics
A1: Discriptive Statistics Table
A3: Variable | B3: N | C3: Mean | D3: Median | E3: SD | F3: Min | G3: Max | H3: Skewness | I3: Distribution Type
A4: Total_Fuel_Expense | B4: 567 | C4: =AVERAGE(Form_Responses34[Total_monthly_fuel_expense ]) -> 3336.4427 | D4: =MEDIAN(Form_Responses34[Total_monthly_fuel_expense ]) -> 1600 | E4: =STDEV(Form_Responses34[Total_monthly_fuel_expense ]) -> 3508.029 | F4: =MIN(Form_Responses34[Total_monthly_fuel_expense ]) -> 200 | G4: =MAX(Form_Responses34[Total_monthly_fuel_expense ]) -> 20000 | H4: =SKEW(Form_Responses34[Total_monthly_fuel_expense ]) -> 1.6117876 | I4: Strongly right-skewed
A5: Per_Capita_Fuel | B5: 567 | C5: 750 | D5: 400 | E5: 763 | F5: 40 | G5: 5000 | H5: =SKEW(Per_Capita_Expenses!C1:C568) -> 1.7721822 | I5: Strongly right-skewed
A6: Num_Vehicles | B6: 567 | C6: =AVERAGE(Form_Responses34[Num_vehicles_in_family ]) -> 1.4409171 | D6: =MEDIAN(Form_Responses34[Num_vehicles_in_family ]) -> 1 | E6: =STDEV(Form_Responses34[Num_vehicles_in_family ]) -> 0.62595612 | F6: =MIN(Form_Responses34[Num_vehicles_in_family ]) -> 1 | G6: =MAX(Form_Responses34[Num_vehicles_in_family ]) -> 4 | H6: =SKEW(Form_Responses34[Num_vehicles_in_family ]) -> 1.1570272 | I6: Strongly right-skewed
A7: Family_Members | B7: 567 | C7: =AVERAGE(Form_Responses34[Total_family _members ]) -> 4.4620811 | D7: =MEDIAN(Form_Responses34[Total_family _members ]) -> 4 | E7: =STDEV(Form_Responses34[Total_family _members ]) -> 0.99017679 | F7: =MIN(Form_Responses34[Total_family _members ]) -> 2 | G7: =MAX(Form_Responses34[Total_family _members ]) -> 10 | H7: =SKEW(Form_Responses34[Total_family _members ]) -> 0.29729671 | I7: Approximately symmetric
A8: Home_Work_Distance | B8: 567 | C8: =AVERAGE(Form_Responses34[Distance_home_ workplace]) -> 8.340388 | D8: =MEDIAN(Form_Responses34[Distance_home_ workplace]) -> 7 | E8: =STDEV(Form_Responses34[Distance_home_ workplace]) -> 4.9046212 | F8: =MIN(Form_Responses34[Distance_home_ workplace]) -> 1 | G8: =MAX(Form_Responses34[Distance_home_ workplace]) -> 40 | H8: =SKEW(Form_Responses34[Distance_home_ workplace]) -> 1.7491891 | I8: Strongly right-skewed

Sheet Pie_Chart
A1: Vehicle type | B1: counts
A2: Bike | B2: =COUNTIF('Fuel_Data_Used_Avg_Fuel(l)'!G2:G568,1) -> 355
A3: Car | B3: =COUNTIF('Fuel_Data_Used_Avg_Fuel(l)'!H2:H568,1) -> 165
A4: Scooty | B4: =COUNTIF('Fuel_Data_Used_Avg_Fuel(l)'!I2:I568,1) -> 169
A5: Commercial Vehicle | B5: =COUNTIF('Fuel_Data_Used_Avg_Fuel(l)'!J2:J568,1) -> 86

Sheet Box_plot
A2: Summary for Box Plot | G2: Segment heights for Box Plot
A3: Statistic | B3: 1 Vehicle | C3: 2 Vehicle | D3: 3 Vehicle | E3: 4 Vehicle | G3: Statistic | H3: 1 Vehicle | I3: 2 Vehicle | J3: 3 Vehicle
A4: Min | B4: =MIN(ANOVA1!D:D) -> 260 | C4: =MIN(ANOVA1!E:E) -> 330 | D4: =MIN(ANOVA1!F:F) -> 200 | E4: =MIN(ANOVA1!G:G) -> 15000 | G4: Min | H4: 260 | I4: 330 | J4: 200
A5: Q1 | B5: =QUARTILE(ANOVA1!D:D,1) -> 650 | C5: =QUARTILE(ANOVA1!E:E,1) -> 3600 | D5: =QUARTILE(ANOVA1!F:F,1) -> 5125 | E5: =QUARTILE(ANOVA1!G:G,1) -> 15000 | G5: Q1 | H5: =650-H4 -> 390 | I5: =3600-I4 -> 3270 | J5: =5125-J4 -> 4925
A6: Median | B6: =QUARTILE(ANOVA1!D:D,2) -> 1000 | C6: =QUARTILE(ANOVA1!E:E,2) -> 4800 | D6: =QUARTILE(ANOVA1!F:F,2) -> 9450 | E6: =QUARTILE(ANOVA1!G:G,2) -> 15000 | G6: Median | H6: =1000-650 -> 350 | I6: =4800-3600 -> 1200 | J6: =9450-5125 -> 4325
A7: Q3 | B7: =QUARTILE(ANOVA1!D:D,3) -> 1800 | C7: =QUARTILE(ANOVA1!E:E,3) -> 8050 | D7: =QUARTILE(ANOVA1!F:F,3) -> 12000 | E7: =QUARTILE(ANOVA1!G:G,3) -> 15000 | G7: Q3 | H7: =1800-1000 -> 800 | I7: =8050-4800 -> 3250 | J7: =12000-9450 -> 2550
A8: Max | B8: =MAX(ANOVA1!D:D) -> 20000 | C8: =MAX(ANOVA1!E:E) -> 20000 | D8: =MAX(ANOVA1!F:F) -> 15600 | E8: =MAX(ANOVA1!G:G) -> 15000 | G8: Max | H8: =20000-1800 -> 18200 | I8: =20000-8050 -> 11950 | J8: =15600-12000 -> 3600
B11: Invisible | C11: Lower Whisker | D11: IQR Lower | E11: IQR Upper | F11: Upper Whisker
A12: 1 Vehicle | B12: 260 | C12: 390 | D12: 350 | E12: 800 | F12: 18200
A13: 2 Vehicle | B13: 330 | C13: 3270 | D13: 1200 | E13: 3250 | F13: 11950
A14: 3 Vehicle | B14: 200 | C14: 4925 | D14: 4325 | E14: 2550 | F14: 3600

Sheet Pivot_Charts
A1: Pivot 1 | G1: Pivot 2
A2: Row Labels | B2: Sum of Has_Bike | C2: Sum of Has_Car | D2: Sum of Has_Scooty | E2: Sum of Has_Commercial | G2: Row Labels | H2: Count of Total_monthly_fuel_expense
A3: Female | B3: 85 | C3: 41 | D3: 146 | E3: 2 | G3: 10,000-30,000 | H3: 101
A4: Male | B4: 270 | C4: 128 | D4: 19 | E4: 84 | G4: 30,000-50,000 | H4: 203
A5: Grand Total | B5: 355 | C5: 169 | D5: 165 | E5: 86 | G5: 50,000-70,000 | H5: 98
G6: 70,000-1,00,000 | H6: 23
G7: above 1,00,000 | H7: 17
G8: below 10,000 | H8: 125
G9: (blank)
G10: Grand Total | H10: 567

Sheet Fuel_Data_Used_Avg_Fuel(l)
A1: Type_vehicle | B1: fuel_monthly_bikes | C1: Fuel_required_monthly_scooty | D1: Fuel_required_monthly_car | E1: Fuel_required_monthly_commercial | F1: Total_monthly_fuel_expense | G1: Has_Bike | H1: Has_Scooty | I1: Has_Car | J1: Has_Commercial | K1: Has_EV | L1: Gender
A2: bikes | B2: 30 | F2: 3000 | G2: =IF(ISNUMBER(SEARCH("bike",A2)),1,0) -> 1 | H2: =IF(ISNUMBER(SEARCH("Scooty",A2)),1,0) -> 0 | I2: =IF(ISNUMBER(SEARCH("Car",A2)),1,0) -> 0 | J2: =IF(ISNUMBER(SEARCH("Commercial vehicle",A2)),1,0) -> 0 | K2: =IF(ISNUMBER(SEARCH("Electric Vehicle",A2)),1,0) -> 0 | L2: Female
A3: bikes, Commercial vehicle | B3: 75 | E3: 1 | F3: 9200 | G3: =IF(ISNUMBER(SEARCH("bike",A3)),1,0) -> 1 | H3: =IF(ISNUMBER(SEARCH("Scooty",A3)),1,0) -> 0 | I3: =IF(ISNUMBER(SEARCH("Car",A3)),1,0) -> 0 | J3: =IF(ISNUMBER(SEARCH("Commercial vehicle",A3)),1,0) -> 1 | K3: =IF(ISNUMBER(SEARCH("Electric Vehicle",A3)),1,0) -> 0 | L3: Male
A4: Scooty | C4: 10 | F4: 1000 | G4: =IF(ISNUMBER(SEARCH("bike",A4)),1,0) -> 0 | H4: =IF(ISNUMBER(SEARCH("Scooty",A4)),1,0) -> 1 | I4: =IF(ISNUMBER(SEARCH("Car",A4)),1,0) -> 0 | J4: =IF(ISNUMBER(SEARCH("Commercial vehicle",A4)),1,0) -> 0 | K4: =IF(ISNUMBER(SEARCH("Electric Vehicle",A4)),1,0) -> 0 | L4: Female
A5: bikes | B5: 20 | F5: 1000 | G5: =IF(ISNUMBER(SEARCH("bike",A5)),1,0) -> 1 | H5: =IF(ISNUMBER(SEARCH("Scooty",A5)),1,0) -> 0 | I5: =IF(ISNUMBER(SEARCH("Car",A5)),1,0) -> 0 | J5: =IF(ISNUMBER(SEARCH("Commercial vehicle",A5)),1,0) -> 0 | K5: =IF(ISNUMBER(SEARCH("Electric Vehicle",A5)),1,0) -> 0 | L5: Male
A6: bikes, car, Commercial vehicle | B6: 8 | D6: 45 | E6: 60 | F6: 10000 | G6: =IF(ISNUMBER(SEARCH("bike",A6)),1,0) -> 1 | H6: =IF(ISNUMBER(SEARCH("Scooty",A6)),1,0) -> 0 | I6: =IF(ISNUMBER(SEARCH("Car",A6)),1,0) -> 1 | J6: =IF(ISNUMBER(SEARCH("Commercial vehicle",A6)),1,0) -> 1 | K6: =IF(ISNUMBER(SEARCH("Electric Vehicle",A6)),1,0) -> 0 | L6: Male
A7: Scooty | C7: 10 | F7: 1200 | G7: =IF(ISNUMBER(SEARCH("bike",A7)),1,0) -> 0 | H7: =IF(ISNUMBER(SEARCH("Scooty",A7)),1,0) -> 1 | I7: =IF(ISNUMBER(SEARCH("Car",A7)),1,0) -> 0 | J7: =IF(ISNUMBER(SEARCH("Commercial vehicle",A7)),1,0) -> 0 | K7: =IF(ISNUMBER(SEARCH("Electric Vehicle",A7)),1,0) -> 0 | L7: Female
A8: bikes, car | B8: 20 | D8: 70 | F8: 1000 | G8: =IF(ISNUMBER(SEARCH("bike",A8)),1,0) -> 1 | H8: =IF(ISNUMBER(SEARCH("Scooty",A8)),1,0) -> 0 | I8: =IF(ISNUMBER(SEARCH("Car",A8)),1,0) -> 1 | J8: =IF(ISNUMBER(SEARCH("Commercial vehicle",A8)),1,0) -> 0 | K8: =IF(ISNUMBER(SEARCH("Electric Vehicle",A8)),1,0) -> 0 | L8: Female
A9: bikes | B9: 28 | F9: 3000 | G9: =IF(ISNUMBER(SEARCH("bike",A9)),1,0) -> 1 | H9: =IF(ISNUMBER(SEARCH("Scooty",A9)),1,0) -> 0 | I9: =IF(ISNUMBER(SEARCH("Car",A9)),1,0) -> 0 | J9: =IF(ISNUMBER(SEARCH("Commercial vehicle",A9)),1,0) -> 0 | K9: =IF(ISNUMBER(SEARCH("Electric Vehicle",A9)),1,0) -> 0 | L9: Male
A10: Scooty | C10: 12 | F10: 1500 | G10: =IF(ISNUMBER(SEARCH("bike",A10)),1,0) -> 0 | H10: =IF(ISNUMBER(SEARCH("Scooty",A10)),1,0) -> 1 | I10: =IF(ISNUMBER(SEARCH("Car",A10)),1,0) -> 0 | J10: =IF(ISNUMBER(SEARCH("Commercial vehicle",A10)),1,0) -> 0 | K10: =IF(ISNUMBER(SEARCH("Electric Vehicle",A10)),1,0) -> 0 | L10: Female
A11: car, Electric Vehicle | D11: 60 | F11: 9500 | G11: =IF(ISNUMBER(SEARCH("bike",A11)),1,0) -> 0 | H11: =IF(ISNUMBER(SEARCH("Scooty",A11)),1,0) -> 0 | I11: =IF(ISNUMBER(SEARCH("Car",A11)),1,0) -> 1 | J11: =IF(ISNUMBER(SEARCH("Commercial vehicle",A11)),1,0) -> 0 | K11: =IF(ISNUMBER(SEARCH("Electric Vehicle",A11)),1,0) -> 1 | L11: Male
A12: Scooty | C12: 8 | F12: 1500 | G12: =IF(ISNUMBER(SEARCH("bike",A12)),1,0) -> 0 | H12: =IF(ISNUMBER(SEARCH("Scooty",A12)),1,0) -> 1 | I12: =IF(ISNUMBER(SEARCH("Car",A12)),1,0) -> 0 | J12: =IF(ISNUMBER(SEARCH("Commercial vehicle",A12)),1,0) -> 0 | K12: =IF(ISNUMBER(SEARCH("Electric Vehicle",A12)),1,0) -> 0 | L12: Male
A13: bikes, Commercial vehicle | B13: 10 | E13: 70 | F13: 8000 | G13: =IF(ISNUMBER(SEARCH("bike",A13)),1,0) -> 1 | H13: =IF(ISNUMBER(SEARCH("Scooty",A13)),1,0) -> 0 | I13: =IF(ISNUMBER(SEARCH("Car",A13)),1,0) -> 0 | J13: =IF(ISNUMBER(SEARCH("Commercial vehicle",A13)),1,0) -> 1 | K13: =IF(ISNUMBER(SEARCH("Electric Vehicle",A13)),1,0) -> 0 | L13: Male
A14: bikes, car | B14: 12 | D14: 55 | F14: 6800 | G14: =IF(ISNUMBER(SEARCH("bike",A14)),1,0) -> 1 | H14: =IF(ISNUMBER(SEARCH("Scooty",A14)),1,0) -> 0 | I14: =IF(ISNUMBER(SEARCH("Car",A14)),1,0) -> 1 | J14: =IF(ISNUMBER(SEARCH("Commercial vehicle",A14)),1,0) -> 0 | K14: =IF(ISNUMBER(SEARCH("Electric Vehicle",A14)),1,0) -> 0 | L14: Female
A15: bikes, car | B15: 7 | D15: 70 | F15: 9000 | G15: =IF(ISNUMBER(SEARCH("bike",A15)),1,0) -> 1 | H15: =IF(ISNUMBER(SEARCH("Scooty",A15)),1,0) -> 0 | I15: =IF(ISNUMBER(SEARCH("Car",A15)),1,0) -> 1 | J15: =IF(ISNUMBER(SEARCH("Commercial vehicle",A15)),1,0) -> 0 | K15: =IF(ISNUMBER(SEARCH("Electric Vehicle",A15)),1,0) -> 0 | L15: Male
A16: bikes, Scooty, car | B16: 13 | C16: 9 | D16: 65 | F16: 9000 | G16: =IF(ISNUMBER(SEARCH("bike",A16)),1,0) -> 1 | H16: =IF(ISNUMBER(SEARCH("Scooty",A16)),1,0) -> 1 | I16: =IF(ISNUMBER(SEARCH("Car",A16)),1,0) -> 1 | J16: =IF(ISNUMBER(SEARCH("Commercial vehicle",A16)),1,0) -> 0 | K16: =IF(ISNUMBER(SEARCH("Electric Vehicle",A16)),1,0) -> 0 | L16: Male
A17: Scooty | C17: 7 | F17: 900 | G17: =IF(ISNUMBER(SEARCH("bike",A17)),1,0) -> 0 | H17: =IF(ISNUMBER(SEARCH("Scooty",A17)),1,0) -> 1 | I17: =IF(ISNUMBER(SEARCH("Car",A17)),1,0) -> 0 | J17: =IF(ISNUMBER(SEARCH("Commercial vehicle",A17)),1,0) -> 0 | K17: =IF(ISNUMBER(SEARCH("Electric Vehicle",A17)),1,0) -> 0 | L17: Female
A18: bikes, car | B18: 6 | D18: 25 | F18: 2000 | G18: =IF(ISNUMBER(SEARCH("bike",A18)),1,0) -> 1 | H18: =IF(ISNUMBER(SEARCH("Scooty",A18)),1,0) -> 0 | I18: =IF(ISNUMBER(SEARCH("Car",A18)),1,0) -> 1 | J18: =IF(ISNUMBER(SEARCH("Commercial vehicle",A18)),1,0) -> 0 | K18: =IF(ISNUMBER(SEARCH("Electric Vehicle",A18)),1,0) -> 0 | L18: Male
A19: bikes | B19: 18 | F19: 2300 | G19: =IF(ISNUMBER(SEARCH("bike",A19)),1,0) -> 1 | H19: =IF(ISNUMBER(SEARCH("Scooty",A19)),1,0) -> 0 | I19: =IF(ISNUMBER(SEARCH("Car",A19)),1,0) -> 0 | J19: =IF(ISNUMBER(SEARCH("Commercial vehicle",A19)),1,0) -> 0 | K19: =IF(ISNUMBER(SEARCH("Electric Vehicle",A19)),1,0) -> 0 | L19: Male
A20: Scooty | C20: 10 | F20: 1200 | G20: =IF(ISNUMBER(SEARCH("bike",A20)),1,0) -> 0 | H20: =IF(ISNUMBER(SEARCH("Scooty",A20)),1,0) -> 1 | I20: =IF(ISNUMBER(SEARCH("Car",A20)),1,0) -> 0 | J20: =IF(ISNUMBER(SEARCH("Commercial vehicle",A20)),1,0) -> 0 | K20: =IF(ISNUMBER(SEARCH("Electric Vehicle",A20)),1,0) -> 0 | L20: Female
A21: bikes, Commercial vehicle | B21: 10 | E21: 80 | F21: 11100 | G21: =IF(ISNUMBER(SEARCH("bike",A21)),1,0) -> 1 | H21: =IF(ISNUMBER(SEARCH("Scooty",A21)),1,0) -> 0 | I21: =IF(ISNUMBER(SEARCH("Car",A21)),1,0) -> 0 | J21: =IF(ISNUMBER(SEARCH("Commercial vehicle",A21)),1,0) -> 1 | K21: =IF(ISNUMBER(SEARCH("Electric Vehicle",A21)),1,0) -> 0 | L21: Male
A22: car | D22: 50 | F22: 6000 | G22: =IF(ISNUMBER(SEARCH("bike",A22)),1,0) -> 0 | H22: =IF(ISNUMBER(SEARCH("Scooty",A22)),1,0) -> 0 | I22: =IF(ISNUMBER(SEARCH("Car",A22)),1,0) -> 1 | J22: =IF(ISNUMBER(SEARCH("Commercial vehicle",A22)),1,0) -> 0 | K22: =IF(ISNUMBER(SEARCH("Electric Vehicle",A22)),1,0) -> 0 | L22: Female
A23: bikes, car, Electric Vehicle | B23: 6 | D23: 55 | F23: 8800 | G23: =IF(ISNUMBER(SEARCH("bike",A23)),1,0) -> 1 | H23: =IF(ISNUMBER(SEARCH("Scooty",A23)),1,0) -> 0 | I23: =IF(ISNUMBER(SEARCH("Car",A23)),1,0) -> 1 | J23: =IF(ISNUMBER(SEARCH("Commercial vehicle",A23)),1,0) -> 0 | K23: =IF(ISNUMBER(SEARCH("Electric Vehicle",A23)),1,0) -> 1 | L23: Male
A24: bikes | B24: 24 | F24: 2700 | G24: =IF(ISNUMBER(SEARCH("bike",A24)),1,0) -> 1 | H24: =IF(ISNUMBER(SEARCH("Scooty",A24)),1,0) -> 0 | I24: =IF(ISNUMBER(SEARCH("Car",A24)),1,0) -> 0 | J24: =IF(ISNUMBER(SEARCH("Commercial vehicle",A24)),1,0) -> 0 | K24: =IF(ISNUMBER(SEARCH("Electric Vehicle",A24)),1,0) -> 0 | L24: Male
A25: bikes, Scooty | B25: 9 | C25: 8 | F25: 3000 | G25: =IF(ISNUMBER(SEARCH("bike",A25)),1,0) -> 1 | H25: =IF(ISNUMBER(SEARCH("Scooty",A25)),1,0) -> 1 | I25: =IF(ISNUMBER(SEARCH("Car",A25)),1,0) -> 0 | J25: =IF(ISNUMBER(SEARCH("Commercial vehicle",A25)),1,0) -> 0 | K25: =IF(ISNUMBER(SEARCH("Electric Vehicle",A25)),1,0) -> 0 | L25: Female
A26: Scooty, car | C26: 9 | D26: 40 | F26: 5200 | G26: =IF(ISNUMBER(SEARCH("bike",A26)),1,0) -> 0 | H26: =IF(ISNUMBER(SEARCH("Scooty",A26)),1,0) -> 1 | I26: =IF(ISNUMBER(SEARCH("Car",A26)),1,0) -> 1 | J26: =IF(ISNUMBER(SEARCH("Commercial vehicle",A26)),1,0) -> 0 | K26: =IF(ISNUMBER(SEARCH("Electric Vehicle",A26)),1,0) -> 0 | L26: Female
A27: bikes, car | B27: 7 | D27: 70 | F27: 9700 | G27: =IF(ISNUMBER(SEARCH("bike",A27)),1,0) -> 1 | H27: =IF(ISNUMBER(SEARCH("Scooty",A27)),1,0) -> 0 | I27: =IF(ISNUMBER(SEARCH("Car",A27)),1,0) -> 1 | J27: =IF(ISNUMBER(SEARCH("Commercial vehicle",A27)),1,0) -> 0 | K27: =IF(ISNUMBER(SEARCH("Electric Vehicle",A27)),1,0) -> 0 | L27: Male
A28: bikes, Commercial vehicle | B28: 12 | E28: 65 | F28: 8200 | G28: =IF(ISNUMBER(SEARCH("bike",A28)),1,0) -> 1 | H28: =IF(ISNUMBER(SEARCH("Scooty",A28)),1,0) -> 0 | I28: =IF(ISNUMBER(SEARCH("Car",A28)),1,0) -> 0 | J28: =IF(ISNUMBER(SEARCH("Commercial vehicle",A28)),1,0) -> 1 | K28: =IF(ISNUMBER(SEARCH("Electric Vehicle",A28)),1,0) -> 0 | L28: Female
A29: bikes | B29: 20 | F29: 2400 | G29: =IF(ISNUMBER(SEARCH("bike",A29)),1,0) -> 1 | H29: =IF(ISNUMBER(SEARCH("Scooty",A29)),1,0) -> 0 | I29: =IF(ISNUMBER(SEARCH("Car",A29)),1,0) -> 0 | J29: =IF(ISNUMBER(SEARCH("Commercial vehicle",A29)),1,0) -> 0 | K29: =IF(ISNUMBER(SEARCH("Electric Vehicle",A29)),1,0) -> 0 | L29: Male
A30: bikes | B30: 26 | F30: 2900 | G30: =IF(ISNUMBER(SEARCH("bike",A30)),1,0) -> 1 | H30: =IF(ISNUMBER(SEARCH("Scooty",A30)),1,0) -> 0 | I30: =IF(ISNUMBER(SEARCH("Car",A30)),1,0) -> 0 | J30: =IF(ISNUMBER(SEARCH("Commercial vehicle",A30)),1,0) -> 0 | K30: =IF(ISNUMBER(SEARCH("Electric Vehicle",A30)),1,0) -> 0 | L30: Male
A31: bikes, Scooty, car | B31: 16 | C31: 6 | D31: 60 | F31: 9500 | G31: =IF(ISNUMBER(SEARCH("bike",A31)),1,0) -> 1 | H31: =IF(ISNUMBER(SEARCH("Scooty",A31)),1,0) -> 1 | I31: =IF(ISNUMBER(SEARCH("Car",A31)),1,0) -> 1 | J31: =IF(ISNUMBER(SEARCH("Commercial vehicle",A31)),1,0) -> 0 | K31: =IF(ISNUMBER(SEARCH("Electric Vehicle",A31)),1,0) -> 0 | L31: Male
A32: car | D32: 45 | F32: 5200 | G32: =IF(ISNUMBER(SEARCH("bike",A32)),1,0) -> 0 | H32: =IF(ISNUMBER(SEARCH("Scooty",A32)),1,0) -> 0 | I32: =IF(ISNUMBER(SEARCH("Car",A32)),1,0) -> 1 | J32: =IF(ISNUMBER(SEARCH("Commercial vehicle",A32)),1,0) -> 0 | K32: =IF(ISNUMBER(SEARCH("Electric Vehicle",A32)),1,0) -> 0 | L32: Female
A33: bikes, car | B33: 7 | D33: 65 | F33: 8500 | G33: =IF(ISNUMBER(SEARCH("bike",A33)),1,0) -> 1 | H33: =IF(ISNUMBER(SEARCH("Scooty",A33)),1,0) -> 0 | I33: =IF(ISNUMBER(SEARCH("Car",A33)),1,0) -> 1 | J33: =IF(ISNUMBER(SEARCH("Commercial vehicle",A33)),1,0) -> 0 | K33: =IF(ISNUMBER(SEARCH("Electric Vehicle",A33)),1,0) -> 0 | L33: Male
A34: bikes, Commercial vehicle | B34: 14 | E34: 55 | F34: 7000 | G34: =IF(ISNUMBER(SEARCH("bike",A34)),1,0) -> 1 | H34: =IF(ISNUMBER(SEARCH("Scooty",A34)),1,0) -> 0 | I34: =IF(ISNUMBER(SEARCH("Car",A34)),1,0) -> 0 | J34: =IF(ISNUMBER(SEARCH("Commercial vehicle",A34)),1,0) -> 1 | K34: =IF(ISNUMBER(SEARCH("Electric Vehicle",A34)),1,0) -> 0 | L34: Male
A35: bikes, car | B35: 12 | D35: 24 | F35: 5500 | G35: =IF(ISNUMBER(SEARCH("bike",A35)),1,0) -> 1 | H35: =IF(ISNUMBER(SEARCH("Scooty",A35)),1,0) -> 0 | I35: =IF(ISNUMBER(SEARCH("Car",A35)),1,0) -> 1 | J35: =IF(ISNUMBER(SEARCH("Commercial vehicle",A35)),1,0) -> 0 | K35: =IF(ISNUMBER(SEARCH("Electric Vehicle",A35)),1,0) -> 0 | L35: Male
A36: Scooty | C36: 7 | F36: 900 | G36: =IF(ISNUMBER(SEARCH("bike",A36)),1,0) -> 0 | H36: =IF(ISNUMBER(SEARCH("Scooty",A36)),1,0) -> 1 | I36: =IF(ISNUMBER(SEARCH("Car",A36)),1,0) -> 0 | J36: =IF(ISNUMBER(SEARCH("Commercial vehicle",A36)),1,0) -> 0 | K36: =IF(ISNUMBER(SEARCH("Electric Vehicle",A36)),1,0) -> 0 | L36: Female
A37: bikes, Commercial vehicle | B37: 10 | E37: 42 | F37: 5200 | G37: =IF(ISNUMBER(SEARCH("bike",A37)),1,0) -> 1 | H37: =IF(ISNUMBER(SEARCH("Scooty",A37)),1,0) -> 0 | I37: =IF(ISNUMBER(SEARCH("Car",A37)),1,0) -> 0 | J37: =IF(ISNUMBER(SEARCH("Commercial vehicle",A37)),1,0) -> 1 | K37: =IF(ISNUMBER(SEARCH("Electric Vehicle",A37)),1,0) -> 0 | L37: Male
A38: Scooty | C38: 5 | F38: 650 | G38: =IF(ISNUMBER(SEARCH("bike",A38)),1,0) -> 0 | H38: =IF(ISNUMBER(SEARCH("Scooty",A38)),1,0) -> 1 | I38: =IF(ISNUMBER(SEARCH("Car",A38)),1,0) -> 0 | J38: =IF(ISNUMBER(SEARCH("Commercial vehicle",A38)),1,0) -> 0 | K38: =IF(ISNUMBER(SEARCH("Electric Vehicle",A38)),1,0) -> 0 | L38: Female
A39: bikes, car, Commercial vehicle | B39: 15 | D39: 26 | E39: 26 | F39: 12000 | G39: =IF(ISNUMBER(SEARCH("bike",A39)),1,0) -> 1 | H39: =IF(ISNUMBER(SEARCH("Scooty",A39)),1,0) -> 0 | I39: =IF(ISNUMBER(SEARCH("Car",A39)),1,0) -> 1 | J39: =IF(ISNUMBER(SEARCH("Commercial vehicle",A39)),1,0) -> 1 | K39: =IF(ISNUMBER(SEARCH("Electric Vehicle",A39)),1,0) -> 0 | L39: Male
A40: car | D40: 20 | F40: 2400 | G40: =IF(ISNUMBER(SEARCH("bike",A40)),1,0) -> 0 | H40: =IF(ISNUMBER(SEARCH("Scooty",A40)),1,0) -> 0 | I40: =IF(ISNUMBER(SEARCH("Car",A40)),1,0) -> 1 | J40: =IF(ISNUMBER(SEARCH("Commercial vehicle",A40)),1,0) -> 0 | K40: =IF(ISNUMBER(SEARCH("Electric Vehicle",A40)),1,0) -> 0 | L40: Female
A41: bikes | B41: 14 | F41: 1500 | G41: =IF(ISNUMBER(SEARCH("bike",A41)),1,0) -> 1 | H41: =IF(ISNUMBER(SEARCH("Scooty",A41)),1,0) -> 0 | I41: =IF(ISNUMBER(SEARCH("Car",A41)),1,0) -> 0 | J41: =IF(ISNUMBER(SEARCH("Commercial vehicle",A41)),1,0) -> 0 | K41: =IF(ISNUMBER(SEARCH("Electric Vehicle",A41)),1,0) -> 0 | L41: Male
A42: Scooty | C42: 4 | F42: 500 | G42: =IF(ISNUMBER(SEARCH("bike",A42)),1,0) -> 0 | H42: =IF(ISNUMBER(SEARCH("Scooty",A42)),1,0) -> 1 | I42: =IF(ISNUMBER(SEARCH("Car",A42)),1,0) -> 0 | J42: =IF(ISNUMBER(SEARCH("Commercial vehicle",A42)),1,0) -> 0 | K42: =IF(ISNUMBER(SEARCH("Electric Vehicle",A42)),1,0) -> 0 | L42: Female
A43: bikes, car | B43: 9 | D43: 9 | F43: 5800 | G43: =IF(ISNUMBER(SEARCH("bike",A43)),1,0) -> 1 | H43: =IF(ISNUMBER(SEARCH("Scooty",A43)),1,0) -> 0 | I43: =IF(ISNUMBER(SEARCH("Car",A43)),1,0) -> 1 | J43: =IF(ISNUMBER(SEARCH("Commercial vehicle",A43)),1,0) -> 0 | K43: =IF(ISNUMBER(SEARCH("Electric Vehicle",A43)),1,0) -> 0 | L43: Male
A44: bikes | B44: 7 | F44: 850 | G44: =IF(ISNUMBER(SEARCH("bike",A44)),1,0) -> 1 | H44: =IF(ISNUMBER(SEARCH("Scooty",A44)),1,0) -> 0 | I44: =IF(ISNUMBER(SEARCH("Car",A44)),1,0) -> 0 | J44: =IF(ISNUMBER(SEARCH("Commercial vehicle",A44)),1,0) -> 0 | K44: =IF(ISNUMBER(SEARCH("Electric Vehicle",A44)),1,0) -> 0 | L44: Female
A45: bikes | B45: 14 | F45: 1400 | G45: =IF(ISNUMBER(SEARCH("bike",A45)),1,0) -> 1 | H45: =IF(ISNUMBER(SEARCH("Scooty",A45)),1,0) -> 0 | I45: =IF(ISNUMBER(SEARCH("Car",A45)),1,0) -> 0 | J45: =IF(ISNUMBER(SEARCH("Commercial vehicle",A45)),1,0) -> 0 | K45: =IF(ISNUMBER(SEARCH("Electric Vehicle",A45)),1,0) -> 0 | L45: Male
A46: Scooty, car | C46: 7 | D46: 20 | F46: 3200 | G46: =IF(ISNUMBER(SEARCH("bike",A46)),1,0) -> 0 | H46: =IF(ISNUMBER(SEARCH("Scooty",A46)),1,0) -> 1 | I46: =IF(ISNUMBER(SEARCH("Car",A46)),1,0) -> 1 | J46: =IF(ISNUMBER(SEARCH("Commercial vehicle",A46)),1,0) -> 0 | K46: =IF(ISNUMBER(SEARCH("Electric Vehicle",A46)),1,0) -> 0 | L46: Female
A47: bikes, Commercial vehicle | B47: 16 | E47: 45 | F47: 6800 | G47: =IF(ISNUMBER(SEARCH("bike",A47)),1,0) -> 1 | H47: =IF(ISNUMBER(SEARCH("Scooty",A47)),1,0) -> 0 | I47: =IF(ISNUMBER(SEARCH("Car",A47)),1,0) -> 0 | J47: =IF(ISNUMBER(SEARCH("Commercial vehicle",A47)),1,0) -> 1 | K47: =IF(ISNUMBER(SEARCH("Electric Vehicle",A47)),1,0) -> 0 | L47: Male
A48: Scooty | C48: 6 | F48: 700 | G48: =IF(ISNUMBER(SEARCH("bike",A48)),1,0) -> 0 | H48: =IF(ISNUMBER(SEARCH("Scooty",A48)),1,0) -> 1 | I48: =IF(ISNUMBER(SEARCH("Car",A48)),1,0) -> 0 | J48: =IF(ISNUMBER(SEARCH("Commercial vehicle",A48)),1,0) -> 0 | K48: =IF(ISNUMBER(SEARCH("Electric Vehicle",A48)),1,0) -> 0 | L48: Female
A49: bikes, car, Commercial vehicle | B49: 12 | D49: 28 | E49: 55 | F49: 11000 | G49: =IF(ISNUMBER(SEARCH("bike",A49)),1,0) -> 1 | H49: =IF(ISNUMBER(SEARCH("Scooty",A49)),1,0) -> 0 | I49: =IF(ISNUMBER(SEARCH("Car",A49)),1,0) -> 1 | J49: =IF(ISNUMBER(SEARCH("Commercial vehicle",A49)),1,0) -> 1 | K49: =IF(ISNUMBER(SEARCH("Electric Vehicle",A49)),1,0) -> 0 | L49: Male
A50: Scooty | C50: 8 | F50: 850 | G50: =IF(ISNUMBER(SEARCH("bike",A50)),1,0) -> 0 | H50: =IF(ISNUMBER(SEARCH("Scooty",A50)),1,0) -> 1 | I50: =IF(ISNUMBER(SEARCH("Car",A50)),1,0) -> 0 | J50: =IF(ISNUMBER(SEARCH("Commercial vehicle",A50)),1,0) -> 0 | K50: =IF(ISNUMBER(SEARCH("Electric Vehicle",A50)),1,0) -> 0 | L50: Female
A51: bikes, Scooty | B51: 18 | C51: 16 | F51: 4500 | G51: =IF(ISNUMBER(SEARCH("bike",A51)),1,0) -> 1 | H51: =IF(ISNUMBER(SEARCH("Scooty",A51)),1,0) -> 1 | I51: =IF(ISNUMBER(SEARCH("Car",A51)),1,0) -> 0 | J51: =IF(ISNUMBER(SEARCH("Commercial vehicle",A51)),1,0) -> 0 | K51: =IF(ISNUMBER(SEARCH("Electric Vehicle",A51)),1,0) -> 0 | L51: Male
A52: bikes, Scooty | B52: 5 | C52: 5 | F52: 200 | G52: =IF(ISNUMBER(SEARCH("bike",A52)),1,0) -> 1 | H52: =IF(ISNUMBER(SEARCH("Scooty",A52)),1,0) -> 1 | I52: =IF(ISNUMBER(SEARCH("Car",A52)),1,0) -> 0 | J52: =IF(ISNUMBER(SEARCH("Commercial vehicle",A52)),1,0) -> 0 | K52: =IF(ISNUMBER(SEARCH("Electric Vehicle",A52)),1,0) -> 0 | L52: Female
A53: car | D53: 24 | F53: 2700 | G53: =IF(ISNUMBER(SEARCH("bike",A53)),1,0) -> 0 | H53: =IF(ISNUMBER(SEARCH("Scooty",A53)),1,0) -> 0 | I53: =IF(ISNUMBER(SEARCH("Car",A53)),1,0) -> 1 | J53: =IF(ISNUMBER(SEARCH("Commercial vehicle",A53)),1,0) -> 0 | K53: =IF(ISNUMBER(SEARCH("Electric Vehicle",A53)),1,0) -> 0 | L53: Female
A54: bikes, Commercial vehicle | B54: 10 | E54: 38 | F54: 5000 | G54: =IF(ISNUMBER(SEARCH("bike",A54)),1,0) -> 1 | H54: =IF(ISNUMBER(SEARCH("Scooty",A54)),1,0) -> 0 | I54: =IF(ISNUMBER(SEARCH("Car",A54)),1,0) -> 0 | J54: =IF(ISNUMBER(SEARCH("Commercial vehicle",A54)),1,0) -> 1 | K54: =IF(ISNUMBER(SEARCH("Electric Vehicle",A54)),1,0) -> 0 | L54: Male
A55: Scooty | C55: 6 | F55: 750 | G55: =IF(ISNUMBER(SEARCH("bike",A55)),1,0) -> 0 | H55: =IF(ISNUMBER(SEARCH("Scooty",A55)),1,0) -> 1 | I55: =IF(ISNUMBER(SEARCH("Car",A55)),1,0) -> 0 | J55: =IF(ISNUMBER(SEARCH("Commercial vehicle",A55)),1,0) -> 0 | K55: =IF(ISNUMBER(SEARCH("Electric Vehicle",A55)),1,0) -> 0 | L55: Female
A56: bikes | B56: 10 | F56: 650 | G56: =IF(ISNUMBER(SEARCH("bike",A56)),1,0) -> 1 | H56: =IF(ISNUMBER(SEARCH("Scooty",A56)),1,0) -> 0 | I56: =IF(ISNUMBER(SEARCH("Car",A56)),1,0) -> 0 | J56: =IF(ISNUMBER(SEARCH("Commercial vehicle",A56)),1,0) -> 0 | K56: =IF(ISNUMBER(SEARCH("Electric Vehicle",A56)),1,0) -> 0 | L56: Female
A57: bikes, Scooty | B57: 12 | C57: 10 | F57: 4000 | G57: =IF(ISNUMBER(SEARCH("bike",A57)),1,0) -> 1 | H57: =IF(ISNUMBER(SEARCH("Scooty",A57)),1,0) -> 1 | I57: =IF(ISNUMBER(SEARCH("Car",A57)),1,0) -> 0 | J57: =IF(ISNUMBER(SEARCH("Commercial vehicle",A57)),1,0) -> 0 | K57: =IF(ISNUMBER(SEARCH("Electric Vehicle",A57)),1,0) -> 0 | L57: Male
A58: bikes | B58: 1 | F58: 650 | G58: =IF(ISNUMBER(SEARCH("bike",A58)),1,0) -> 1 | H58: =IF(ISNUMBER(SEARCH("Scooty",A58)),1,0) -> 0 | I58: =IF(ISNUMBER(SEARCH("Car",A58)),1,0) -> 0 | J58: =IF(ISNUMBER(SEARCH("Commercial vehicle",A58)),1,0) -> 0 | K58: =IF(ISNUMBER(SEARCH("Electric Vehicle",A58)),1,0) -> 0 | L58: Female
A59: bikes | B59: 8 | F59: 650 | G59: =IF(ISNUMBER(SEARCH("bike",A59)),1,0) -> 1 | H59: =IF(ISNUMBER(SEARCH("Scooty",A59)),1,0) -> 0 | I59: =IF(ISNUMBER(SEARCH("Car",A59)),1,0) -> 0 | J59: =IF(ISNUMBER(SEARCH("Commercial vehicle",A59)),1,0) -> 0 | K59: =IF(ISNUMBER(SEARCH("Electric Vehicle",A59)),1,0) -> 0 | L59: Male
A60: bikes, Scooty | B60: 8 | C60: 6 | F60: 650 | G60: =IF(ISNUMBER(SEARCH("bike",A60)),1,0) -> 1 | H60: =IF(ISNUMBER(SEARCH("Scooty",A60)),1,0) -> 1 | I60: =IF(ISNUMBER(SEARCH("Car",A60)),1,0) -> 0 | J60: =IF(ISNUMBER(SEARCH("Commercial vehicle",A60)),1,0) -> 0 | K60: =IF(ISNUMBER(SEARCH("Electric Vehicle",A60)),1,0) -> 0 | L60: Female
A61: Scooty | C61: 10 | F61: 1000 | G61: =IF(ISNUMBER(SEARCH("bike",A61)),1,0) -> 0 | H61: =IF(ISNUMBER(SEARCH("Scooty",A61)),1,0) -> 1 | I61: =IF(ISNUMBER(SEARCH("Car",A61)),1,0) -> 0 | J61: =IF(ISNUMBER(SEARCH("Commercial vehicle",A61)),1,0) -> 0 | K61: =IF(ISNUMBER(SEARCH("Electric Vehicle",A61)),1,0) -> 0 | L61: Male
A62: bikes | B62: 60 | F62: 1000 | G62: =IF(ISNUMBER(SEARCH("bike",A62)),1,0) -> 1 | H62: =IF(ISNUMBER(SEARCH("Scooty",A62)),1,0) -> 0 | I62: =IF(ISNUMBER(SEARCH("Car",A62)),1,0) -> 0 | J62: =IF(ISNUMBER(SEARCH("Commercial vehicle",A62)),1,0) -> 0 | K62: =IF(ISNUMBER(SEARCH("Electric Vehicle",A62)),1,0) -> 0 | L62: Male
A63: bikes, Commercial vehicle | B63: 55 | E63: 55 | F63: 7500 | G63: =IF(ISNUMBER(SEARCH("bike",A63)),1,0) -> 1 | H63: =IF(ISNUMBER(SEARCH("Scooty",A63)),1,0) -> 0 | I63: =IF(ISNUMBER(SEARCH("Car",A63)),1,0) -> 0 | J63: =IF(ISNUMBER(SEARCH("Commercial vehicle",A63)),1,0) -> 1 | K63: =IF(ISNUMBER(SEARCH("Electric Vehicle",A63)),1,0) -> 0 | L63: Male
A64: Scooty | C64: 7 | F64: 900 | G64: =IF(ISNUMBER(SEARCH("bike",A64)),1,0) -> 0 | H64: =IF(ISNUMBER(SEARCH("Scooty",A64)),1,0) -> 1 | I64: =IF(ISNUMBER(SEARCH("Car",A64)),1,0) -> 0 | J64: =IF(ISNUMBER(SEARCH("Commercial vehicle",A64)),1,0) -> 0 | K64: =IF(ISNUMBER(SEARCH("Electric Vehicle",A64)),1,0) -> 0 | L64: Female
A65: bikes, car | B65: 15 | D65: 22 | F65: 5500 | G65: =IF(ISNUMBER(SEARCH("bike",A65)),1,0) -> 1 | H65: =IF(ISNUMBER(SEARCH("Scooty",A65)),1,0) -> 0 | I65: =IF(ISNUMBER(SEARCH("Car",A65)),1,0) -> 1 | J65: =IF(ISNUMBER(SEARCH("Commercial vehicle",A65)),1,0) -> 0 | K65: =IF(ISNUMBER(SEARCH("Electric Vehicle",A65)),1,0) -> 0 | L65: Male
A66: Scooty | C66: 6 | F66: 700 | G66: =IF(ISNUMBER(SEARCH("bike",A66)),1,0) -> 0 | H66: =IF(ISNUMBER(SEARCH("Scooty",A66)),1,0) -> 1 | I66: =IF(ISNUMBER(SEARCH("Car",A66)),1,0) -> 0 | J66: =IF(ISNUMBER(SEARCH("Commercial vehicle",A66)),1,0) -> 0 | K66: =IF(ISNUMBER(SEARCH("Electric Vehicle",A66)),1,0) -> 0 | L66: Female
A67: bikes | B67: 10 | F67: 1200 | G67: =IF(ISNUMBER(SEARCH("bike",A67)),1,0) -> 1 | H67: =IF(ISNUMBER(SEARCH("Scooty",A67)),1,0) -> 0 | I67: =IF(ISNUMBER(SEARCH("Car",A67)),1,0) -> 0 | J67: =IF(ISNUMBER(SEARCH("Commercial vehicle",A67)),1,0) -> 0 | K67: =IF(ISNUMBER(SEARCH("Electric Vehicle",A67)),1,0) -> 0 | L67: Male
A68: car | D68: 24 | F68: 3200 | G68: =IF(ISNUMBER(SEARCH("bike",A68)),1,0) -> 0 | H68: =IF(ISNUMBER(SEARCH("Scooty",A68)),1,0) -> 0 | I68: =IF(ISNUMBER(SEARCH("Car",A68)),1,0) -> 1 | J68: =IF(ISNUMBER(SEARCH("Commercial vehicle",A68)),1,0) -> 0 | K68: =IF(ISNUMBER(SEARCH("Electric Vehicle",A68)),1,0) -> 0 | L68: Female
A69: bikes, car | B69: 14 | D69: 19 | F69: 4800 | G69: =IF(ISNUMBER(SEARCH("bike",A69)),1,0) -> 1 | H69: =IF(ISNUMBER(SEARCH("Scooty",A69)),1,0) -> 0 | I69: =IF(ISNUMBER(SEARCH("Car",A69)),1,0) -> 1 | J69: =IF(ISNUMBER(SEARCH("Commercial vehicle",A69)),1,0) -> 0 | K69: =IF(ISNUMBER(SEARCH("Electric Vehicle",A69)),1,0) -> 0 | L69: Male
A70: Scooty | C70: 6 | F70: 750 | G70: =IF(ISNUMBER(SEARCH("bike",A70)),1,0) -> 0 | H70: =IF(ISNUMBER(SEARCH("Scooty",A70)),1,0) -> 1 | I70: =IF(ISNUMBER(SEARCH("Car",A70)),1,0) -> 0 | J70: =IF(ISNUMBER(SEARCH("Commercial vehicle",A70)),1,0) -> 0 | K70: =IF(ISNUMBER(SEARCH("Electric Vehicle",A70)),1,0) -> 0 | L70: Female
A71: car, Commercial vehicle | D71: 25 | E71: 65 | F71: 10000 | G71: =IF(ISNUMBER(SEARCH("bike",A71)),1,0) -> 0 | H71: =IF(ISNUMBER(SEARCH("Scooty",A71)),1,0) -> 0 | I71: =IF(ISNUMBER(SEARCH("Car",A71)),1,0) -> 1 | J71: =IF(ISNUMBER(SEARCH("Commercial vehicle",A71)),1,0) -> 1 | K71: =IF(ISNUMBER(SEARCH("Electric Vehicle",A71)),1,0) -> 0 | L71: Male
A72: car | D72: 19 | F72: 2300 | G72: =IF(ISNUMBER(SEARCH("bike",A72)),1,0) -> 0 | H72: =IF(ISNUMBER(SEARCH("Scooty",A72)),1,0) -> 0 | I72: =IF(ISNUMBER(SEARCH("Car",A72)),1,0) -> 1 | J72: =IF(ISNUMBER(SEARCH("Commercial vehicle",A72)),1,0) -> 0 | K72: =IF(ISNUMBER(SEARCH("Electric Vehicle",A72)),1,0) -> 0 | L72: Female
A73: bikes | B73: 19 | F73: 2000 | G73: =IF(ISNUMBER(SEARCH("bike",A73)),1,0) -> 1 | H73: =IF(ISNUMBER(SEARCH("Scooty",A73)),1,0) -> 0 | I73: =IF(ISNUMBER(SEARCH("Car",A73)),1,0) -> 0 | J73: =IF(ISNUMBER(SEARCH("Commercial vehicle",A73)),1,0) -> 0 | K73: =IF(ISNUMBER(SEARCH("Electric Vehicle",A73)),1,0) -> 0 | L73: Male
A74: bikes, car | B74: 10 | D74: 40 | F74: 5000 | G74: =IF(ISNUMBER(SEARCH("bike",A74)),1,0) -> 1 | H74: =IF(ISNUMBER(SEARCH("Scooty",A74)),1,0) -> 0 | I74: =IF(ISNUMBER(SEARCH("Car",A74)),1,0) -> 1 | J74: =IF(ISNUMBER(SEARCH("Commercial vehicle",A74)),1,0) -> 0 | K74: =IF(ISNUMBER(SEARCH("Electric Vehicle",A74)),1,0) -> 0 | L74: Male
A75: Scooty | C75: 6 | F75: 1000 | G75: =IF(ISNUMBER(SEARCH("bike",A75)),1,0) -> 0 | H75: =IF(ISNUMBER(SEARCH("Scooty",A75)),1,0) -> 1 | I75: =IF(ISNUMBER(SEARCH("Car",A75)),1,0) -> 0 | J75: =IF(ISNUMBER(SEARCH("Commercial vehicle",A75)),1,0) -> 0 | K75: =IF(ISNUMBER(SEARCH("Electric Vehicle",A75)),1,0) -> 0 | L75: Female
A76: bikes, Commercial vehicle | B76: 7 | E76: 70 | F76: 9500 | G76: =IF(ISNUMBER(SEARCH("bike",A76)),1,0) -> 1 | H76: =IF(ISNUMBER(SEARCH("Scooty",A76)),1,0) -> 0 | I76: =IF(ISNUMBER(SEARCH("Car",A76)),1,0) -> 0 | J76: =IF(ISNUMBER(SEARCH("Commercial vehicle",A76)),1,0) -> 1 | K76: =IF(ISNUMBER(SEARCH("Electric Vehicle",A76)),1,0) -> 0 | L76: Male
A77: Scooty, car | C77: 4 | D77: 5 | F77: 4800 | G77: =IF(ISNUMBER(SEARCH("bike",A77)),1,0) -> 0 | H77: =IF(ISNUMBER(SEARCH("Scooty",A77)),1,0) -> 1 | I77: =IF(ISNUMBER(SEARCH("Car",A77)),1,0) -> 1 | J77: =IF(ISNUMBER(SEARCH("Commercial vehicle",A77)),1,0) -> 0 | K77: =IF(ISNUMBER(SEARCH("Electric Vehicle",A77)),1,0) -> 0 | L77: Female
A78: car, Commercial vehicle | D78: 50 | E78: 80 | F78: 14000 | G78: =IF(ISNUMBER(SEARCH("bike",A78)),1,0) -> 0 | H78: =IF(ISNUMBER(SEARCH("Scooty",A78)),1,0) -> 0 | I78: =IF(ISNUMBER(SEARCH("Car",A78)),1,0) -> 1 | J78: =IF(ISNUMBER(SEARCH("Commercial vehicle",A78)),1,0) -> 1 | K78: =IF(ISNUMBER(SEARCH("Electric Vehicle",A78)),1,0) -> 0 | L78: Male
A79: bikes | B79: 6 | F79: 1500 | G79: =IF(ISNUMBER(SEARCH("bike",A79)),1,0) -> 1 | H79: =IF(ISNUMBER(SEARCH("Scooty",A79)),1,0) -> 0 | I79: =IF(ISNUMBER(SEARCH("Car",A79)),1,0) -> 0 | J79: =IF(ISNUMBER(SEARCH("Commercial vehicle",A79)),1,0) -> 0 | K79: =IF(ISNUMBER(SEARCH("Electric Vehicle",A79)),1,0) -> 0 | L79: Female
A80: bikes | B80: 12 | F80: 2000 | G80: =IF(ISNUMBER(SEARCH("bike",A80)),1,0) -> 1 | H80: =IF(ISNUMBER(SEARCH("Scooty",A80)),1,0) -> 0 | I80: =IF(ISNUMBER(SEARCH("Car",A80)),1,0) -> 0 | J80: =IF(ISNUMBER(SEARCH("Commercial vehicle",A80)),1,0) -> 0 | K80: =IF(ISNUMBER(SEARCH("Electric Vehicle",A80)),1,0) -> 0 | L80: Male
A81: Scooty | C81: 7 | F81: 1200 | G81: =IF(ISNUMBER(SEARCH("bike",A81)),1,0) -> 0 | H81: =IF(ISNUMBER(SEARCH("Scooty",A81)),1,0) -> 1 | I81: =IF(ISNUMBER(SEARCH("Car",A81)),1,0) -> 0 | J81: =IF(ISNUMBER(SEARCH("Commercial vehicle",A81)),1,0) -> 0 | K81: =IF(ISNUMBER(SEARCH("Electric Vehicle",A81)),1,0) -> 0 | L81: Male
A82: car, Electric Vehicle | D82: 30 | F82: 3200 | G82: =IF(ISNUMBER(SEARCH("bike",A82)),1,0) -> 0 | H82: =IF(ISNUMBER(SEARCH("Scooty",A82)),1,0) -> 0 | I82: =IF(ISNUMBER(SEARCH("Car",A82)),1,0) -> 1 | J82: =IF(ISNUMBER(SEARCH("Commercial vehicle",A82)),1,0) -> 0 | K82: =IF(ISNUMBER(SEARCH("Electric Vehicle",A82)),1,0) -> 1 | L82: Male
A83: Scooty | C83: 5 | F83: 900 | G83: =IF(ISNUMBER(SEARCH("bike",A83)),1,0) -> 0 | H83: =IF(ISNUMBER(SEARCH("Scooty",A83)),1,0) -> 1 | I83: =IF(ISNUMBER(SEARCH("Car",A83)),1,0) -> 0 | J83: =IF(ISNUMBER(SEARCH("Commercial vehicle",A83)),1,0) -> 0 | K83: =IF(ISNUMBER(SEARCH("Electric Vehicle",A83)),1,0) -> 0 | L83: Female
A84: bikes, Commercial vehicle | B84: 9 | E84: 90 | F84: 12000 | G84: =IF(ISNUMBER(SEARCH("bike",A84)),1,0) -> 1 | H84: =IF(ISNUMBER(SEARCH("Scooty",A84)),1,0) -> 0 | I84: =IF(ISNUMBER(SEARCH("Car",A84)),1,0) -> 0 | J84: =IF(ISNUMBER(SEARCH("Commercial vehicle",A84)),1,0) -> 1 | K84: =IF(ISNUMBER(SEARCH("Electric Vehicle",A84)),1,0) -> 0 | L84: Male
A85: bikes | B85: 20 | F85: 650 | G85: =IF(ISNUMBER(SEARCH("bike",A85)),1,0) -> 1 | H85: =IF(ISNUMBER(SEARCH("Scooty",A85)),1,0) -> 0 | I85: =IF(ISNUMBER(SEARCH("Car",A85)),1,0) -> 0 | J85: =IF(ISNUMBER(SEARCH("Commercial vehicle",A85)),1,0) -> 0 | K85: =IF(ISNUMBER(SEARCH("Electric Vehicle",A85)),1,0) -> 0 | L85: Female
A86: bikes, car | B86: 9 | D86: 21 | F86: 4200 | G86: =IF(ISNUMBER(SEARCH("bike",A86)),1,0) -> 1 | H86: =IF(ISNUMBER(SEARCH("Scooty",A86)),1,0) -> 0 | I86: =IF(ISNUMBER(SEARCH("Car",A86)),1,0) -> 1 | J86: =IF(ISNUMBER(SEARCH("Commercial vehicle",A86)),1,0) -> 0 | K86: =IF(ISNUMBER(SEARCH("Electric Vehicle",A86)),1,0) -> 0 | L86: Male
A87: car | D87: 20 | F87: 2600 | G87: =IF(ISNUMBER(SEARCH("bike",A87)),1,0) -> 0 | H87: =IF(ISNUMBER(SEARCH("Scooty",A87)),1,0) -> 0 | I87: =IF(ISNUMBER(SEARCH("Car",A87)),1,0) -> 1 | J87: =IF(ISNUMBER(SEARCH("Commercial vehicle",A87)),1,0) -> 0 | K87: =IF(ISNUMBER(SEARCH("Electric Vehicle",A87)),1,0) -> 0 | L87: Female
A88: bikes | B88: 10 | F88: 1100 | G88: =IF(ISNUMBER(SEARCH("bike",A88)),1,0) -> 1 | H88: =IF(ISNUMBER(SEARCH("Scooty",A88)),1,0) -> 0 | I88: =IF(ISNUMBER(SEARCH("Car",A88)),1,0) -> 0 | J88: =IF(ISNUMBER(SEARCH("Commercial vehicle",A88)),1,0) -> 0 | K88: =IF(ISNUMBER(SEARCH("Electric Vehicle",A88)),1,0) -> 0 | L88: Male
A89: Scooty | C89: 5 | F89: 650 | G89: =IF(ISNUMBER(SEARCH("bike",A89)),1,0) -> 0 | H89: =IF(ISNUMBER(SEARCH("Scooty",A89)),1,0) -> 1 | I89: =IF(ISNUMBER(SEARCH("Car",A89)),1,0) -> 0 | J89: =IF(ISNUMBER(SEARCH("Commercial vehicle",A89)),1,0) -> 0 | K89: =IF(ISNUMBER(SEARCH("Electric Vehicle",A89)),1,0) -> 0 | L89: Female
A90: bikes, car | B90: 8 | D90: 18 | F90: 3600 | G90: =IF(ISNUMBER(SEARCH("bike",A90)),1,0) -> 1 | H90: =IF(ISNUMBER(SEARCH("Scooty",A90)),1,0) -> 0 | I90: =IF(ISNUMBER(SEARCH("Car",A90)),1,0) -> 1 | J90: =IF(ISNUMBER(SEARCH("Commercial vehicle",A90)),1,0) -> 0 | K90: =IF(ISNUMBER(SEARCH("Electric Vehicle",A90)),1,0) -> 0 | L90: Male
A91: bikes | B91: 11 | F91: 1300 | G91: =IF(ISNUMBER(SEARCH("bike",A91)),1,0) -> 1 | H91: =IF(ISNUMBER(SEARCH("Scooty",A91)),1,0) -> 0 | I91: =IF(ISNUMBER(SEARCH("Car",A91)),1,0) -> 0 | J91: =IF(ISNUMBER(SEARCH("Commercial vehicle",A91)),1,0) -> 0 | K91: =IF(ISNUMBER(SEARCH("Electric Vehicle",A91)),1,0) -> 0 | L91: Male
A92: Scooty | C92: 5 | F92: 650 | G92: =IF(ISNUMBER(SEARCH("bike",A92)),1,0) -> 0 | H92: =IF(ISNUMBER(SEARCH("Scooty",A92)),1,0) -> 1 | I92: =IF(ISNUMBER(SEARCH("Car",A92)),1,0) -> 0 | J92: =IF(ISNUMBER(SEARCH("Commercial vehicle",A92)),1,0) -> 0 | K92: =IF(ISNUMBER(SEARCH("Electric Vehicle",A92)),1,0) -> 0 | L92: Female
A93: bikes, car | B93: 9 | D93: 17 | F93: 3800 | G93: =IF(ISNUMBER(SEARCH("bike",A93)),1,0) -> 1 | H93: =IF(ISNUMBER(SEARCH("Scooty",A93)),1,0) -> 0 | I93: =IF(ISNUMBER(SEARCH("Car",A93)),1,0) -> 1 | J93: =IF(ISNUMBER(SEARCH("Commercial vehicle",A93)),1,0) -> 0 | K93: =IF(ISNUMBER(SEARCH("Electric Vehicle",A93)),1,0) -> 0 | L93: Male
A94: Scooty | C94: 6 | F94: 720 | G94: =IF(ISNUMBER(SEARCH("bike",A94)),1,0) -> 0 | H94: =IF(ISNUMBER(SEARCH("Scooty",A94)),1,0) -> 1 | I94: =IF(ISNUMBER(SEARCH("Car",A94)),1,0) -> 0 | J94: =IF(ISNUMBER(SEARCH("Commercial vehicle",A94)),1,0) -> 0 | K94: =IF(ISNUMBER(SEARCH("Electric Vehicle",A94)),1,0) -> 0 | L94: Female
A95: car | D95: 18 | F95: 2300 | G95: =IF(ISNUMBER(SEARCH("bike",A95)),1,0) -> 0 | H95: =IF(ISNUMBER(SEARCH("Scooty",A95)),1,0) -> 0 | I95: =IF(ISNUMBER(SEARCH("Car",A95)),1,0) -> 1 | J95: =IF(ISNUMBER(SEARCH("Commercial vehicle",A95)),1,0) -> 0 | K95: =IF(ISNUMBER(SEARCH("Electric Vehicle",A95)),1,0) -> 0 | L95: Female
A96: bikes | B96: 10 | F96: 1200 | G96: =IF(ISNUMBER(SEARCH("bike",A96)),1,0) -> 1 | H96: =IF(ISNUMBER(SEARCH("Scooty",A96)),1,0) -> 0 | I96: =IF(ISNUMBER(SEARCH("Car",A96)),1,0) -> 0 | J96: =IF(ISNUMBER(SEARCH("Commercial vehicle",A96)),1,0) -> 0 | K96: =IF(ISNUMBER(SEARCH("Electric Vehicle",A96)),1,0) -> 0 | L96: Male
A97: Scooty | C97: 5 | F97: 600 | G97: =IF(ISNUMBER(SEARCH("bike",A97)),1,0) -> 0 | H97: =IF(ISNUMBER(SEARCH("Scooty",A97)),1,0) -> 1 | I97: =IF(ISNUMBER(SEARCH("Car",A97)),1,0) -> 0 | J97: =IF(ISNUMBER(SEARCH("Commercial vehicle",A97)),1,0) -> 0 | K97: =IF(ISNUMBER(SEARCH("Electric Vehicle",A97)),1,0) -> 0 | L97: Female
A98: bikes, Commercial vehicle | B98: 11 | E98: 60 | F98: 8200 | G98: =IF(ISNUMBER(SEARCH("bike",A98)),1,0) -> 1 | H98: =IF(ISNUMBER(SEARCH("Scooty",A98)),1,0) -> 0 | I98: =IF(ISNUMBER(SEARCH("Car",A98)),1,0) -> 0 | J98: =IF(ISNUMBER(SEARCH("Commercial vehicle",A98)),1,0) -> 1 | K98: =IF(ISNUMBER(SEARCH("Electric Vehicle",A98)),1,0) -> 0 | L98: Male
A99: bikes, Commercial vehicle | B99: 13 | E99: 70 | F99: 9000 | G99: =IF(ISNUMBER(SEARCH("bike",A99)),1,0) -> 1 | H99: =IF(ISNUMBER(SEARCH("Scooty",A99)),1,0) -> 0 | I99: =IF(ISNUMBER(SEARCH("Car",A99)),1,0) -> 0 | J99: =IF(ISNUMBER(SEARCH("Commercial vehicle",A99)),1,0) -> 1 | K99: =IF(ISNUMBER(SEARCH("Electric Vehicle",A99)),1,0) -> 0 | L99: Male
A100: car | D100: 19 | F100: 2400 | G100: =IF(ISNUMBER(SEARCH("bike",A100)),1,0) -> 0 | H100: =IF(ISNUMBER(SEARCH("Scooty",A100)),1,0) -> 0 | I100: =IF(ISNUMBER(SEARCH("Car",A100)),1,0) -> 1 | J100: =IF(ISNUMBER(SEARCH("Commercial vehicle",A100)),1,0) -> 0 | K100: =IF(ISNUMBER(SEARCH("Electric Vehicle",A100)),1,0) -> 0 | L100: Female
...

Sheet Avg_Fuel(LMonth)
A1: PIVOT TABLE
A3: Row Labels | B3: Avg_Bike_Fuel(L/month) | C3: Avg_Scooty_Fuel_(L/month) | D3: Avg_Car_Fuel(L/month) | E3: Ave_Commercial_Fuel(L/month) | F3: Sum of Total_monthly_fuel_expense
A4: bike | B4: 5.5 | F4: 690
A5: bike, Commercial vehicle | B5: 7 | E5: 70 | F5: 9000
A6: bikes | B6: 12.238372 | F6: 283069
A7: bikes, car | B7: 7.1956522 | D7: 26.304348 | F7: 298789
A8: bikes, car, Commercial vehicle | B8: 6.9333333 | D8: 27.6 | E8: 62.066667 | F8: 177300
A9: bikes, car, Electric Vehicle | B9: 7.3571429 | D9: 37.285714 | F9: 56100
A10: bikes, Commercial vehicle | B10: 8.0666667 | E10: 68.616667 | F10: 513400
A11: bikes, Commercial vehicle, Tractor | B11: 10 | E11: 80 | F11: 11100
A12: bikes, Electric Vehicle | B12: 5.5 | F12: 3800
A13: bikes, Scooty | B13: 16.666667 | C13: 9.7222222 | F13: 46380
A14: bikes, Scooty, car | B14: 18.625 | C14: 15.375 | D14: 37.375 | F14: 61900
A15: car | D15: 25.333333 | F15: 198640
A16: car, Commercial vehicle | D16: 37.5 | E16: 72.5 | F16: 24000
A17: car, Electric Vehicle | D17: 29 | F17: 20900
A18: Commercial vehicle | E18: 85.714286 | F18: 59500
A19: Electric Vehicle | F19: 2300
A20: Scooty | C20: 6.3533835 | F20: 97695
A21: Scooty, car | C21: 5.8333333 | D21: 24 | F21: 27200
A22: Grand Total | B22: 10.504225 | C22: 7.1393939 | D22: 27.201183 | E22: 69.104651 | F22: 1891763
A25: Summary Table
A26: Vehicle_Type | B26: Avg_Fuel(L/month)
A27: Bike owners | B27: =AVERAGEIF('Fuel_Data_Used_Avg_Fuel(l)'!$G$2:$G$569, 1, 'Fuel_Data_Used_Avg_Fuel(l)'!$B$2:$B$569) -> 10.504225
A28: Scooty owners | B28: =AVERAGEIF('Fuel_Data_Used_Avg_Fuel(l)'!$H$2:$H$569, 1, 'Fuel_Data_Used_Avg_Fuel(l)'!$C$2:$C$569) -> 7.1393939
A29: Car owners | B29: =AVERAGEIF('Fuel_Data_Used_Avg_Fuel(l)'!$I$2:$I$569, 1, 'Fuel_Data_Used_Avg_Fuel(l)'!$D$2:$D$569) -> 27.201183
A30: Commercial Vehicle owners | B30: =AVERAGEIF('Fuel_Data_Used_Avg_Fuel(l)'!$J$2:$J$569, 1, 'Fuel_Data_Used_Avg_Fuel(l)'!$E$2:$E$569) -> 69.104651

Sheet Avg_Fuel_Expense
A1: Vehicle_Type | B1: Avg Monthly Fuel Expense
A2: Bike owners | B2: =AVERAGEIF('Fuel_Data_Used_Avg_Fuel(l)'!G2:G568,1,'Fuel_Data_Used_Avg_Fuel(l)'!F2:F568) -> 4116.9803
A3: Scooty owners | B3: =AVERAGEIF('Fuel_Data_Used_Avg_Fuel(l)'!H2:H568,1,'Fuel_Data_Used_Avg_Fuel(l)'!F2:F568) -> 1413.1818
A4: Car owners | B4: =AVERAGEIF('Fuel_Data_Used_Avg_Fuel(l)'!I2:I568,1,'Fuel_Data_Used_Avg_Fuel(l)'!F2:F568) -> 5117.3314
A5: Commercial Vehicle owners | B5: =AVERAGEIF('Fuel_Data_Used_Avg_Fuel(l)'!J2:J568,1,'Fuel_Data_Used_Avg_Fuel(l)'!F2:F568) -> 9236.0465

Sheet Per_Capita_Expenses
A1: Total_monthly_fuel_expense | B1: Total_family _members | C1: Per_Capita_Fuel_Expense | D1: Gender | E1: Monthly_income | F1: Bin | H1: Summary Table
A2: 3000 | B2: 4 | C2: =A2/B2 -> 750 | D2: Female | E2: below 10,000 | F2: 500 | H2: Statistic | I2: Result
A3: 9200 | B3: 4 | C3: =A3/B3 -> 2300 | D3: Male | E3: 10,000-30,000 | F3: 1000 | H3: Average Per Capita | I3: =AVERAGE(C2:C568) -> 750.05726
A4: 1000 | B4: 6 | C4: =A4/B4 -> 166.66667 | D4: Female | E4: 10,000-30,000 | F4: 1500 | H4: Median Per Capita | I4: =MEDIAN(C2:C568) -> 400
A5: 1000 | B5: 5 | C5: =A5/B5 -> 200 | D5: Male | E5: 10,000-30,000 | F5: 2000 | H5: Minimum | I5: =MIN(C2:C568) -> 40
A6: 10000 | B6: 5 | C6: =A6/B6 -> 2000 | D6: Male | E6: 30,000-50,000 | F6: 2500 | H6: Maximum | I6: =MAX(C2:C568) -> 5000
A7: 1200 | B7: 3 | C7: =A7/B7 -> 400 | D7: Female | E7: below 10,000 | F7: 3000 | H7: Std Deviation | I7: =STDEV(C2:C568) -> 763.28503
A8: 1000 | B8: 2 | C8: =A8/B8 -> 500 | D8: Female | E8: 30,000-50,000 | F8: 3500 | H8: Cound(Valid rows) | I8: =COUNT(C2:C568) -> 567
A9: 3000 | B9: 6 | C9: =A9/B9 -> 500 | D9: Male | E9: 10,000-30,000 | F9: 4000
A10: 1500 | B10: 3 | C10: =A10/B10 -> 500 | D10: Female | E10: 30,000-50,000 | H10: Per Capita Fuel by Gender
A11: 9500 | B11: 4 | C11: =A11/B11 -> 2375 | D11: Male | E11: above 1,00,000 | H11: Male Average Per Capita | I11: =AVERAGEIF($D$2:$D$568, "Male", $C$2:$C$568) -> 1023.5884
A12: 1500 | B12: 3 | C12: =A12/B12 -> 500 | D12: Male | E12: below 10,000 | H12: Female Average Per Capita | I12: =AVERAGEIF($D$2:$D$568, "Female", $C$2:$C$568) -> 395.68489
A13: 8000 | B13: 5 | C13: =A13/B13 -> 1600 | D13: Male | E13: 30,000-50,000
A14: 6800 | B14: 4 | C14: =A14/B14 -> 1700 | D14: Female | E14: 50,000-70,000
A15: 9000 | B15: 4 | C15: =A15/B15 -> 2250 | D15: Male | E15: 50,000-70,000 | H15: Per Capita Fuel by Income
A16: 9000 | B16: 5 | C16: =A16/B16 -> 1800 | D16: Male | E16: 30,000-50,000
A17: 900 | B17: 4 | C17: =A17/B17 -> 225 | D17: Female | E17: below 10,000 | H17: Income Group | I17: Result | J17: count
A18: 2000 | B18: 5 | C18: =A18/B18 -> 400 | D18: Male | E18: below 10,000 | H18: below 10,000 | I18: =AVERAGEIF($E$2:$E$568, "below 10,000", $C$2:$C$568) -> 319.39467 | J18: =COUNTIF($E$2:$E$568,"below 10,000") -> 125
A19: 2300 | B19: 3 | C19: =A19/B19 -> 766.66667 | D19: Male | E19: 30,000-50,000 | H19: 10,000-30,000 | I19: =AVERAGEIF($E$2:$E$568, "10,000-30,000", $C$2:$C$568) -> 418.69661 | J19: =COUNTIF($E$2:$E$568,"10,000-30,000") -> 101
A20: 1200 | B20: 4 | C20: =A20/B20 -> 300 | D20: Female | E20: below 10,000 | H20: 30,000-50,000 | I20: =AVERAGEIF($E$2:$E$568, "30,000-50,000", $C$2:$C$568) -> 803.53026 | J20: =COUNTIF($E$2:$E$568,"30,000-50,000") -> 203
A21: 11100 | B21: 6 | C21: =A21/B21 -> 1850 | D21: Male | E21: 30,000-50,000 | H21: 50,000-70,000 | I21: =AVERAGEIF($E$2:$E$568, "50,000-70,000", $C$2:$C$568) -> 1075.3976 | J21: =COUNTIF($E$2:$E$568,"50,000-70,000") -> 98
A22: 6000 | B22: 3 | C22: =A22/B22 -> 2000 | D22: Female | E22: 30,000-50,000 | H22: 70,000-1,00,000 | I22: =AVERAGEIF($E$2:$E$568, "70,000-1,00,000", $C$2:$C$568) -> 1446.8478 | J22: =COUNTIF($E$2:$E$568,"70,000-1,00,000") -> 23
A23: 8800 | B23: 5 | C23: =A23/B23 -> 1760 | D23: Male | E23: 70,000-1,00,000 | H23: above 1,00,000 | I23: =AVERAGEIF($E$2:$E$568, "above 1,00,000", $C$2:$C$568) -> 2428.6275 | J23: =COUNTIF($E$2:$E$568,"above 1,00,000") -> 17
A24: 2700 | B24: 4 | C24: =A24/B24 -> 675 | D24: Male | E24: below 10,000 | H24: Overall Average | I24: =AVERAGE($C$2:$C$568) -> 750.05726 | J24: =COUNTA(E2:E568) -> 567
A25: 3000 | B25: 6 | C25: =A25/B25 -> 500 | D25: Female | E25: 10,000-30,000
A26: 5200 | B26: 5 | C26: =A26/B26 -> 1040 | D26: Female | E26: 10,000-30,000
A27: 9700 | B27: 4 | C27: =A27/B27 -> 2425 | D27: Male | E27: 50,000-70,000
A28: 8200 | B28: 5 | C28: =A28/B28 -> 1640 | D28: Female | E28: 30,000-50,000
A29: 2400 | B29: 3 | C29: =A29/B29 -> 800 | D29: Male | E29: 10,000-30,000
A30: 2900 | B30: 4 | C30: =A30/B30 -> 725 | D30: Male | E30: below 10,000
A31: 9500 | B31: 6 | C31: =A31/B31 -> 1583.3333 | D31: Male | E31: 50,000-70,000
A32: 5200 | B32: 3 | C32: =A32/B32 -> 1733.3333 | D32: Female | E32: 30,000-50,000
A33: 8500 | B33: 4 | C33: =A33/B33 -> 2125 | D33: Male | E33: 70,000-1,00,000
A34: 7000 | B34: 5 | C34: =A34/B34 -> 1400 | D34: Male | E34: 10,000-30,000
A35: 5500 | B35: 5 | C35: =A35/B35 -> 1100 | D35: Male | E35: 50,000-70,000
A36: 900 | B36: 3 | C36: =A36/B36 -> 300 | D36: Female | E36: 30,000-50,000
... A568: 2000 | B568: 5 | C568: =A568/B568 -> 400 | D568: Female | E568: 50,000-70,000

Sheet Histogram
A2: Histogram
A3: Bin | B3: Frequency
A4: 500 | B4: 304
A5: 1000 | B5: 109
A6: 1500 | B6: 69
A7: 2000 | B7: 45
A8: 2500 | B8: 25
A9: 3000 | B9: 4
A10: 3500 | B10: 5
A11: 4000 | B11: 5
A12: More | B12: 1

Sheet Correlation
A1: Income Group | B1: Midpoint to use | E1: Monthly_income | F1: Income_Numeric | G1: Total_monthly_fuel_expense | H1: Per_Capita_Fuel | J1: Statistic | K1: Result
A2: below 10,000 | B2: 5000 | E2: below 10,000 | F2: =IF(E2="below 10,000",5000, IF(E2="10,000-30,000", 20000, IF(E2="30,000-50,000", 40000, IF(E2="50,000-70,000", 60000, IF(E2="70,000-1,00,000",85000,IF(E2="above 1,00,000",125000," ")))))) -> 5000 | G2: 3000 | H2: =F2/G2 -> 1.6666667 | J2: Correlation(Income vs Total Expense) | K2: =CORREL($F$2:$F$568, $G$2:$G$568) -> 0.51836596
A3: 10,000-30,000 | B3: 20000 | E3: 10,000-30,000 | F3: =IF(E3="below 10,000",5000, IF(E3="10,000-30,000", 20000, IF(E3="30,000-50,000", 40000, IF(E3="50,000-70,000", 60000, IF(E3="70,000-1,00,000",85000,IF(E3="above 1,00,000",125000," ")))))) -> 20000 | G3: 9200 | H3: =F3/G3 -> 2.173913 | J3: Count | K3: =COUNT($F$2:$F$568) -> 567
A4: 30,000-50,000 | B4: 40000 | E4: 10,000-30,000 | F4: =IF(E4="below 10,000",5000, IF(E4="10,000-30,000", 20000, IF(E4="30,000-50,000", 40000, IF(E4="50,000-70,000", 60000, IF(E4="70,000-1,00,000",85000,IF(E4="above 1,00,000",125000," ")))))) -> 20000 | G4: 1000 | H4: =F4/G4 -> 20
A5: 50,000-70,000 | B5: 60000 | E5: 10,000-30,000 | F5: =IF(E5="below 10,000",5000, IF(E5="10,000-30,000", 20000, IF(E5="30,000-50,000", 40000, IF(E5="50,000-70,000", 60000, IF(E5="70,000-1,00,000",85000,IF(E5="above 1,00,000",125000," ")))))) -> 20000 | G5: 1000 | H5: =F5/G5 -> 20
A6: 70,000-1,00,000 | B6: 85000 | E6: 30,000-50,000 | F6: =IF(E6="below 10,000",5000, IF(E6="10,000-30,000", 20000, IF(E6="30,000-50,000", 40000, IF(E6="50,000-70,000", 60000, IF(E6="70,000-1,00,000",85000,IF(E6="above 1,00,000",125000," ")))))) -> 40000 | G6: 10000 | H6: =F6/G6 -> 4
A7: above 1,00,000 | B7: 125000 | E7: below 10,000 | F7: =IF(E7="below 10,000",5000, IF(E7="10,000-30,000", 20000, IF(E7="30,000-50,000", 40000, IF(E7="50,000-70,000", 60000, IF(E7="70,000-1,00,000",85000,IF(E7="above 1,00,000",125000," ")))))) -> 5000 | G7: 1200 | H7: =F7/G7 -> 4.1666667
E8: 30,000-50,000 | F8: =IF(E8="below 10,000",5000, IF(E8="10,000-30,000", 20000, IF(E8="30,000-50,000", 40000, IF(E8="50,000-70,000", 60000, IF(E8="70,000-1,00,000",85000,IF(E8="above 1,00,000",125000," ")))))) -> 40000 | G8: 1000 | H8: =F8/G8 -> 40
E9: 10,000-30,000 | F9: =IF(E9="below 10,000",5000, IF(E9="10,000-30,000", 20000, IF(E9="30,000-50,000", 40000, IF(E9="50,000-70,000", 60000, IF(E9="70,000-1,00,000",85000,IF(E9="above 1,00,000",125000," ")))))) -> 20000 | G9: 3000 | H9: =F9/G9 -> 6.6666667
E10: 30,000-50,000 | F10: =IF(E10="below 10,000",5000, IF(E10="10,000-30,000", 20000, IF(E10="30,000-50,000", 40000, IF(E10="50,000-70,000", 60000, IF(E10="70,000-1,00,000",85000,IF(E10="above 1,00,000",125000," ")))))) -> 40000 | G10: 1500 | H10: =F10/G10 -> 26.666667
E11: above 1,00,000 | F11: =IF(E11="below 10,000",5000, IF(E11="10,000-30,000", 20000, IF(E11="30,000-50,000", 40000, IF(E11="50,000-70,000", 60000, IF(E11="70,000-1,00,000",85000,IF(E11="above 1,00,000",125000," ")))))) -> 125000 | G11: 9500 | H11: =F11/G11 -> 13.157895
E12: below 10,000 | F12: =IF(E12="below 10,000",5000, IF(E12="10,000-30,000", 20000, IF(E12="30,000-50,000", 40000, IF(E12="50,000-70,000", 60000, IF(E12="70,000-1,00,000",85000,IF(E12="above 1,00,000",125000," ")))))) -> 5000 | G12: 1500 | H12: =F12/G12 -> 3.3333333
E13: 30,000-50,000 | F13: =IF(E13="below 10,000",5000, IF(E13="10,000-30,000", 20000, IF(E13="30,000-50,000", 40000, IF(E13="50,000-70,000", 60000, IF(E13="70,000-1,00,000",85000,IF(E13="above 1,00,000",125000," ")))))) -> 40000 | G13: 8000 | H13: =F13/G13 -> 5
E14: 50,000-70,000 | F14: =IF(E14="below 10,000",5000, IF(E14="10,000-30,000", 20000, IF(E14="30,000-50,000", 40000, IF(E14="50,000-70,000", 60000, IF(E14="70,000-1,00,000",85000,IF(E14="above 1,00,000",125000," ")))))) -> 60000 | G14: 6800 | H14: =F14/G14 -> 8.8235294
E15: 50,000-70,000 | F15: =IF(E15="below 10,000",5000, IF(E15="10,000-30,000", 20000, IF(E15="30,000-50,000", 40000, IF(E15="50,000-70,000", 60000, IF(E15="70,000-1,00,000",85000,IF(E15="above 1,00,000",125000," ")))))) -> 60000 | G15: 9000 | H15: =F15/G15 -> 6.6666667
E16: 30,000-50,000 | F16: =IF(E16="below 10,000",5000, IF(E16="10,000-30,000", 20000, IF(E16="30,000-50,000", 40000, IF(E16="50,000-70,000", 60000, IF(E16="70,000-1,00,000",85000,IF(E16="above 1,00,000",125000," ")))))) -> 40000 | G16: 9000 | H16: =F16/G16 -> 4.4444444
E17: below 10,000 | F17: =IF(E17="below 10,000",5000, IF(E17="10,000-30,000", 20000, IF(E17="30,000-50,000", 40000, IF(E17="50,000-70,000", 60000, IF(E17="70,000-1,00,000",85000,IF(E17="above 1,00,000",125000," ")))))) -> 5000 | G17: 900 | H17: =F17/G17 -> 5.5555556
E18: below 10,000 | F18: =IF(E18="below 10,000",5000, IF(E18="10,000-30,000", 20000, IF(E18="30,000-50,000", 40000, IF(E18="50,000-70,000", 60000, IF(E18="70,000-1,00,000",85000,IF(E18="above 1,00,000",125000," ")))))) -> 5000 | G18: 2000 | H18: =F18/G18 -> 2.5
E19: 30,000-50,000 | F19: =IF(E19="below 10,000",5000, IF(E19="10,000-30,000", 20000, IF(E19="30,000-50,000", 40000, IF(E19="50,000-70,000", 60000, IF(E19="70,000-1,00,000",85000,IF(E19="above 1,00,000",125000," ")))))) -> 40000 | G19: 2300 | H19: =F19/G19 -> 17.391304
... E28: 30,000-50,000 | F28: =IF(E28="below 10,000",5000, IF(E28="10,000-30,000", 20000, IF(E28="30,000-50,000", 40000, IF(E28="50,000-70,000", 60000, IF(E28="70,000-1,00,000",85000,IF(E28="above 1,00,000",125000," ")))))) -> 40000 | G28: 8200 | H28: =F28/G28 -> 4.8780488
E29: 10,000-30,000 | F29: =IF(E29="below 10,000",5000, IF(E29="10,000-30,000", 20000, IF(E29="30,000-50,000", 40000, IF(E29="50,000-70,000", 60000, IF(E29="70,000-1,00,000",85000,IF(E29="above 1,00,000",125000," ")))))) -> 20000 | G29: 2400 | H29: =F29/G29 -> 8.3333333 | J29: Summary Table
E30: below 10,000 | F30: =IF(E30="below 10,000",5000, IF(E30="10,000-30,000", 20000, IF(E30="30,000-50,000", 40000, IF(E30="50,000-70,000", 60000, IF(E30="70,000-1,00,000",85000,IF(E30="above 1,00,000",125000," ")))))) -> 5000 | G30: 2900 | H30: =F30/G30 -> 1.7241379
E31: 50,000-70,000 | F31: =IF(E31="below 10,000",5000, IF(E31="10,000-30,000", 20000, IF(E31="30,000-50,000", 40000, IF(E31="50,000-70,000", 60000, IF(E31="70,000-1,00,000",85000,IF(E31="above 1,00,000",125000," ")))))) -> 60000 | G31: 9500 | H31: =F31/G31 -> 6.3157895 | J31: Income Group | K31: Avg Monthly Fuel | L31: Avg Per Capita | M31: Count
E32: 30,000-50,000 | F32: =IF(E32="below 10,000",5000, IF(E32="10,000-30,000", 20000, IF(E32="30,000-50,000", 40000, IF(E32="50,000-70,000", 60000, IF(E32="70,000-1,00,000",85000,IF(E32="above 1,00,000",125000," ")))))) -> 40000 | G32: 5200 | H32: =F32/G32 -> 7.6923077 | J32: below 10,000 | K32: =AVERAGEIF($E$2:$E$568, "below 10,000", $G$2:$G$568) -> 1309.04 | L32: 319.39467 | M32: =COUNTIF(E2:E568,"below 10,000") -> 125
E33: 70,000-1,00,000 | F33: =IF(E33="below 10,000",5000, IF(E33="10,000-30,000", 20000, IF(E33="30,000-50,000", 40000, IF(E33="50,000-70,000", 60000, IF(E33="70,000-1,00,000",85000,IF(E33="above 1,00,000",125000," ")))))) -> 85000 | G33: 8500 | H33: =F33/G33 -> 10 | J33: 10,000-30,000 | K33: =AVERAGEIF($E$2:$E$568, "10,000-30,000", $G$2:$G$568) -> 2049.0495 | L33: 418.69661 | M33: =COUNTIF(E2:E568,"10,000-30,000") -> 101
E34: 10,000-30,000 | F34: =IF(E34="below 10,000",5000, IF(E34="10,000-30,000", 20000, IF(E34="30,000-50,000", 40000, IF(E34="50,000-70,000", 60000, IF(E34="70,000-1,00,000",85000,IF(E34="above 1,00,000",125000," ")))))) -> 20000 | G34: 7000 | H34: =F34/G34 -> 2.8571429 | J34: 30,000-50,000 | K34: =AVERAGEIF($E$2:$E$568, "30,000-50,000", $G$2:$G$568) -> 3577.6847 | L34: 803.53026 | M34: =COUNTIF($E$2:$E$568,"30,000-50,000") -> 203
E35: 50,000-70,000 | F35: =IF(E35="below 10,000",5000, IF(E35="10,000-30,000", 20000, IF(E35="30,000-50,000", 40000, IF(E35="50,000-70,000", 60000, IF(E35="70,000-1,00,000",85000,IF(E35="above 1,00,000",125000," ")))))) -> 60000 | G35: 5500 | H35: =F35/G35 -> 10.909091 | J35: 50,000-70,000 | K35: =AVERAGEIF($E$2:$E$568, "50,000-70,000", $G$2:$G$568) -> 4925.9082 | L35: 1075.3976 | M35: =COUNTIF($E$2:$E$568,"50,000-70,000") -> 98
E36: 30,000-50,000 | F36: =IF(E36="below 10,000",5000, IF(E36="10,000-30,000", 20000, IF(E36="30,000-50,000", 40000, IF(E36="50,000-70,000", 60000, IF(E36="70,000-1,00,000",85000,IF(E36="above 1,00,000",125000," ")))))) -> 40000 | G36: 900 | H36: =F36/G36 -> 44.444444 | J36: 70,000-1,00,000 | K36: =AVERAGEIF($E$2:$E$568, "70,000-1,00,000", $G$2:$G$568) -> 6133.4783 | L36: 1446.8478 | M36: =COUNTIF($E$2:$E$568,"70,000-1,00,000") -> 23
E37: 10,000-30,000 | F37: =IF(E37="below 10,000",5000, IF(E37="10,000-30,000", 20000, IF(E37="30,000-50,000", 40000, IF(E37="50,000-70,000", 60000, IF(E37="70,000-1,00,000",85000,IF(E37="above 1,00,000",125000," ")))))) -> 20000 | G37: 5200 | H37: =F37/G37 -> 3.8461538 | J37: above 1,00,000 | K37: =AVERAGEIF($E$2:$E$568, "above 1,00,000", $G$2:$G$568) -> 10064.706 | L37: 2428.6275 | M37: =COUNTIF($E$2:$E$568,"above 1,00,000") -> 17
E38: below 10,000 | F38: =IF(E38="below 10,000",5000, IF(E38="10,000-30,000", 20000, IF(E38="30,000-50,000", 40000, IF(E38="50,000-70,000", 60000, IF(E38="70,000-1,00,000",85000,IF(E38="above 1,00,000",125000," ")))))) -> 5000 | G38: 650 | H38: =F38/G38 -> 7.6923077 | J38: Correlation | K38: =K2 -> 0.51836596 | L38: =K3 -> 567 | M38: =SUM(M32:M37) -> 567
E39: 70,000-1,00,000 | F39: =IF(E39="below 10,000",5000, IF(E39="10,000-30,000", 20000, IF(E39="30,000-50,000", 40000, IF(E39="50,000-70,000", 60000, IF(E39="70,000-1,00,000",85000,IF(E39="above 1,00,000",125000," ")))))) -> 85000 | G39: 12000 | H39: =F39/G39 -> 7.0833333
E40: 50,000-70,000 | F40: =IF(E40="below 10,000",5000, IF(E40="10,000-30,000", 20000, IF(E40="30,000-50,000", 40000, IF(E40="50,000-70,000", 60000, IF(E40="70,000-1,00,000",85000,IF(E40="above 1,00,000",125000," ")))))) -> 60000 | G40: 2400 | H40: =F40/G40 -> 25
E41: 10,000-30,000 | F41: =IF(E41="below 10,000",5000, IF(E41="10,000-30,000", 20000, IF(E41="30,000-50,000", 40000, IF(E41="50,000-70,000", 60000, IF(E41="70,000-1,00,000",85000,IF(E41="above 1,00,000",125000," ")))))) -> 20000 | G41: 1500 | H41: =F41/G41 -> 13.333333
E42: below 10,000 | F42: =IF(E42="below 10,000",5000, IF(E42="10,000-30,000", 20000, IF(E42="30,000-50,000", 40000, IF(E42="50,000-70,000", 60000, IF(E42="70,000-1,00,000",85000,IF(E42="above 1,00,000",125000," ")))))) -> 5000 | G42: 500 | H42: =F42/G42 -> 10
E43: above 1,00,000 | F43: =IF(E43="below 10,000",5000, IF(E43="10,000-30,000", 20000, IF(E43="30,000-50,000", 40000, IF(E43="50,000-70,000", 60000, IF(E43="70,000-1,00,000",85000,IF(E43="above 1,00,000",125000," ")))))) -> 125000 | G43: 5800 | H43: =F43/G43 -> 21.551724
E44: below 10,000 | F44: =IF(E44="below 10,000",5000, IF(E44="10,000-30,000", 20000, IF(E44="30,000-50,000", 40000, IF(E44="50,000-70,000", 60000, IF(E44="70,000-1,00,000",85000,IF(E44="above 1,00,000",125000," ")))))) -> 5000 | G44: 850 | H44: =F44/G44 -> 5.8823529
E45: 10,000-30,000 | F45: =IF(E45="below 10,000",5000, IF(E45="10,000-30,000", 20000, IF(E45="30,000-50,000", 40000, IF(E45="50,000-70,000", 60000, IF(E45="70,000-1,00,000",85000,IF(E45="above 1,00,000",125000," ")))))) -> 20000 | G45: 1400 | H45: =F45/G45 -> 14.285714
E46: 30,000-50,000 | F46: =IF(E46="below 10,000",5000, IF(E46="10,000-30,000", 20000, IF(E46="30,000-50,000", 40000, IF(E46="50,000-70,000", 60000, IF(E46="70,000-1,00,000",85000,IF(E46="above 1,00,000",125000," ")))))) -> 40000 | G46: 3200 | H46: =F46/G46 -> 12.5
E47: 30,000-50,000 | F47: =IF(E47="below 10,000",5000, IF(E47="10,000-30,000", 20000, IF(E47="30,000-50,000", 40000, IF(E47="50,000-70,000", 60000, IF(E47="70,000-1,00,000",85000,IF(E47="above 1,00,000",125000," ")))))) -> 40000 | G47: 6800 | H47: =F47/G47 -> 5.8823529
E48: 10,000-30,000 | F48: =IF(E48="below 10,000",5000, IF(E48="10,000-30,000", 20000, IF(E48="30,000-50,000", 40000, IF(E48="50,000-70,000", 60000, IF(E48="70,000-1,00,000",85000,IF(E48="above 1,00,000",125000," ")))))) -> 20000 | G48: 700 | H48: =F48/G48 -> 28.571429
E49: 70,000-1,00,000 | F49: =IF(E49="below 10,000",5000, IF(E49="10,000-30,000", 20000, IF(E49="30,000-50,000", 40000, IF(E49="50,000-70,000", 60000, IF(E49="70,000-1,00,000",85000,IF(E49="above 1,00,000",125000," ")))))) -> 85000 | G49: 11000 | H49: =F49/G49 -> 7.7272727
E50: below 10,000 | F50: =IF(E50="below 10,000",5000, IF(E50="10,000-30,000", 20000, IF(E50="30,000-50,000", 40000, IF(E50="50,000-70,000", 60000, IF(E50="70,000-1,00,000",85000,IF(E50="above 1,00,000",125000," ")))))) -> 5000 | G50: 850 | H50: =F50/G50 -> 5.8823529
... E568: 50,000-70,000 | F568: =IF(E568="below 10,000",5000, IF(E568="10,000-30,000", 20000, IF(E568="30,000-50,000", 40000, IF(E568="50,000-70,000", 60000, IF(E568="70,000-1,00,000",85000,IF(E568="above 1,00,000",125000," ")))))) -> 60000 | G568: 2000 | H568: =F568/G568 -> 30

Sheet Correlation_Matrix
A1: Total_monthly_fuel_expense | B1: Income_Numeric | C1: No._of_vehicles_in_family | D1: Total_family _members | E1: Distance_home_ workplacr
A2: 3000 | B2: 5000 | C2: 1 | D2: 4 | E2: 11
A3: 9200 | B3: 20000 | C3: 2 | D3: 4 | E3: 11 | G3: Correlation Matrix
A4: 1000 | B4: 20000 | C4: 1 | D4: 6 | E4: 14 | H4: Total_monthly_fuel_expense | I4: Income_Numeric | J4: No._of_vehicles_in_family | K4: Total_family _members | L4: Distance_home_ workplacr
A5: 1000 | B5: 20000 | C5: 1 | D5: 5 | E5: 10 | G5: Total_monthly_fuel_expense | H5: 1
A6: 10000 | B6: 40000 | C6: 3 | D6: 5 | E6: 15 | G6: Income_Numeric | H6: 0.51836596 | I6: 1
A7: 1200 | B7: 5000 | C7: 1 | D7: 3 | E7: 6 | G7: No._of_vehicles_in_family | H7: 0.66581182 | I7: 0.46101979 | J7: 1
A8: 1000 | B8: 40000 | C8: 2 | D8: 2 | E8: 21 | G8: Total_family _members | H8: 0.19622135 | I8: -0.050742784 | J8: 0.22370947 | K8: 1
A9: 3000 | B9: 20000 | C9: 1 | D9: 6 | E9: 18 | G9: Distance_home_ workplacr | H9: 0.37367666 | I9: 0.37706352 | J9: 0.32912175 | K9: -0.041903344 | L9: 1
A10: 1500 | B10: 40000 | C10: 1 | D10: 3 | E10: 7
A11: 9500 | B11: 125000 | C11: 2 | D11: 4 | E11: 20 | G11: Correlation Legend Table
A12: 1500 | B12: 5000 | C12: 1 | D12: 3 | E12: 5 | G12: Colour | H12: Range | I12: Meaning
A13: 8000 | B13: 40000 | C13: 2 | D13: 5 | E13: 14 | G13: Dark Blue | H13: 1 | I13: Perfect positive correlation
A14: 6800 | B14: 60000 | C14: 2 | D14: 4 | E14: 10 | G14: Blue | H14: 0.70 to 0.99 | I14: Strong positive correlation
A15: 9000 | B15: 60000 | C15: 2 | D15: 4 | E15: 18 | G15: Light Blue | H15: 0.30 to 0.69 | I15: Moderate positive correlation
A16: 9000 | B16: 40000 | C16: 3 | D16: 5 | E16: 15 | G16: White | H16: 0.00 to 0.29 | I16: Weak / no correlation
A17: 900 | B17: 5000 | C17: 1 | D17: 4 | E17: 5 | G17: Light Red | H17: -0.29 to 0.00 | I17: Weak negative correlation
A18: 2000 | B18: 5000 | C18: 3 | D18: 5 | E18: 9 | G18: Red | H18: - 0.69 to - 0.30 | I18: Moderate negative correlation
A19: 2300 | B19: 40000 | C19: 1 | D19: 3 | E19: 10 | G19: Dark Red | H19: - 1.00 to - 0.70 | I19: Strong negative correlation
A20: 1200 | B20: 5000 | C20: 1 | D20: 4 | E20: 6
A21: 11100 | B21: 40000 | C21: 3 | D21: 6 | E21: 12 | G21: Key finding:
A22: 6000 | B22: 40000 | C22: 1 | D22: 3 | E22: 10
A23: 8800 | B23: 85000 | C23: 3 | D23: 5 | E23: 14 | G23: 1] Strongest correlation: Num_Vehicles vs Total_Expense (r=0.67) - vehicle ownership is the strongest predictor
A24: 2700 | B24: 5000 | C24: 1 | D24: 4 | E24: 14 | G24: 2] Income vs Num_Vehicles(r=0.461) - higher income households own more vehicles - indirect income effect
A25: 3000 | B25: 20000 | C25: 2 | D25: 6 | E25: 4 | G25: 3] No multicollinearity concern - no pair of predictors exceeds r=0.80
A26: 5200 | B26: 20000 | C26: 2 | D26: 5 | E26: 8
A27: 9700 | B27: 60000 | C27: 2 | D27: 4 | E27: 15
A28: 8200 | B28: 40000 | C28: 2 | D28: 5 | E28: 8
A29: 2400 | B29: 20000 | C29: 1 | D29: 3 | E29: 7
A30: 2900 | B30: 5000 | C30: 1 | D30: 4 | E30: 12
A31: 9500 | B31: 60000 | C31: 3 | D31: 6 | E31: 20
A32: 5200 | B32: 40000 | C32: 1 | D32: 3 | E32: 9
A33: 8500 | B33: 85000 | C33: 2 | D33: 4 | E33: 18
A34: 7000 | B34: 20000 | C34: 2 | D34: 5 | E34: 10
A35: 5500 | B35: 60000 | C35: 2 | D35: 5 | E35: 12
A36: 900 | B36: 40000 | C36: 1 | D36: 3 | E36: 4
A37: 5200 | B37: 20000 | C37: 2 | D37: 6 | E37: 10
... A568: 2000 | B568: 60000 | C568: 1 | D568: 5 | E568: 9

Sheet per_capita_fuel
A1: Total_Vehicle_Fuel | B1: fuel_monthly_bikes | C1: Fuel_required_monthly_scooty | D1: Fuel_required_monthly_car | E1: Fuel_required_monthly_commercial | F1: Total_family _members | G1: Per_Capita_Vehicle_Fuel
A2: =IFERROR(B2,0)+IFERROR(C2,0)+IFERROR(D2,0)+IFERROR(E2,0) -> 30 | B2: 30 | F2: 4 | G2: =IFERROR(A2/F2," ") -> 7.5 | I2: Summary Table
A3: =IFERROR(B3,0)+IFERROR(C3,0)+IFERROR(D3,0)+IFERROR(E3,0) -> 76 | B3: 75 | E3: 1 | F3: 4 | G3: =IFERROR(A3/F3," ") -> 19 | I3: Statistic | J3: Result
A4: =IFERROR(B4,0)+IFERROR(C4,0)+IFERROR(D4,0)+IFERROR(E4,0) -> 10 | C4: 10 | F4: 6 | G4: =IFERROR(A4/F4," ") -> 1.6666667 | I4: Average Per Capita | J4: =AVERAGE(G2:G568) -> 6.0711997
A5: =IFERROR(B5,0)+IFERROR(C5,0)+IFERROR(D5,0)+IFERROR(E5,0) -> 20 | B5: 20 | F5: 5 | G5: =IFERROR(A5/F5," ") -> 4 | I5: Median Per Capita | J5: =MEDIAN(G2:G568) -> 3.75
A6: =IFERROR(B6,0)+IFERROR(C6,0)+IFERROR(D6,0)+IFERROR(E6,0) -> 113 | B6: 8 | D6: 45 | E6: 60 | F6: 5 | G6: =IFERROR(A6/F6," ") -> 22.6 | I6: Minimum | J6: 0.4
A7: =IFERROR(B7,0)+IFERROR(C7,0)+IFERROR(D7,0)+IFERROR(E7,0) -> 10 | C7: 10 | F7: 3 | G7: =IFERROR(A7/F7," ") -> 3.3333333 | I7: Maximum | J7: =MAX(G2:G568) -> 45
A8: =IFERROR(B8,0)+IFERROR(C8,0)+IFERROR(D8,0)+IFERROR(E8,0) -> 90 | B8: 20 | D8: 70 | F8: 2 | G8: =IFERROR(A8/F8," ") -> 45 | I8: Std Deviation | J8: =STDEV(G2:G568) -> 6.2044078
A9: =IFERROR(B9,0)+IFERROR(C9,0)+IFERROR(D9,0)+IFERROR(E9,0) -> 28 | B9: 28 | F9: 6 | G9: =IFERROR(A9/F9," ") -> 4.6666667 | I9: Cound(Valid rows) | J9: =COUNT(G2:G568) -> 567
A10: =IFERROR(B10,0)+IFERROR(C10,0)+IFERROR(D10,0)+IFERROR(E10,0) -> 12 | C10: 12 | F10: 3 | G10: =IFERROR(A10/F10," ") -> 4
A11: =IFERROR(B11,0)+IFERROR(C11,0)+IFERROR(D11,0)+IFERROR(E11,0) -> 60 | D11: 60 | F11: 4 | G11: =IFERROR(A11/F11," ") -> 15
A12: =IFERROR(B12,0)+IFERROR(C12,0)+IFERROR(D12,0)+IFERROR(E12,0) -> 8 | C12: 8 | F12: 3 | G12: =IFERROR(A12/F12," ") -> 2.6666667
A13: =IFERROR(B13,0)+IFERROR(C13,0)+IFERROR(D13,0)+IFERROR(E13,0) -> 80 | B13: 10 | E13: 70 | F13: 5 | G13: =IFERROR(A13/F13," ") -> 16
A14: =IFERROR(B14,0)+IFERROR(C14,0)+IFERROR(D14,0)+IFERROR(E14,0) -> 67 | B14: 12 | D14: 55 | F14: 4 | G14: =IFERROR(A14/F14," ") -> 16.75
A15: =IFERROR(B15,0)+IFERROR(C15,0)+IFERROR(D15,0)+IFERROR(E15,0) -> 77 | B15: 7 | D15: 70 | F15: 4 | G15: =IFERROR(A15/F15," ") -> 19.25
A16: =IFERROR(B16,0)+IFERROR(C16,0)+IFERROR(D16,0)+IFERROR(E16,0) -> 87 | B16: 13 | C16: 9 | D16: 65 | F16: 5 | G16: =IFERROR(A16/F16," ") -> 17.4
A17: =IFERROR(B17,0)+IFERROR(C17,0)+IFERROR(D17,0)+IFERROR(E17,0) -> 7 | C17: 7 | F17: 4 | G17: =IFERROR(A17/F17," ") -> 1.75
A18: =IFERROR(B18,0)+IFERROR(C18,0)+IFERROR(D18,0)+IFERROR(E18,0) -> 31 | B18: 6 | D18: 25 | F18: 5 | G18: =IFERROR(A18/F18," ") -> 6.2
A19: =IFERROR(B19,0)+IFERROR(C19,0)+IFERROR(D19,0)+IFERROR(E19,0) -> 18 | B19: 18 | F19: 3 | G19: =IFERROR(A19/F19," ") -> 6
A20: =IFERROR(B20,0)+IFERROR(C20,0)+IFERROR(D20,0)+IFERROR(E20,0) -> 10 | C20: 10 | F20: 4 | G20: =IFERROR(A20/F20," ") -> 2.5
A21: =IFERROR(B21,0)+IFERROR(C21,0)+IFERROR(D21,0)+IFERROR(E21,0) -> 90 | B21: 10 | E21: 80 | F21: 6 | G21: =IFERROR(A21/F21," ") -> 15
A22: =IFERROR(B22,0)+IFERROR(C22,0)+IFERROR(D22,0)+IFERROR(E22,0) -> 50 | D22: 50 | F22: 3 | G22: =IFERROR(A22/F22," ") -> 16.666667
A23: =IFERROR(B23,0)+IFERROR(C23,0)+IFERROR(D23,0)+IFERROR(E23,0) -> 61 | B23: 6 | D23: 55 | F23: 5 | G23: =IFERROR(A23/F23," ") -> 12.2
A24: =IFERROR(B24,0)+IFERROR(C24,0)+IFERROR(D24,0)+IFERROR(E24,0) -> 24 | B24: 24 | F24: 4 | G24: =IFERROR(A24/F24," ") -> 6
A25: =IFERROR(B25,0)+IFERROR(C25,0)+IFERROR(D25,0)+IFERROR(E25,0) -> 17 | B25: 9 | C25: 8 | F25: 6 | G25: =IFERROR(A25/F25," ") -> 2.8333333
A26: =IFERROR(B26,0)+IFERROR(C26,0)+IFERROR(D26,0)+IFERROR(E26,0) -> 49 | C26: 9 | D26: 40 | F26: 5 | G26: =IFERROR(A26/F26," ") -> 9.8
A27: =IFERROR(B27,0)+IFERROR(C27,0)+IFERROR(D27,0)+IFERROR(E27,0) -> 77 | B27: 7 | D27: 70 | F27: 4 | G27: =IFERROR(A27/F27," ") -> 19.25
A28: =IFERROR(B28,0)+IFERROR(C28,0)+IFERROR(D28,0)+IFERROR(E28,0) -> 77 | B28: 12 | E28: 65 | F28: 5 | G28: =IFERROR(A28/F28," ") -> 15.4
A29: =IFERROR(B29,0)+IFERROR(C29,0)+IFERROR(D29,0)+IFERROR(E29,0) -> 20 | B29: 20 | F29: 3 | G29: =IFERROR(A29/F29," ") -> 6.6666667
A30: =IFERROR(B30,0)+IFERROR(C30,0)+IFERROR(D30,0)+IFERROR(E30,0) -> 26 | B30: 26 | F30: 4 | G30: =IFERROR(A30/F30," ") -> 6.5
A31: =IFERROR(B31,0)+IFERROR(C31,0)+IFERROR(D31,0)+IFERROR(E31,0) -> 82 | B31: 16 | C31: 6 | D31: 60 | F31: 6 | G31: =IFERROR(A31/F31," ") -> 13.666667
A32: =IFERROR(B32,0)+IFERROR(C32,0)+IFERROR(D32,0)+IFERROR(E32,0) -> 45 | D32: 45 | F32: 3 | G32: =IFERROR(A32/F32," ") -> 15
A33: =IFERROR(B33,0)+IFERROR(C33,0)+IFERROR(D33,0)+IFERROR(E33,0) -> 72 | B33: 7 | D33: 65 | F33: 4 | G33: =IFERROR(A33/F33," ") -> 18
A34: =IFERROR(B34,0)+IFERROR(C34,0)+IFERROR(D34,0)+IFERROR(E34,0) -> 69 | B34: 14 | E34: 55 | F34: 5 | G34: =IFERROR(A34/F34," ") -> 13.8
A35: =IFERROR(B35,0)+IFERROR(C35,0)+IFERROR(D35,0)+IFERROR(E35,0) -> 36 | B35: 12 | D35: 24 | F35: 5 | G35: =IFERROR(A35/F35," ") -> 7.2
A36: =IFERROR(B36,0)+IFERROR(C36,0)+IFERROR(D36,0)+IFERROR(E36,0) -> 7 | C36: 7 | F36: 3 | G36: =IFERROR(A36/F36," ") -> 2.3333333
A37: =IFERROR(B37,0)+IFERROR(C37,0)+IFERROR(D37,0)+IFERROR(E37,0) -> 52 | B37: 10 | E37: 42 | F37: 6 | G37: =IFERROR(A37/F37," ") -> 8.6666667
A38: =IFERROR(B38,0)+IFERROR(C38,0)+IFERROR(D38,0)+IFERROR(E38,0) -> 5 | C38: 5 | F38: 4 | G38: =IFERROR(A38/F38," ") -> 1.25
A39: =IFERROR(B39,0)+IFERROR(C39,0)+IFERROR(D39,0)+IFERROR(E39,0) -> 67 | B39: 15 | D39: 26 | E39: 26 | F39: 5 | G39: =IFERROR(A39/F39," ") -> 13.4
A40: =IFERROR(B40,0)+IFERROR(C40,0)+IFERROR(D40,0)+IFERROR(E40,0) -> 20 | D40: 20 | F40: 4 | G40: =IFERROR(A40/F40," ") -> 5
A41: =IFERROR(B41,0)+IFERROR(C41,0)+IFERROR(D41,0)+IFERROR(E41,0) -> 14 | B41: 14 | F41: 3 | G41: =IFERROR(A41/F41," ") -> 4.6666667
A42: =IFERROR(B42,0)+IFERROR(C42,0)+IFERROR(D42,0)+IFERROR(E42,0) -> 4 | C42: 4 | F42: 4 | G42: =IFERROR(A42/F42," ") -> 1
A43: =IFERROR(B43,0)+IFERROR(C43,0)+IFERROR(D43,0)+IFERROR(E43,0) -> 18 | B43: 9 | D43: 9 | F43: 4 | G43: =IFERROR(A43/F43," ") -> 4.5
A44: =IFERROR(B44,0)+IFERROR(C44,0)+IFERROR(D44,0)+IFERROR(E44,0) -> 7 | B44: 7 | F44: 5 | G44: =IFERROR(A44/F44," ") -> 1.4
A45: =IFERROR(B45,0)+IFERROR(C45,0)+IFERROR(D45,0)+IFERROR(E45,0) -> 14 | B45: 14 | F45: 4 | G45: =IFERROR(A45/F45," ") -> 3.5
A46: =IFERROR(B46,0)+IFERROR(C46,0)+IFERROR(D46,0)+IFERROR(E46,0) -> 27 | C46: 7 | D46: 20 | F46: 3 | G46: =IFERROR(A46/F46," ") -> 9
A47: =IFERROR(B47,0)+IFERROR(C47,0)+IFERROR(D47,0)+IFERROR(E47,0) -> 61 | B47: 16 | E47: 45 | F47: 5 | G47: =IFERROR(A47/F47," ") -> 12.2
A48: =IFERROR(B48,0)+IFERROR(C48,0)+IFERROR(D48,0)+IFERROR(E48,0) -> 6 | C48: 6 | F48: 4 | G48: =IFERROR(A48/F48," ") -> 1.5
A49: =IFERROR(B49,0)+IFERROR(C49,0)+IFERROR(D49,0)+IFERROR(E49,0) -> 95 | B49: 12 | D49: 28 | E49: 55 | F49: 5 | G49: =IFERROR(A49/F49," ") -> 19
A50: =IFERROR(B50,0)+IFERROR(C50,0)+IFERROR(D50,0)+IFERROR(E50,0) -> 8 | C50: 8 | F50: 3 | G50: =IFERROR(A50/F50," ") -> 2.6666667
A51: =IFERROR(B51,0)+IFERROR(C51,0)+IFERROR(D51,0)+IFERROR(E51,0) -> 34 | B51: 18 | C51: 16 | F51: 4 | G51: =IFERROR(A51/F51," ") -> 8.5
A52: =IFERROR(B52,0)+IFERROR(C52,0)+IFERROR(D52,0)+IFERROR(E52,0) -> 10 | B52: 5 | C52: 5 | F52: 5 | G52: =IFERROR(A52/F52," ") -> 2
A53: =IFERROR(B53,0)+IFERROR(C53,0)+IFERROR(D53,0)+IFERROR(E53,0) -> 24 | D53: 24 | F53: 3 | G53: =IFERROR(A53/F53," ") -> 8
A54: =IFERROR(B54,0)+IFERROR(C54,0)+IFERROR(D54,0)+IFERROR(E54,0) -> 48 | B54: 10 | E54: 38 | F54: 6 | G54: =IFERROR(A54/F54," ") -> 8
A55: =IFERROR(B55,0)+IFERROR(C55,0)+IFERROR(D55,0)+IFERROR(E55,0) -> 6 | C55: 6 | F55: 4 | G55: =IFERROR(A55/F55," ") -> 1.5
A56: =IFERROR(B56,0)+IFERROR(C56,0)+IFERROR(D56,0)+IFERROR(E56,0) -> 10 | B56: 10 | F56: 5 | G56: =IFERROR(A56/F56," ") -> 2
A57: =IFERROR(B57,0)+IFERROR(C57,0)+IFERROR(D57,0)+IFERROR(E57,0) -> 22 | B57: 12 | C57: 10 | F57: 4 | G57: =IFERROR(A57/F57," ") -> 5.5
A58: =IFERROR(B58,0)+IFERROR(C58,0)+IFERROR(D58,0)+IFERROR(E58,0) -> 1 | B58: 1 | F58: 5 | G58: =IFERROR(A58/F58," ") -> 0.2
A59: =IFERROR(B59,0)+IFERROR(C59,0)+IFERROR(D59,0)+IFERROR(E59,0) -> 8 | B59: 8 | F59: 5 | G59: =IFERROR(A59/F59," ") -> 1.6
A60: =IFERROR(B60,0)+IFERROR(C60,0)+IFERROR(D60,0)+IFERROR(E60,0) -> 14 | B60: 8 | C60: 6 | F60: 6 | G60: =IFERROR(A60/F60," ") -> 2.3333333
A61: =IFERROR(B61,0)+IFERROR(C61,0)+IFERROR(D61,0)+IFERROR(E61,0) -> 10 | C61: 10 | F61: 5 | G61: =IFERROR(A61/F61," ") -> 2
A62: =IFERROR(B62,0)+IFERROR(C62,0)+IFERROR(D62,0)+IFERROR(E62,0) -> 60 | B62: 60 | F62: 3 | G62: =IFERROR(A62/F62," ") -> 20
A63: =IFERROR(B63,0)+IFERROR(C63,0)+IFERROR(D63,0)+IFERROR(E63,0) -> 110 | B63: 55 | E63: 55 | F63: 6 | G63: =IFERROR(A63/F63," ") -> 18.333333
A64: =IFERROR(B64,0)+IFERROR(C64,0)+IFERROR(D64,0)+IFERROR(E64,0) -> 7 | C64: 7 | F64: 3 | G64: =IFERROR(A64/F64," ") -> 2.3333333
A65: =IFERROR(B65,0)+IFERROR(C65,0)+IFERROR(D65,0)+IFERROR(E65,0) -> 37 | B65: 15 | D65: 22 | F65: 4 | G65: =IFERROR(A65/F65," ") -> 9.25
A66: =IFERROR(B66,0)+IFERROR(C66,0)+IFERROR(D66,0)+IFERROR(E66,0) -> 6 | C66: 6 | F66: 5 | G66: =IFERROR(A66/F66," ") -> 1.2
A67: =IFERROR(B67,0)+IFERROR(C67,0)+IFERROR(D67,0)+IFERROR(E67,0) -> 10 | B67: 10 | F67: 6 | G67: =IFERROR(A67/F67," ") -> 1.6666667
A68: =IFERROR(B68,0)+IFERROR(C68,0)+IFERROR(D68,0)+IFERROR(E68,0) -> 24 | D68: 24 | F68: 3 | G68: =IFERROR(A68/F68," ") -> 8
A69: =IFERROR(B69,0)+IFERROR(C69,0)+IFERROR(D69,0)+IFERROR(E69,0) -> 33 | B69: 14 | D69: 19 | F69: 4 | G69: =IFERROR(A69/F69," ") -> 8.25
A70: =IFERROR(B70,0)+IFERROR(C70,0)+IFERROR(D70,0)+IFERROR(E70,0) -> 6 | C70: 6 | F70: 4 | G70: =IFERROR(A70/F70," ") -> 1.5
A71: =IFERROR(B71,0)+IFERROR(C71,0)+IFERROR(D71,0)+IFERROR(E71,0) -> 90 | D71: 25 | E71: 65 | F71: 5 | G71: =IFERROR(A71/F71," ") -> 18
A72: =IFERROR(B72,0)+IFERROR(C72,0)+IFERROR(D72,0)+IFERROR(E72,0) -> 19 | D72: 19 | F72: 3 | G72: =IFERROR(A72/F72," ") -> 6.3333333
A73: =IFERROR(B73,0)+IFERROR(C73,0)+IFERROR(D73,0)+IFERROR(E73,0) -> 19 | B73: 19 | F73: 4 | G73: =IFERROR(A73/F73," ") -> 4.75
A74: =IFERROR(B74,0)+IFERROR(C74,0)+IFERROR(D74,0)+IFERROR(E74,0) -> 50 | B74: 10 | D74: 40 | F74: 4 | G74: =IFERROR(A74/F74," ") -> 12.5
A75: =IFERROR(B75,0)+IFERROR(C75,0)+IFERROR(D75,0)+IFERROR(E75,0) -> 6 | C75: 6 | F75: 5 | G75: =IFERROR(A75/F75," ") -> 1.2
A76: =IFERROR(B76,0)+IFERROR(C76,0)+IFERROR(D76,0)+IFERROR(E76,0) -> 77 | B76: 7 | E76: 70 | F76: 6 | G76: =IFERROR(A76/F76," ") -> 12.833333
A77: =IFERROR(B77,0)+IFERROR(C77,0)+IFERROR(D77,0)+IFERROR(E77,0) -> 9 | C77: 4 | D77: 5 | F77: 3 | G77: =IFERROR(A77/F77," ") -> 3
A78: =IFERROR(B78,0)+IFERROR(C78,0)+IFERROR(D78,0)+IFERROR(E78,0) -> 130 | D78: 50 | E78: 80 | F78: 4 | G78: =IFERROR(A78/F78," ") -> 32.5
A79: =IFERROR(B79,0)+IFERROR(C79,0)+IFERROR(D79,0)+IFERROR(E79,0) -> 6 | B79: 6 | F79: 5 | G79: =IFERROR(A79/F79," ") -> 1.2
A80: =IFERROR(B80,0)+IFERROR(C80,0)+IFERROR(D80,0)+IFERROR(E80,0) -> 12 | B80: 12 | F80: 3 | G80: =IFERROR(A80/F80," ") -> 4
A81: =IFERROR(B81,0)+IFERROR(C81,0)+IFERROR(D81,0)+IFERROR(E81,0) -> 7 | C81: 7 | F81: 4 | G81: =IFERROR(A81/F81," ") -> 1.75
A82: =IFERROR(B82,0)+IFERROR(C82,0)+IFERROR(D82,0)+IFERROR(E82,0) -> 30 | D82: 30 | F82: 3 | G82: =IFERROR(A82/F82," ") -> 10
A83: =IFERROR(B83,0)+IFERROR(C83,0)+IFERROR(D83,0)+IFERROR(E83,0) -> 5 | C83: 5 | F83: 6 | G83: =IFERROR(A83/F83," ") -> 0.83333333
A84: =IFERROR(B84,0)+IFERROR(C84,0)+IFERROR(D84,0)+IFERROR(E84,0) -> 99 | B84: 9 | E84: 90 | F84: 6 | G84: =IFERROR(A84/F84," ") -> 16.5
A85: =IFERROR(B85,0)+IFERROR(C85,0)+IFERROR(D85,0)+IFERROR(E85,0) -> 20 | B85: 20 | F85: 6 | G85: =IFERROR(A85/F85," ") -> 3.3333333
A86: =IFERROR(B86,0)+IFERROR(C86,0)+IFERROR(D86,0)+IFERROR(E86,0) -> 30 | B86: 9 | D86: 21 | F86: 5 | G86: =IFERROR(A86/F86," ") -> 6
A87: =IFERROR(B87,0)+IFERROR(C87,0)+IFERROR(D87,0)+IFERROR(E87,0) -> 20 | D87: 20 | F87: 3 | G87: =IFERROR(A87/F87," ") -> 6.6666667
A88: =IFERROR(B88,0)+IFERROR(C88,0)+IFERROR(D88,0)+IFERROR(E88,0) -> 10 | B88: 10 | F88: 6 | G88: =IFERROR(A88/F88," ") -> 1.6666667
A89: =IFERROR(B89,0)+IFERROR(C89,0)+IFERROR(D89,0)+IFERROR(E89,0) -> 5 | C89: 5 | F89: 4 | G89: =IFERROR(A89/F89," ") -> 1.25
A90: =IFERROR(B90,0)+IFERROR(C90,0)+IFERROR(D90,0)+IFERROR(E90,0) -> 26 | B90: 8 | D90: 18 | F90: 3 | G90: =IFERROR(A90/F90," ") -> 8.6666667
A91: =IFERROR(B91,0)+IFERROR(C91,0)+IFERROR(D91,0)+IFERROR(E91,0) -> 11 | B91: 11 | F91: 5 | G91: =IFERROR(A91/F91," ") -> 2.2
A92: =IFERROR(B92,0)+IFERROR(C92,0)+IFERROR(D92,0)+IFERROR(E92,0) -> 5 | C92: 5 | F92: 4 | G92: =IFERROR(A92/F92," ") -> 1.25
A93: =IFERROR(B93,0)+IFERROR(C93,0)+IFERROR(D93,0)+IFERROR(E93,0) -> 26 | B93: 9 | D93: 17 | F93: 3 | G93: =IFERROR(A93/F93," ") -> 8.6666667
A94: =IFERROR(B94,0)+IFERROR(C94,0)+IFERROR(D94,0)+IFERROR(E94,0) -> 6 | C94: 6 | F94: 4 | G94: =IFERROR(A94/F94," ") -> 1.5
A95: =IFERROR(B95,0)+IFERROR(C95,0)+IFERROR(D95,0)+IFERROR(E95,0) -> 18 | D95: 18 | F95: 3 | G95: =IFERROR(A95/F95," ") -> 6
A96: =IFERROR(B96,0)+IFERROR(C96,0)+IFERROR(D96,0)+IFERROR(E96,0) -> 10 | B96: 10 | F96: 5 | G96: =IFERROR(A96/F96," ") -> 2
A97: =IFERROR(B97,0)+IFERROR(C97,0)+IFERROR(D97,0)+IFERROR(E97,0) -> 5 | C97: 5 | F97: 4 | G97: =IFERROR(A97/F97," ") -> 1.25
A98: =IFERROR(B98,0)+IFERROR(C98,0)+IFERROR(D98,0)+IFERROR(E98,0) -> 71 | B98: 11 | E98: 60 | F98: 6 | G98: =IFERROR(A98/F98," ") -> 11.833333
A99: =IFERROR(B99,0)+IFERROR(C99,0)+IFERROR(D99,0)+IFERROR(E99,0) -> 83 | B99: 13 | E99: 70 | F99: 6 | G99: =IFERROR(A99/F99," ") -> 13.833333
A100: =IFERROR(B100,0)+IFERROR(C100,0)+IFERROR(D100,0)+IFERROR(E100,0) -> 19 | D100: 19 | F100: 3 | G100: =IFERROR(A100/F100," ") -> 6.3333333
...

Sheet ANOVA1
A1: No._of_vehicles_in_family | B1: Total_monthly_fuel_expense | D1: 1 Vehicle | E1: 2 Vehicle | F1: 3 Vehicle | G1: 4 Vehicle
A2: 1 | B2: 3000 | D2: 3000 | E2: 9200 | F2: 10000 | G2: 15000 | I2: Num_Vehicle | J2: Avg_Fuel_Monthly | K2: Count | L2: Avg_Fuel_Monthly in Rs.
A3: 2 | B3: 9200 | D3: 1000 | E3: 1000 | F3: 9000 | I3: 1 Vehicle | J3: =AVERAGEIF($A$2:$A$568, 1, $B$2:$B$568) -> 1657.8123 | K3: =COUNTIF($A$2:$A$568,1) -> 357 | L3: 1657.8123
A4: 1 | B4: 1000 | D4: 1000 | E4: 9500 | F4: 2000 | I4: 2 Vehicle | J4: =AVERAGEIF($A$2:$A$568, 2, $B$2:$B$568) -> 5574.4094 | K4: =COUNTIF($A$2:$A$568,2) -> 171 | L4: 5574.4094
A5: 1 | B5: 1000 | D5: 1200 | E5: 8000 | F5: 11100 | I5: 3 Vehicle | J5: =AVERAGEIF($A$2:$A$568, 3, $B$2:$B$568) -> 8728.9474 | K5: =COUNTIF($A$2:$A$568,3) -> 38 | L5: 8728.9474
A6: 3 | B6: 10000 | D6: 3000 | E6: 6800 | F6: 8800 | I6: 4 Vehicle | J6: =AVERAGEIF($A$2:$A$568, 4, $B$2:$B$568) -> 15000 | K6: =COUNTIF($A$2:$A$568,4) -> 1 | L6: 15000
A7: 1 | B7: 1200 | D7: 1500 | E7: 9000 | F7: 9500 | K7: =SUM(K3:K6) -> 567
A8: 2 | B8: 1000 | D8: 1500 | E8: 3000 | F8: 12000
A9: 1 | B9: 3000 | D9: 900 | E9: 5200 | F9: 11000
A10: 1 | B10: 1500 | D10: 2300 | E10: 9700 | F10: 200
A11: 2 | B11: 9500 | D11: 1200 | E11: 8200 | F11: 14000
A12: 1 | B12: 1500 | D12: 6000 | E12: 8500 | F12: 9500
A13: 2 | B13: 8000 | D13: 2700 | E13: 7000 | F13: 5500
A14: 2 | B14: 6800 | D14: 2400 | E14: 5500 | F14: 8200
A15: 2 | B15: 9000 | D15: 2900 | E15: 5200 | F15: 10200
A16: 3 | B16: 9000 | D16: 5200 | E16: 5800 | F16: 9900
A17: 1 | B17: 900 | D17: 900 | E17: 3200 | F17: 5000
A18: 3 | B18: 2000 | D18: 650 | E18: 6800 | F18: 9200
A19: 1 | B19: 2300 | D19: 2400 | E19: 4500 | F19: 12000
A20: 1 | B20: 1200 | D20: 1500 | E20: 5000 | F20: 9000
A21: 3 | B21: 11100 | D21: 500 | E21: 4000 | F21: 14000 | I21: Anova: Single Factor
A22: 1 | B22: 6000 | D22: 850 | E22: 650 | F22: 500
A23: 3 | B23: 8800 | D23: 1400 | E23: 1000 | F23: 7000 | I23: SUMMARY
A24: 1 | B24: 2700 | D24: 700 | E24: 7500 | F24: 7500 | I24: Groups | J24: Count | K24: Sum | L24: Average | M24: Variance
A25: 2 | B25: 3000 | D25: 850 | E25: 5500 | F25: 1500 | I25: 1 Vehicle | J25: 357 | K25: 591839 | L25: 1657.8123 | M25: 3780721.1
A26: 2 | B26: 5200 | D26: 2700 | E26: 4800 | F26: 4500 | I26: 2 Vehicle | J26: 171 | K26: 953224 | L26: 5574.4094 | M26: 10611181
A27: 2 | B27: 9700 | D27: 750 | E27: 10000 | F27: 14000 | I27: 3 Vehicle | J27: 38 | K27: 331700 | L27: 8728.9474 | M27: 19244815
A28: 2 | B28: 8200 | D28: 650 | E28: 5000 | F28: 12500 | I28: 4 Vehicle | J28: 1 | K28: 15000 | L28: 15000 | M28: #DIV/0!
A29: 1 | B29: 2400 | D29: 650 | E29: 9500 | F29: 13200
A30: 1 | B30: 2900 | D30: 650 | E30: 4800 | F30: 1200
A31: 3 | B31: 9500 | D31: 1000 | E31: 3200 | F31: 13800 | I31: ANOVA
A32: 1 | B32: 5200 | D32: 900 | E32: 12000 | F32: 14500 | I32: Source of Variation | J32: SS | K32: df | L32: MS | M32: F | N32: P-value | O32: F crit
A33: 2 | B33: 8500 | D33: 700 | E33: 650 | F33: 15600 | I33: Between Groups | J33: 3.1034518e+09 | K33: 3 | L33: 1.0344839e+09 | M33: 150.81051 | N33: 9.9800412e-72 | O33: 2.6207328
A34: 2 | B34: 7000 | D34: 1200 | E34: 4200 | F34: 14800 | I34: Within Groups | J34: 3.8618956e+09 | K34: 563 | L34: 6859494.8
A35: 2 | B35: 5500 | D35: 3200 | E35: 3600 | F35: 9700
A36: 1 | B36: 900 | D36: 750 | E36: 3800 | F36: 4500 | I36: Total | J36: 6.9653474e+09 | K36: 566
A37: 2 | B37: 5200 | D37: 2300 | E37: 8200 | F37: 4400
A38: 1 | B38: 650 | D38: 2000 | E38: 9000 | F38: 9400
A39: 3 | B39: 12000 | D39: 1000 | E39: 7000 | F39: 3000 | I39: Effect Size n^2(Eda-squared)
A40: 1 | B40: 2400 | D40: 1500 | E40: 4300 | I40: ᾐ2 | J40: =J33/J36 -> 0.44555593
A41: 1 | B41: 1500 | D41: 2000 | E41: 3400
A42: 1 | B42: 500 | D42: 1200 | E42: 4800 | I42: vehicle ownership explains 44.5% of fuel expenditure variance.
A43: 2 | B43: 5800 | D43: 900 | E43: 5800
A44: 1 | B44: 850 | D44: 2600 | E44: 8500
A45: 1 | B45: 1400 | D45: 1100 | E45: 5200
A46: 2 | B46: 3200 | D46: 650 | E46: 5600
A47: 2 | B47: 6800 | D47: 1300 | E47: 7100
A48: 1 | B48: 700 | D48: 650 | E48: 5200
A49: 3 | B49: 11000 | D49: 720 | E49: 4800
A50: 1 | B50: 850 | D50: 2300 | E50: 6400
A51: 2 | B51: 4500 | D51: 1200 | E51: 4900
A52: 3 | B52: 200 | D52: 600 | E52: 1000
A53: 1 | B53: 2700 | D53: 2400 | E53: 1000
A54: 2 | B54: 5000 | D54: 700 | E54: 4200
... A172: 2 | B172: 6000 | D172: 1000 | E172: 6600
A173: 1 | B173: 550 | D173: 1300
A174: 3 | B174: 9000 | D174: 390
A175: 2 | B175: 5000 | D175: 3000
A176: 1 | B176: 1500 | D176: 650
A177: 1 | B177: 550 | D177: 850
A178: 2 | B178: 7000 | D178: 3000
A179: 1 | B179: 1600 | D179: 300
A180: 1 | B180: 600 | D180: 2800
A181: 2 | B181: 9000 | D181: 900
A182: 2 | B182: 5200 | D182: 650
A183: 1 | B183: 1800 | D183: 1000
A184: 3 | B184: 14000 | D184: 3000
... A358: 1 | B358: 3900 | D358: 2000
A359: 1 | B359: 350
A360: 2 | B360: 3700
A361: 1 | B361: 1300
A362: 1 | B362: 1000
A363: 1 | B363: 780
A364: 2 | B364: 3800
A365: 1 | B365: 520
A366: 1 | B366: 900
A367: 2 | B367: 9900
A368: 1 | B368: 11430
A369: 1 | B369: 390
A370: 2 | B370: 4000
... A568: 1 | B568: 2000

Sheet ANOVA2
A1: Below10k | B1: 10k-30k | C1: 30k-50k | D1: 50k-70k | E1: 70k-1L | F1: above 1L
A2: 3000 | B2: 9200 | C2: 10000 | D2: 6800 | E2: 8800 | F2: 9500
A3: 1200 | B3: 1000 | C3: 1000 | D3: 9000 | E3: 8500 | F3: 5800
A4: 1500 | B4: 1000 | C4: 1500 | D4: 9700 | E4: 12000 | F4: 14000 | I4: Anova: Single Factor
A5: 900 | B5: 3000 | C5: 8000 | D5: 9500 | E5: 11000 | F5: 8200
A6: 2000 | B6: 3000 | C6: 9000 | D6: 5500 | E6: 3200 | F6: 10200 | I6: SUMMARY
A7: 1200 | B7: 5200 | C7: 2300 | D7: 2400 | E7: 5200 | F7: 9900 | I7: Groups | J7: Count | K7: Sum | L7: Average | M7: Variance
A8: 2700 | B8: 2400 | C8: 11100 | D8: 4500 | E8: 4900 | F8: 9000 | I8: Below10k | J8: 125 | K8: 163630 | L8: 1309.04 | M8: 4075202.3
A9: 2900 | B9: 7000 | C9: 6000 | D9: 5500 | E9: 12000 | F9: 10000 | I9: 10k-30k | J9: 101 | K9: 206954 | L9: 2049.0495 | M9: 10498319
A10: 650 | B10: 5200 | C10: 8200 | D10: 10000 | E10: 5000 | F10: 14000 | I10: 30k-50k | J10: 203 | K10: 726270 | L10: 3577.6847 | M10: 9847244.6
A11: 500 | B11: 1500 | C11: 5200 | D11: 4800 | E11: 5200 | F11: 12500 | I11: 50k-70k | J11: 98 | K11: 482739 | L11: 4925.9082 | M11: 10202293
A12: 850 | B12: 1400 | C12: 900 | D12: 3200 | E12: 1000 | F12: 13200 | I12: 70k-1L | J12: 23 | K12: 141070 | L12: 6133.4783 | M12: 12504242
A13: 850 | B13: 700 | C13: 3200 | D13: 650 | E13: 3900 | F13: 13800 | I13: above 1L | J13: 17 | K13: 171100 | L13: 10064.706 | M13: 16638676
A14: 200 | B14: 5000 | C14: 6800 | D14: 2600 | E14: 14500 | F14: 15600
A15: 750 | B15: 650 | C15: 2700 | D15: 9000 | E15: 9600 | F15: 14800
A16: 650 | B16: 650 | C16: 4000 | D16: 9500 | E16: 4400 | F16: 4100 | I16: ANOVA
A17: 650 | B17: 900 | C17: 7500 | D17: 5500 | E17: 3250 | F17: 3900 | I17: Source of Variation | J17: SS | K17: df | L17: MS | M17: F | N17: P-value | O17: F crit
A18: 1000 | B18: 1200 | C18: 4800 | D18: 7100 | E18: 3900 | F18: 2600 | I18: Between Groups | J18: 1.8901124e+09 | K18: 5 | L18: 3.7802248e+08 | M18: 41.785378 | N18: 1.3889177e-36 | O18: 2.2300842
A19: 1000 | B19: 9500 | C19: 2300 | D19: 4900 | E19: 4160 | I19: Within Groups | J19: 5.075235e+09 | K19: 561 | L19: 9046764.7
A20: 700 | B20: 1500 | C20: 2000 | D20: 5200 | E20: 4350
A21: 750 | B21: 900 | C21: 5000 | D21: 9200 | E21: 4800 | I21: Total | J21: 6.9653474e+09 | K21: 566
A22: 1000 | B22: 1100 | C22: 12000 | D22: 6000 | E22: 3000
A23: 2000 | B23: 1300 | C23: 4200 | D23: 7000 | E23: 3520
A24: 1200 | B24: 650 | C24: 3600 | D24: 1800 | E24: 4890 | I24: Summary | L24: Effect Size n^2(Eda-squared)
A25: 650 | B25: 720 | C25: 3800 | D25: 750 | I25: Income group | J25: Avg_monthly_fuel_expense | L25: ᾐ2 | M25: =J18/J21 -> 0.27135939
A26: 600 | B26: 1200 | C26: 2300 | D26: 1800 | I26: Below10k | J26: 1309.04
A27: 700 | B27: 7000 | C27: 8200 | D27: 900 | I27: 10k-30k | J27: 2049.0495 | L27: Income Group Explains 27.12% of fuel expenditure variance
A28: 700 | B28: 600 | C28: 2400 | D28: 7000 | I28: 30k-50k | J28: 3577.6847
A29: 3000 | B29: 5800 | C29: 4300 | D29: 3200 | I29: 50k-70k | J29: 4925.9082
A30: 580 | B30: 8500 | C30: 3400 | D30: 8500 | I30: 70k-1L | J30: 6133.4783
A31: 500 | B31: 650 | C31: 4800 | D31: 3600 | I31: above 1L | J31: 10064.706
A32: 720 | B32: 650 | C32: 750 | D32: 1200
A33: 850 | B33: 600 | C33: 1100 | D33: 9000
A34: 720 | B34: 750 | C34: 2500 | D34: 10200
A35: 650 | B35: 20000 | C35: 1400 | D35: 10800
A36: 700 | B36: 950 | C36: 5600 | D36: 3609
A37: 600 | B37: 650 | C37: 780 | D37: 1900
A38: 600 | B38: 5200 | C38: 4800 | D38: 9700
A39: 500 | B39: 900 | C39: 6400 | D39: 3700
A40: 1000 | B40: 800 | C40: 990 | D40: 4200
A41: 900 | B41: 600 | C41: 5000 | D41: 12000
A42: 850 | B42: 1000 | C42: 4200 | D42: 4200
A43: 550 | B43: 1000 | C43: 9500 | D43: 12800
... A99: 520 | B99: 555 | C99: 4400 | D99: 2000
A100: 1560 | B100: 1000 | C100: 1300
A101: 520 | B101: 520 | C101: 3600
A102: 390 | B102: 520 | C102: 11000
A103: 1170 | C103: 1000
A104: 1430 | C104: 4000
A105: 1170 | C105: 1300
A106: 1560 | C106: 11600
A107: 520 | C107: 650
A108: 1170 | C108: 3000
A109: 900 | C109: 2800
A110: 520 | C110: 900
A111: 420 | C111: 4000
A112: 1000 | C112: 12000
A113: 1000 | C113: 3000
A114: 1170 | C114: 4000
... A126: 950 | C126: 3800
C127: 520
C128: 9900
C129: 11430
C130: 390
C131: 4000
C132: 1070
C133: 2400
C134: 1700
C135: 6500
C136: 2600
C137: 3800
C138: 1000
... C204: 680

Sheet Hypothesis_Summary
A1: Hypothesis Testing Summary - Fuel Consumption Analysis, Phaltan 2025
A2: α = 0.05 | All tests conducted on n = 567 households
A4: Hypothesis Table:
B6: Test | C6: Variables | D6: H0 | E6: H1 | F6: Test Statistic | G6: p-value | H6: Effect Size | I6: Decision | J6: Practical Meaning
A7: H1 | B7: Independent T-test | C7: Gender vs Fuel Expense | D7: No difference in fuel spending between males and females | E7: Significant gender difference exists | F7: t = 12.86 | G7: 5.2783151e-30 | H7: Cohen's d = 1.021 | I7: Reject H0 | J7: Males spend ₹4,731/month vs females ₹1,530 - 3.1x difference
A8: H2 | B8: One-way ANOVA | C8: Income Groups vs Fuel | D8: No difference across 6 income groups | E8: At least one group differs | F8: F = 41.79 | G8: 1.3889177e-36 | H8: ᾐ2 = 0.271 (Medium-Large) | I8: Reject H0 | J8: Income strongly determines fuel spending - above ₹1L spends 7.6x more than below ₹10K
A9: H3 | B9: One-way ANOVA | C9: Num_Vehicles vs Fuel | D9: Vehicle ownership has no effect | E9: Vehicle ownership significantly affects fuel | F9: F = 150.81 | G9: 9.9800412e-72 | H9: ᾐ2 = 0.445 (Large) | I9: Reject H0 | J9: Strongest finding - each vehicle adds ₹2,716/month
A10: H4 | B10: Pearson Correlation | C10: Income vs Fuel | D10: No correlation ( r= 0) | E10: Significant Positive correlation | F10: r = 0.518 | G10: p<0.05 (n = 567) | H10: r2 = 0.268 | I10: Reject H0 | J10: Moderate positive relationship - income explains 26.8% of fuel variance
A13: Effect Size Reference table:
A15: Effect Size Measure | B15: Value | C15: Benchmark | D15: Classification
A16: ᾐ2 ( Vehicle ANOVA) | B16: 0.521 | C16: Cohen:>0.14 = Large | D16: Large
A17: ᾐ2 ( Income ANOVA) | B17: 0.271 | C17: Cohen:>0.14 = Large | D17: Large
A18: r2 (Correlation) | B18: 0.268 | C18: 0.26 = Moderate | D18: Moderate
A19: Adj R2 (Regression) | B19: 0.5176 | C19: >.50 = Strong | D19: Strong
A22: Conclusion :
A24: All four hypothesis tests yeild statistically significant results at α= 0.05. Vehicle ownership (H3) demonstrates the largest practical effect ( ᾐ2 = 0.521), confirming it as the primary driver of fuel consuption in Phaltan. Income level ( H2, H4) and gender (H1) are also significant determinants. These results collectively validate the regression model findings ( Adj R2 = 0.5176) and support the study's recommendations for targeted transport policy interventions.

Sheet T-test
A1: Female_Expenses | B1: Male_Expenses | D1: T-test p-value(Male vs Female)
A2: 3000 | B2: 9200 | D2: t-test | E2: =_xlfn.T.TEST(B2:B321,A2:A248,2,2) -> 5.2783151e-30
A3: 1000 | B3: 1000
A4: 1200 | B4: 10000
A5: 1000 | B5: 3000 | E5: Male Avg Fuel Expenses | F5: =AVERAGE(B2:B321) -> 4730.6187 | H5: variance for Males | I5: =_xlfn.VAR.S(B2:B321) -> 13748144
A6: 1500 | B6: 9500 | E6: Female Avg Fuel Expenses | F6: =AVERAGE(A2:A248) -> 1530.2227 | H6: variance for Females | I6: =_xlfn.VAR.S(A2:A248) -> 4682424
A7: 6800 | B7: 1500 | E7: T-test,p-value | F7: 5.2783151e-30
A8: 900 | B8: 8000 | E8: Decision | F8: =IF(F7<0.5,"Reject H0 - Significant","Fail to reject H0") -> Reject H0 - Significant | H8: Pooled Standard Deviation (Sp)
A9: 1200 | B9: 9000
A10: 6000 | B10: 9000 | H10: Sp = | I10: =SQRT(((319*E15)+(246*F15))/(319+247-2)) -> 3133.4204
A11: 3000 | B11: 2000 | D11: T-Test: Two-Sample Assuming Unequal Variances
A12: 5200 | B12: 2300 | H12: Cohen's d
A13: 8200 | B13: 11100 | E13: Male_Expenses | F13: Female_Expenses
A14: 5200 | B14: 8800 | D14: Mean | E14: 4730.6187 | F14: 1530.2227 | H14: d = | I14: =(E14-F14)/I10 -> 1.0213746
A15: 900 | B15: 2700 | D15: Variance | E15: 13748144 | F15: 4682424
A16: 650 | B16: 9700 | D16: Observations | E16: 320 | F16: 247 | H16: t-Statistic
A17: 2400 | B17: 2400 | D17: Hypothesized Mean Difference | E17: 0
A18: 500 | B18: 2900 | D18: df | E18: 529 | H18: t= | I18: =(E14-F14)/(SQRT((E15/320)+(F15/247))) -> 12.861386
A19: 850 | B19: 9500 | D19: t Stat | E19: 12.861386
A20: 3200 | B20: 8500 | D20: P(T<=t) one-tail | E20: 1.9663158e-33
A21: 700 | B21: 7000 | D21: t Critical one-tail | E21: 1.6477392
A22: 850 | B22: 5500 | D22: P(T<=t) two-tail | E22: 3.9326316e-33
A23: 200 | B23: 5200 | D23: t Critical two-tail | E23: 1.9644585
A24: 2700 | B24: 12000
A25: 750 | B25: 1500
A26: 650 | B26: 5800
A27: 650 | B27: 1400
A28: 650 | B28: 6800
A29: 900 | B29: 11000
A30: 700 | B30: 4500
A31: 3200 | B31: 5000
A32: 750 | B32: 4000
A33: 2300 | B33: 650
A34: 1000 | B34: 1000
A35: 4800 | B35: 1000
... A248: 2000 | B248: 7200
B249: 3250
B250: 4550
B251: 1430
B252: 780
B253: 4100
B254: 910
B255: 1300
B256: 3640
B257: 1820
B258: 3900
B259: 1170
B260: 910
... B321: 6600

Sheet Regression1
A1: Total_monthly_fuel_expense | B1: Income_Numeric | C1: No._of_vehicles_in_family | D1: Total_family _members | E1: Distance_home_ workplacr | G1: SUMMARY OUTPUT | Q1: RESIDUAL OUTPUT
A2: 3000 | B2: 5000 | C2: 1 | D2: 4 | E2: 11
A3: 9200 | B3: 20000 | C3: 2 | D3: 4 | E3: 11 | G3: Regression Statistics | Q3: Observation | R3: Predicted Total_monthly_fuel_expense | S3: Residuals
A4: 1000 | B4: 20000 | C4: 1 | D4: 6 | E4: 14 | G4: Multiple R | H4: 0.72179933 | Q4: 1 | R4: 1135.6479 | S4: 1864.3521
A5: 1000 | B5: 20000 | C5: 1 | D5: 5 | E5: 10 | G5: R Square | H5: 0.52099428 | Q5: 2 | R5: 4357.1854 | S5: 4842.8146
A6: 10000 | B6: 40000 | C6: 3 | D6: 5 | E6: 15 | G6: Adjusted R Square | H6: 0.51758499 | Q6: 3 | R6: 2654.9504 | S6: -1654.9504
A7: 1200 | B7: 5000 | C7: 1 | D7: 3 | E7: 6 | G7: Standard Error | H7: 2436.5402 | Q7: 4 | R7: 1928.4946 | S7: -928.49457
A8: 1000 | B8: 40000 | C8: 2 | D8: 2 | E8: 21 | G8: Observations | H8: 567 | Q8: 5 | R8: 8473.7478 | S8: 1526.2522
A9: 3000 | B9: 20000 | C9: 1 | D9: 6 | E9: 18 | Q9: 6 | R9: 321.3288 | S9: 878.6712
A10: 1500 | B10: 40000 | C10: 1 | D10: 3 | E10: 7 | G10: ANOVA | Q10: 7 | R10: 5160.0891 | S10: -4160.0891
A11: 9500 | B11: 125000 | C11: 2 | D11: 4 | E11: 20 | H11: df | I11: SS | J11: MS | K11: F | L11: Significance F | Q11: 8 | R11: 3006.4035 | S11: -6.4034712
A12: 1500 | B12: 5000 | C12: 1 | D12: 3 | E12: 5 | G12: Regression | H12: 4 | I12: 3.6289061e+09 | J12: 9.0722654e+08 | K12: 152.81591 | L12: 2.2091866e-88 | Q12: 9 | R12: 1589.1757 | S12: -89.175702
A13: 8000 | B13: 40000 | C13: 2 | D13: 5 | E13: 14 | G13: Residual | H13: 562 | I13: 3.3364412e+09 | J13: 5936728.2 | Q13: 10 | R13: 8687.9057 | S13: 812.09425
A14: 6800 | B14: 60000 | C14: 2 | D14: 4 | E14: 10 | G14: Total | H14: 566 | I14: 6.9653474e+09 | Q14: 11 | R14: 233.46553 | S14: 1266.5345
A15: 9000 | B15: 60000 | C15: 2 | D15: 4 | E15: 18 | Q15: 12 | R15: 5670.0543 | S15: 2329.9457
A16: 9000 | B16: 40000 | C16: 3 | D16: 5 | E16: 15 | H16: Coefficients | I16: Standard Error | J16: t Stat | K16: P-value | L16: Lower 95% | M16: Upper 95% | N16: Lower 95.0% | O16: Upper 95.0% | Q16: 13 | R16: 5617.8748 | S16: 1182.1252
A17: 900 | B17: 5000 | C17: 1 | D17: 4 | E17: 5 | G17: Intercept | H17: -4215.2583 | I17: 521.73238 | J17: -8.0793495 | K17: 3.9983103e-15 | L17: -5240.0419 | M17: -3190.4746 | N17: -5240.0419 | O17: -3190.4746 | Q17: 14 | R17: 6320.781 | S17: 2679.219
A18: 2000 | B18: 5000 | C18: 3 | D18: 5 | E18: 9 | G18: Income_Numeric | H18: 0.033713818 | I18: 0.0045861449 | J18: 7.3512326 | K18: 6.9715728e-13 | L18: 0.024705739 | M18: 0.042721896 | N18: 0.024705739 | O18: 0.042721896 | Q18: 15 | R18: 8473.7478 | S18: 526.25219
A19: 2300 | B19: 40000 | C19: 1 | D19: 3 | E19: 10 | G19: No._of_vehicles_in_family | H19: 2715.8303 | I19: 196.11288 | J19: 13.848301 | K19: 9.8351637e-38 | L19: 2330.6265 | M19: 3101.034 | N19: 2330.6265 | O19: 3101.034 | Q19: 16 | R19: 608.46823 | S19: 291.53177
A20: 1200 | B20: 5000 | C20: 1 | D20: 4 | E20: 6 | G20: Total_family _members | H20: 375.0027 | I20: 108.20557 | J20: 3.4656505 | K20: 0.00056934018 | L20: 162.46596 | M20: 587.53944 | N20: 162.46596 | O20: 587.53944 | Q20: 17 | R20: 6766.5845 | S20: -4766.5845
A21: 11100 | B21: 40000 | C21: 3 | D21: 6 | E21: 12 | G21: Distance_home_ workplacr | H21: 87.863275 | I21: 23.036599 | J21: 3.8140732 | K21: 0.00015183426 | L21: 42.614925 | M21: 133.11163 | N21: 42.614925 | O21: 133.11163 | Q21: 18 | R21: 1852.7655 | S21: 447.23447
A22: 6000 | B22: 40000 | C22: 1 | D22: 3 | E22: 10 | Q22: 19 | R22: 696.3315 | S22: 503.6685
A23: 8800 | B23: 85000 | C23: 3 | D23: 5 | E23: 14 | Q23: 20 | R23: 8585.1607 | S23: 2514.8393
A24: 2700 | B24: 5000 | C24: 1 | D24: 4 | E24: 14 | G24: CI Summary table | Q24: 21 | R24: 1852.7655 | S24: 4147.2345
A25: 3000 | B25: 20000 | C25: 2 | D25: 6 | E25: 4 | Q25: 22 | R25: 9903.0063 | S25: -1103.0063
A26: 5200 | B26: 20000 | C26: 2 | D26: 5 | E26: 8 | G26: Variable | H26: Coefficient (β) | I26: p-value | J26: Lower 95% CI | K26: Upper 95% CI | L26: Report as | Q26: 23 | R26: 1399.2377 | S26: 1300.7623
A27: 9700 | B27: 60000 | C27: 2 | D27: 4 | E27: 15 | G27: Intercept | H27: =H17 -> -4215.2583 | I27: =K17 -> 3.9983103e-15 | J27: =L17 -> -5240.0419 | K27: =M17 -> -3190.4746 | L27: - | Q27: 24 | R27: 4492.1479 | S27: -1492.1479
A28: 8200 | B28: 40000 | C28: 2 | D28: 5 | E28: 8 | G28: Num_Vehicles | H28: =H19 -> 2715.8303 | I28: =K19 -> 9.8351637e-38 | J28: =L19 -> 2330.6265 | K28: =M19 -> 3101.034 | L28: β= 2,716 (95%CI: 2,330-3,101) | Q28: 25 | R28: 4468.5983 | S28: 731.40172
A29: 2400 | B29: 20000 | C29: 1 | D29: 3 | E29: 7 | G29: Income_Numeric | H29: =H18 -> 0.033713818 | I29: =K18 -> 6.9715728e-13 | J29: =L18 -> 0.024705739 | K29: =M18 -> 0.042721896 | L29: β= 0.034 (95%CI: X-Y) | Q29: 26 | R29: 6057.1912 | S29: 3642.8088
A30: 2900 | B30: 5000 | C30: 1 | D30: 4 | E30: 12 | G30: Family_Members | H30: =H20 -> 375.0027 | I30: =K20 -> 0.00056934018 | J30: =L20 -> 162.46596 | K30: =M20 -> 587.53944 | L30: β= 375 (95%CI: X-Y) | Q30: 27 | R30: 5142.8746 | S30: 3057.1254
A31: 9500 | B31: 60000 | C31: 3 | D31: 6 | E31: 20 | G31: Distance_km | H31: =H21 -> 87.863275 | I31: =K21 -> 0.00015183426 | J31: =L21 -> 42.614925 | K31: =M21 -> 133.11163 | L31: β= 88 (95%CI: X-Y) | Q31: 28 | R31: 914.89935 | S31: 1485.1007
A32: 5200 | B32: 40000 | C32: 1 | D32: 3 | E32: 9 | Q32: 29 | R32: 1223.5112 | S32: 1676.4888
A33: 8500 | B33: 85000 | C33: 2 | D33: 4 | E33: 18 | G33: Note : 95% CI: if we repeated this survey 100 times, the true coefficient would fall within this range 95 times | Q33: 30 | R33: 9962.3432 | S33: -462.34325
A34: 7000 | B34: 20000 | C34: 2 | D34: 5 | E34: 10 | Q34: 31 | R34: 1764.9023 | S34: 3435.0977
A35: 5500 | B35: 60000 | C35: 2 | D35: 5 | E35: 12 | Q35: 32 | R35: 7163.6265 | S35: 1336.3735
A36: 900 | B36: 40000 | C36: 1 | D36: 3 | E36: 4 | Q36: 33 | R36: 4644.3248 | S36: 2355.6752
A37: 5200 | B37: 20000 | C37: 2 | D37: 6 | E37: 10 | Q37: 34 | R37: 6168.6041 | S37: -668.60409
A38: 650 | B38: 5000 | C38: 1 | D38: 4 | E38: 5 | Q38: 35 | R38: 1325.5859 | S38: -425.58588
A39: 12000 | B39: 85000 | C39: 3 | D39: 5 | E39: 15 | Q39: 36 | R39: 5019.3275 | S39: 180.67247
A40: 2400 | B40: 60000 | C40: 1 | D40: 4 | E40: 6 | Q40: 37 | R40: 608.46823 | S40: 41.531772
A41: 1500 | B41: 20000 | C41: 1 | D41: 3 | E41: 9 | Q41: 38 | R41: 9990.8696 | S41: 2009.1304
A42: 500 | B42: 5000 | C42: 1 | D42: 4 | E42: 3 | Q42: 39 | R42: 2550.5915 | S42: -150.59148
A43: 5800 | B43: 125000 | C43: 2 | D43: 4 | E43: 10 | Q43: 40 | R43: 1090.6259 | S43: 409.3741
A44: 850 | B44: 5000 | C44: 1 | D44: 5 | E44: 6 | Q44: 41 | R44: 432.74168 | S44: 67.258322
A45: 1400 | B45: 20000 | C45: 1 | D45: 4 | E45: 9 | Q45: 42 | R45: 7809.273 | S45: -2009.273
... A568: 2000 | B568: 60000 | C568: 1 | D568: 5 | E568: 9 | Q568: 565 | R568: 4703.5583 | S568: 1896.4417
Q569: 566 | R569: 1987.728 | S569: -1307.728
Q570: 567 | R570: 3189.184 | S570: -1189.184

Sheet Regression2
A1: Per_Capita_Vehicle_Fuel | B1: Has_2-Wheeler | C1: Has_4-Wheeler | D1: No._of_vehicles_in_family | E1: Income_Numeric | F1: Type_vehicle | H1: SUMMARY OUTPUT
A2: 7.5 | B2: =IF(ISNUMBER(SEARCH("bike",F2))+ISNUMBER(SEARCH("scooty",F2))>0,1,0) -> 1 | C2: =IF(ISNUMBER(SEARCH("car",F2))+ISNUMBER(SEARCH("Commercial vehicle",F2))>0,1,0) -> 0 | D2: 1 | E2: 5000 | F2: bikes
A3: 19 | B3: =IF(ISNUMBER(SEARCH("bike",F3))+ISNUMBER(SEARCH("scooty",F3))>0,1,0) -> 1 | C3: =IF(ISNUMBER(SEARCH("car",F3))+ISNUMBER(SEARCH("Commercial vehicle",F3))>0,1,0) -> 1 | D3: 2 | E3: 20000 | F3: bikes, Commercial vehicle | H3: Regression Statistics
A4: 1.6666667 | B4: =IF(ISNUMBER(SEARCH("bike",F4))+ISNUMBER(SEARCH("scooty",F4))>0,1,0) -> 1 | C4: =IF(ISNUMBER(SEARCH("car",F4))+ISNUMBER(SEARCH("Commercial vehicle",F4))>0,1,0) -> 0 | D4: 1 | E4: 20000 | F4: Scooty | H4: Multiple R | I4: 0.73521491
A5: 4 | B5: =IF(ISNUMBER(SEARCH("bike",F5))+ISNUMBER(SEARCH("scooty",F5))>0,1,0) -> 1 | C5: =IF(ISNUMBER(SEARCH("car",F5))+ISNUMBER(SEARCH("Commercial vehicle",F5))>0,1,0) -> 0 | D5: 1 | E5: 20000 | F5: bikes | H5: R Square | I5: 0.54054097
A6: 22.6 | B6: =IF(ISNUMBER(SEARCH("bike",F6))+ISNUMBER(SEARCH("scooty",F6))>0,1,0) -> 1 | C6: =IF(ISNUMBER(SEARCH("car",F6))+ISNUMBER(SEARCH("Commercial vehicle",F6))>0,1,0) -> 1 | D6: 3 | E6: 40000 | F6: bikes, car, Commercial vehicle | H6: Adjusted R Square | I6: 0.5372708
A7: 3.3333333 | B7: =IF(ISNUMBER(SEARCH("bike",F7))+ISNUMBER(SEARCH("scooty",F7))>0,1,0) -> 1 | C7: =IF(ISNUMBER(SEARCH("car",F7))+ISNUMBER(SEARCH("Commercial vehicle",F7))>0,1,0) -> 0 | D7: 1 | E7: 5000 | F7: Scooty | H7: Standard Error | I7: 4.2204989
A8: 45 | B8: =IF(ISNUMBER(SEARCH("bike",F8))+ISNUMBER(SEARCH("scooty",F8))>0,1,0) -> 1 | C8: =IF(ISNUMBER(SEARCH("car",F8))+ISNUMBER(SEARCH("Commercial vehicle",F8))>0,1,0) -> 1 | D8: 2 | E8: 40000 | F8: bikes, car | H8: Observations | I8: 567
A9: 4.6666667 | B9: =IF(ISNUMBER(SEARCH("bike",F9))+ISNUMBER(SEARCH("scooty",F9))>0,1,0) -> 1 | C9: =IF(ISNUMBER(SEARCH("car",F9))+ISNUMBER(SEARCH("Commercial vehicle",F9))>0,1,0) -> 0 | D9: 1 | E9: 20000 | F9: bikes
A10: 4 | B10: =IF(ISNUMBER(SEARCH("bike",F10))+ISNUMBER(SEARCH("scooty",F10))>0,1,0) -> 1 | C10: =IF(ISNUMBER(SEARCH("car",F10))+ISNUMBER(SEARCH("Commercial vehicle",F10))>0,1,0) -> 0 | D10: 1 | E10: 40000 | F10: Scooty | H10: ANOVA
A11: 15 | B11: =IF(ISNUMBER(SEARCH("bike",F11))+ISNUMBER(SEARCH("scooty",F11))>0,1,0) -> 0 | C11: =IF(ISNUMBER(SEARCH("car",F11))+ISNUMBER(SEARCH("Commercial vehicle",F11))>0,1,0) -> 1 | D11: 2 | E11: 125000 | F11: car, Electric Vehicle | I11: df | J11: SS | K11: MS | L11: F | M11: Significance F
A12: 2.6666667 | B12: =IF(ISNUMBER(SEARCH("bike",F12))+ISNUMBER(SEARCH("scooty",F12))>0,1,0) -> 1 | C12: =IF(ISNUMBER(SEARCH("car",F12))+ISNUMBER(SEARCH("Commercial vehicle",F12))>0,1,0) -> 0 | D12: 1 | E12: 5000 | F12: Scooty | H12: Regression | I12: 4 | J12: 11777.3 | K12: 2944.3249 | L12: 165.2944 | M12: 1.886831e-93
A13: 16 | B13: =IF(ISNUMBER(SEARCH("bike",F13))+ISNUMBER(SEARCH("scooty",F13))>0,1,0) -> 1 | C13: =IF(ISNUMBER(SEARCH("car",F13))+ISNUMBER(SEARCH("Commercial vehicle",F13))>0,1,0) -> 1 | D13: 2 | E13: 40000 | F13: bikes, Commercial vehicle | H13: Residual | I13: 562 | J13: 10010.687 | K13: 17.812611
A14: 16.75 | B14: =IF(ISNUMBER(SEARCH("bike",F14))+ISNUMBER(SEARCH("scooty",F14))>0,1,0) -> 1 | C14: =IF(ISNUMBER(SEARCH("car",F14))+ISNUMBER(SEARCH("Commercial vehicle",F14))>0,1,0) -> 1 | D14: 2 | E14: 60000 | F14: bikes, car | H14: Total | I14: 566 | J14: 21787.987
A15: 19.25 | B15: =IF(ISNUMBER(SEARCH("bike",F15))+ISNUMBER(SEARCH("scooty",F15))>0,1,0) -> 1 | C15: =IF(ISNUMBER(SEARCH("car",F15))+ISNUMBER(SEARCH("Commercial vehicle",F15))>0,1,0) -> 1 | D15: 2 | E15: 60000 | F15: bikes, car
A16: 17.4 | B16: =IF(ISNUMBER(SEARCH("bike",F16))+ISNUMBER(SEARCH("scooty",F16))>0,1,0) -> 1 | C16: =IF(ISNUMBER(SEARCH("car",F16))+ISNUMBER(SEARCH("Commercial vehicle",F16))>0,1,0) -> 1 | D16: 3 | E16: 40000 | F16: bikes, Scooty, car | I16: Coefficients | J16: Standard Error | K16: t Stat | L16: P-value | M16: Lower 95% | N16: Upper 95% | O16: Lower 95.0% | P16: Upper 95.0%
A17: 1.75 | B17: =IF(ISNUMBER(SEARCH("bike",F17))+ISNUMBER(SEARCH("scooty",F17))>0,1,0) -> 1 | C17: =IF(ISNUMBER(SEARCH("car",F17))+ISNUMBER(SEARCH("Commercial vehicle",F17))>0,1,0) -> 0 | D17: 1 | E17: 5000 | F17: Scooty | H17: Intercept | I17: -1.6594571 | J17: 0.66104921 | K17: -2.5103383 | L17: 0.01234133 | M17: -2.9578861 | N17: -0.36102821 | O17: -2.9578861 | P17: -0.36102821
A18: 6.2 | B18: =IF(ISNUMBER(SEARCH("bike",F18))+ISNUMBER(SEARCH("scooty",F18))>0,1,0) -> 1 | C18: =IF(ISNUMBER(SEARCH("car",F18))+ISNUMBER(SEARCH("Commercial vehicle",F18))>0,1,0) -> 1 | D18: 3 | E18: 5000 | F18: bikes, car | H18: Has_2-Wheeler | I18: -0.005197458 | J18: 0.76093404 | K18: -0.0068303661 | L18: 0.99455262 | M18: -1.4998196 | N18: 1.4894247 | O18: -1.4998196 | P18: 1.4894247
A19: 6 | B19: =IF(ISNUMBER(SEARCH("bike",F19))+ISNUMBER(SEARCH("scooty",F19))>0,1,0) -> 1 | C19: =IF(ISNUMBER(SEARCH("car",F19))+ISNUMBER(SEARCH("Commercial vehicle",F19))>0,1,0) -> 0 | D19: 1 | E19: 40000 | F19: bikes | H19: Has_4-Wheeler | I19: 5.4233297 | J19: 0.64459072 | K19: 8.4136019 | L19: 3.3023242e-16 | M19: 4.1572285 | N19: 6.689431 | O19: 4.1572285 | P19: 6.689431
A20: 2.5 | B20: =IF(ISNUMBER(SEARCH("bike",F20))+ISNUMBER(SEARCH("scooty",F20))>0,1,0) -> 1 | C20: =IF(ISNUMBER(SEARCH("car",F20))+ISNUMBER(SEARCH("Commercial vehicle",F20))>0,1,0) -> 0 | D20: 1 | E20: 5000 | F20: Scooty | H20: No._of_vehicles_in_family | I20: 3.423869 | J20: 0.46894517 | K20: 7.3012139 | L20: 9.7996021e-13 | M20: 2.5027697 | N20: 4.3449683 | O20: 2.5027697 | P20: 4.3449683
A21: 15 | B21: =IF(ISNUMBER(SEARCH("bike",F21))+ISNUMBER(SEARCH("scooty",F21))>0,1,0) -> 1 | C21: =IF(ISNUMBER(SEARCH("car",F21))+ISNUMBER(SEARCH("Commercial vehicle",F21))>0,1,0) -> 1 | D21: 3 | E21: 40000 | F21: bikes, Commercial vehicle, Tractor | H21: Income_Numeric | I21: 1.4368953e-05 | J21: 8.4834026e-06 | K21: 1.6937724 | L21: 0.090862636 | M21: -2.294096e-06 | N21: 3.1032002e-05 | O21: -2.294096e-06 | P21: 3.1032002e-05
A22: 16.666667 | B22: =IF(ISNUMBER(SEARCH("bike",F22))+ISNUMBER(SEARCH("scooty",F22))>0,1,0) -> 0 | C22: =IF(ISNUMBER(SEARCH("car",F22))+ISNUMBER(SEARCH("Commercial vehicle",F22))>0,1,0) -> 1 | D22: 1 | E22: 40000 | F22: car
A23: 12.2 | B23: =IF(ISNUMBER(SEARCH("bike",F23))+ISNUMBER(SEARCH("scooty",F23))>0,1,0) -> 1 | C23: =IF(ISNUMBER(SEARCH("car",F23))+ISNUMBER(SEARCH("Commercial vehicle",F23))>0,1,0) -> 1 | D23: 3 | E23: 85000 | F23: bikes, car, Electric Vehicle
A24: 6 | B24: =IF(ISNUMBER(SEARCH("bike",F24))+ISNUMBER(SEARCH("scooty",F24))>0,1,0) -> 1 | C24: =IF(ISNUMBER(SEARCH("car",F24))+ISNUMBER(SEARCH("Commercial vehicle",F24))>0,1,0) -> 0 | D24: 1 | E24: 5000 | F24: bikes
A25: 2.8333333 | B25: =IF(ISNUMBER(SEARCH("bike",F25))+ISNUMBER(SEARCH("scooty",F25))>0,1,0) -> 1 | C25: =IF(ISNUMBER(SEARCH("car",F25))+ISNUMBER(SEARCH("Commercial vehicle",F25))>0,1,0) -> 0 | D25: 2 | E25: 20000 | F25: bikes, Scooty | H25: RESIDUAL OUTPUT
A26: 9.8 | B26: =IF(ISNUMBER(SEARCH("bike",F26))+ISNUMBER(SEARCH("scooty",F26))>0,1,0) -> 1 | C26: =IF(ISNUMBER(SEARCH("car",F26))+ISNUMBER(SEARCH("Commercial vehicle",F26))>0,1,0) -> 1 | D26: 2 | E26: 20000 | F26: Scooty, car
A27: 19.25 | B27: =IF(ISNUMBER(SEARCH("bike",F27))+ISNUMBER(SEARCH("scooty",F27))>0,1,0) -> 1 | C27: =IF(ISNUMBER(SEARCH("car",F27))+ISNUMBER(SEARCH("Commercial vehicle",F27))>0,1,0) -> 1 | D27: 2 | E27: 60000 | F27: bikes, car | H27: Observation | I27: Predicted Per_Capita_Vehicle_Fuel | J27: Residuals | K27: Standard Residuals
A28: 15.4 | B28: =IF(ISNUMBER(SEARCH("bike",F28))+ISNUMBER(SEARCH("scooty",F28))>0,1,0) -> 1 | C28: =IF(ISNUMBER(SEARCH("car",F28))+ISNUMBER(SEARCH("Commercial vehicle",F28))>0,1,0) -> 1 | D28: 2 | E28: 40000 | F28: bikes, Commercial vehicle | H28: 1 | I28: 1.8310591 | J28: 5.6689409 | K28: 1.3479637
A29: 6.6666667 | B29: =IF(ISNUMBER(SEARCH("bike",F29))+ISNUMBER(SEARCH("scooty",F29))>0,1,0) -> 1 | C29: =IF(ISNUMBER(SEARCH("car",F29))+ISNUMBER(SEARCH("Commercial vehicle",F29))>0,1,0) -> 0 | D29: 1 | E29: 20000 | F29: bikes | H29: 2 | I29: 10.893792 | J29: 8.1062079 | K29: 1.9274983
A30: 6.5 | B30: =IF(ISNUMBER(SEARCH("bike",F30))+ISNUMBER(SEARCH("scooty",F30))>0,1,0) -> 1 | C30: =IF(ISNUMBER(SEARCH("car",F30))+ISNUMBER(SEARCH("Commercial vehicle",F30))>0,1,0) -> 0 | D30: 1 | E30: 5000 | F30: bikes | H30: 3 | I30: 2.0465934 | J30: -0.37992677 | K30: -0.090339184
A31: 13.666667 | B31: =IF(ISNUMBER(SEARCH("bike",F31))+ISNUMBER(SEARCH("scooty",F31))>0,1,0) -> 1 | C31: =IF(ISNUMBER(SEARCH("car",F31))+ISNUMBER(SEARCH("Commercial vehicle",F31))>0,1,0) -> 1 | D31: 3 | E31: 60000 | F31: bikes, Scooty, car | H31: 4 | I31: 2.0465934 | J31: 1.9534066 | K31: 0.46448202
A32: 15 | B32: =IF(ISNUMBER(SEARCH("bike",F32))+ISNUMBER(SEARCH("scooty",F32))>0,1,0) -> 0 | C32: =IF(ISNUMBER(SEARCH("car",F32))+ISNUMBER(SEARCH("Commercial vehicle",F32))>0,1,0) -> 1 | D32: 1 | E32: 40000 | F32: car | H32: 5 | I32: 14.60504 | J32: 7.9949598 | K32: 1.9010457
A33: 18 | B33: =IF(ISNUMBER(SEARCH("bike",F33))+ISNUMBER(SEARCH("scooty",F33))>0,1,0) -> 1 | C33: =IF(ISNUMBER(SEARCH("car",F33))+ISNUMBER(SEARCH("Commercial vehicle",F33))>0,1,0) -> 1 | D33: 2 | E33: 85000 | F33: bikes, car | H33: 6 | I33: 1.8310591 | J33: 1.5022742 | K33: 0.35721153
A34: 13.8 | B34: =IF(ISNUMBER(SEARCH("bike",F34))+ISNUMBER(SEARCH("scooty",F34))>0,1,0) -> 1 | C34: =IF(ISNUMBER(SEARCH("car",F34))+ISNUMBER(SEARCH("Commercial vehicle",F34))>0,1,0) -> 1 | D34: 2 | E34: 20000 | F34: bikes, Commercial vehicle | H34: 7 | I34: 11.181171 | J34: 33.818829 | K34: 8.0414586
